Workbook
Name _: #N/A
Name _______________________________FR1: {"Lpor",#N/A,FALSE,"Porta";"LRDOS1",#N/A,FALSE,"Rdos";"LRDOS2",#N/A,FALSE,"Rdos";"LBAL1",#N/A,FALSE,"Bala";"LTES1",#N/A,FALSE,"Teso"}
Name _______________________________FR1: {"Lpor",#N/A,FALSE,"Porta";"LRDOS1",#N/A,FALSE,"Rdos";"LRDOS2",#N/A,FALSE,"Rdos";"LBAL1",#N/A,FALSE,"Bala";"LTES1",#N/A,FALSE,"Teso"}
Name ______________________________FR1: {"Lpor",#N/A,FALSE,"Porta";"LRDOS1",#N/A,FALSE,"Rdos";"LRDOS2",#N/A,FALSE,"Rdos";"LBAL1",#N/A,FALSE,"Bala";"LTES1",#N/A,FALSE,"Teso"}
Name ______________________________FR1: {"Lpor",#N/A,FALSE,"Porta";"LRDOS1",#N/A,FALSE,"Rdos";"LRDOS2",#N/A,FALSE,"Rdos";"LBAL1",#N/A,FALSE,"Bala";"LTES1",#N/A,FALSE,"Teso"}
Name _____________________________FR1: {"Lpor",#N/A,FALSE,"Porta";"LRDOS1",#N/A,FALSE,"Rdos";"LRDOS2",#N/A,FALSE,"Rdos";"LBAL1",#N/A,FALSE,"Bala";"LTES1",#N/A,FALSE,"Teso"}
Name _____________________________FR1: {"Lpor",#N/A,FALSE,"Porta";"LRDOS1",#N/A,FALSE,"Rdos";"LRDOS2",#N/A,FALSE,"Rdos";"LBAL1",#N/A,FALSE,"Bala";"LTES1",#N/A,FALSE,"Teso"}
Name ____________________________FR1: {"Lpor",#N/A,FALSE,"Porta";"LRDOS1",#N/A,FALSE,"Rdos";"LRDOS2",#N/A,FALSE,"Rdos";"LBAL1",#N/A,FALSE,"Bala";"LTES1",#N/A,FALSE,"Teso"}
Name ____________________________FR1: {"Lpor",#N/A,FALSE,"Porta";"LRDOS1",#N/A,FALSE,"Rdos";"LRDOS2",#N/A,FALSE,"Rdos";"LBAL1",#N/A,FALSE,"Bala";"LTES1",#N/A,FALSE,"Teso"}
Name ___________________________FR1: {"Lpor",#N/A,FALSE,"Porta";"LRDOS1",#N/A,FALSE,"Rdos";"LRDOS2",#N/A,FALSE,"Rdos";"LBAL1",#N/A,FALSE,"Bala";"LTES1",#N/A,FALSE,"Teso"}
Name ___________________________FR1: {"Lpor",#N/A,FALSE,"Porta";"LRDOS1",#N/A,FALSE,"Rdos";"LRDOS2",#N/A,FALSE,"Rdos";"LBAL1",#N/A,FALSE,"Bala";"LTES1",#N/A,FALSE,"Teso"}
Name _________________________FR1: {"Lpor",#N/A,FALSE,"Porta";"LRDOS1",#N/A,FALSE,"Rdos";"LRDOS2",#N/A,FALSE,"Rdos";"LBAL1",#N/A,FALSE,"Bala";"LTES1",#N/A,FALSE,"Teso"}
Name _________________________FR1: {"Lpor",#N/A,FALSE,"Porta";"LRDOS1",#N/A,FALSE,"Rdos";"LRDOS2",#N/A,FALSE,"Rdos";"LBAL1",#N/A,FALSE,"Bala";"LTES1",#N/A,FALSE,"Teso"}
Name ________________________FR1: {"Lpor",#N/A,FALSE,"Porta";"LRDOS1",#N/A,FALSE,"Rdos";"LRDOS2",#N/A,FALSE,"Rdos";"LBAL1",#N/A,FALSE,"Bala";"LTES1",#N/A,FALSE,"Teso"}
Name ________________________FR1: {"Lpor",#N/A,FALSE,"Porta";"LRDOS1",#N/A,FALSE,"Rdos";"LRDOS2",#N/A,FALSE,"Rdos";"LBAL1",#N/A,FALSE,"Bala";"LTES1",#N/A,FALSE,"Teso"}
Name _______________________FR1: {"Lpor",#N/A,FALSE,"Porta";"LRDOS1",#N/A,FALSE,"Rdos";"LRDOS2",#N/A,FALSE,"Rdos";"LBAL1",#N/A,FALSE,"Bala";"LTES1",#N/A,FALSE,"Teso"}
Name _______________________FR1: {"Lpor",#N/A,FALSE,"Porta";"LRDOS1",#N/A,FALSE,"Rdos";"LRDOS2",#N/A,FALSE,"Rdos";"LBAL1",#N/A,FALSE,"Bala";"LTES1",#N/A,FALSE,"Teso"}
Name ______________________FR1: {"Lpor",#N/A,FALSE,"Porta";"LRDOS1",#N/A,FALSE,"Rdos";"LRDOS2",#N/A,FALSE,"Rdos";"LBAL1",#N/A,FALSE,"Bala";"LTES1",#N/A,FALSE,"Teso"}
Name ______________________FR1: {"Lpor",#N/A,FALSE,"Porta";"LRDOS1",#N/A,FALSE,"Rdos";"LRDOS2",#N/A,FALSE,"Rdos";"LBAL1",#N/A,FALSE,"Bala";"LTES1",#N/A,FALSE,"Teso"}
Name _____________________FR1: {"Lpor",#N/A,FALSE,"Porta";"LRDOS1",#N/A,FALSE,"Rdos";"LRDOS2",#N/A,FALSE,"Rdos";"LBAL1",#N/A,FALSE,"Bala";"LTES1",#N/A,FALSE,"Teso"}
Name _____________________FR1: {"Lpor",#N/A,FALSE,"Porta";"LRDOS1",#N/A,FALSE,"Rdos";"LRDOS2",#N/A,FALSE,"Rdos";"LBAL1",#N/A,FALSE,"Bala";"LTES1",#N/A,FALSE,"Teso"}
Name ____________________FR1: {"Lpor",#N/A,FALSE,"Porta";"LRDOS1",#N/A,FALSE,"Rdos";"LRDOS2",#N/A,FALSE,"Rdos";"LBAL1",#N/A,FALSE,"Bala";"LTES1",#N/A,FALSE,"Teso"}
Name ____________________FR1: {"Lpor",#N/A,FALSE,"Porta";"LRDOS1",#N/A,FALSE,"Rdos";"LRDOS2",#N/A,FALSE,"Rdos";"LBAL1",#N/A,FALSE,"Bala";"LTES1",#N/A,FALSE,"Teso"}
Name ___________________FR1: {"Lpor",#N/A,FALSE,"Porta";"LRDOS1",#N/A,FALSE,"Rdos";"LRDOS2",#N/A,FALSE,"Rdos";"LBAL1",#N/A,FALSE,"Bala";"LTES1",#N/A,FALSE,"Teso"}
Name ___________________FR1: {"Lpor",#N/A,FALSE,"Porta";"LRDOS1",#N/A,FALSE,"Rdos";"LRDOS2",#N/A,FALSE,"Rdos";"LBAL1",#N/A,FALSE,"Bala";"LTES1",#N/A,FALSE,"Teso"}
Name __________________FR1: {"Lpor",#N/A,FALSE,"Porta";"LRDOS1",#N/A,FALSE,"Rdos";"LRDOS2",#N/A,FALSE,"Rdos";"LBAL1",#N/A,FALSE,"Bala";"LTES1",#N/A,FALSE,"Teso"}
Name __________________FR1: {"Lpor",#N/A,FALSE,"Porta";"LRDOS1",#N/A,FALSE,"Rdos";"LRDOS2",#N/A,FALSE,"Rdos";"LBAL1",#N/A,FALSE,"Bala";"LTES1",#N/A,FALSE,"Teso"}
Name _________________FR1: {"Lpor",#N/A,FALSE,"Porta";"LRDOS1",#N/A,FALSE,"Rdos";"LRDOS2",#N/A,FALSE,"Rdos";"LBAL1",#N/A,FALSE,"Bala";"LTES1",#N/A,FALSE,"Teso"}
Name _________________FR1: {"Lpor",#N/A,FALSE,"Porta";"LRDOS1",#N/A,FALSE,"Rdos";"LRDOS2",#N/A,FALSE,"Rdos";"LBAL1",#N/A,FALSE,"Bala";"LTES1",#N/A,FALSE,"Teso"}
Name ________________FR1: {"Lpor",#N/A,FALSE,"Porta";"LRDOS1",#N/A,FALSE,"Rdos";"LRDOS2",#N/A,FALSE,"Rdos";"LBAL1",#N/A,FALSE,"Bala";"LTES1",#N/A,FALSE,"Teso"}
Name ________________FR1: {"Lpor",#N/A,FALSE,"Porta";"LRDOS1",#N/A,FALSE,"Rdos";"LRDOS2",#N/A,FALSE,"Rdos";"LBAL1",#N/A,FALSE,"Bala";"LTES1",#N/A,FALSE,"Teso"}
Name _______________FR1: {"Lpor",#N/A,FALSE,"Porta";"LRDOS1",#N/A,FALSE,"Rdos";"LRDOS2",#N/A,FALSE,"Rdos";"LBAL1",#N/A,FALSE,"Bala";"LTES1",#N/A,FALSE,"Teso"}
Name _______________FR1: {"Lpor",#N/A,FALSE,"Porta";"LRDOS1",#N/A,FALSE,"Rdos";"LRDOS2",#N/A,FALSE,"Rdos";"LBAL1",#N/A,FALSE,"Bala";"LTES1",#N/A,FALSE,"Teso"}
Name ______________FR1: {"Lpor",#N/A,FALSE,"Porta";"LRDOS1",#N/A,FALSE,"Rdos";"LRDOS2",#N/A,FALSE,"Rdos";"LBAL1",#N/A,FALSE,"Bala";"LTES1",#N/A,FALSE,"Teso"}
Name ______________FR1: {"Lpor",#N/A,FALSE,"Porta";"LRDOS1",#N/A,FALSE,"Rdos";"LRDOS2",#N/A,FALSE,"Rdos";"LBAL1",#N/A,FALSE,"Bala";"LTES1",#N/A,FALSE,"Teso"}
Name _____________FR1: {"Lpor",#N/A,FALSE,"Porta";"LRDOS1",#N/A,FALSE,"Rdos";"LRDOS2",#N/A,FALSE,"Rdos";"LBAL1",#N/A,FALSE,"Bala";"LTES1",#N/A,FALSE,"Teso"}
Name _____________FR1: {"Lpor",#N/A,FALSE,"Porta";"LRDOS1",#N/A,FALSE,"Rdos";"LRDOS2",#N/A,FALSE,"Rdos";"LBAL1",#N/A,FALSE,"Bala";"LTES1",#N/A,FALSE,"Teso"}
Name ____________FR1: {"Lpor",#N/A,FALSE,"Porta";"LRDOS1",#N/A,FALSE,"Rdos";"LRDOS2",#N/A,FALSE,"Rdos";"LBAL1",#N/A,FALSE,"Bala";"LTES1",#N/A,FALSE,"Teso"}
Name ____________FR1: {"Lpor",#N/A,FALSE,"Porta";"LRDOS1",#N/A,FALSE,"Rdos";"LRDOS2",#N/A,FALSE,"Rdos";"LBAL1",#N/A,FALSE,"Bala";"LTES1",#N/A,FALSE,"Teso"}
Name ___________FR1: {"Lpor",#N/A,FALSE,"Porta";"LRDOS1",#N/A,FALSE,"Rdos";"LRDOS2",#N/A,FALSE,"Rdos";"LBAL1",#N/A,FALSE,"Bala";"LTES1",#N/A,FALSE,"Teso"}
Name ___________FR1: {"Lpor",#N/A,FALSE,"Porta";"LRDOS1",#N/A,FALSE,"Rdos";"LRDOS2",#N/A,FALSE,"Rdos";"LBAL1",#N/A,FALSE,"Bala";"LTES1",#N/A,FALSE,"Teso"}
Name __________A330: {"Lpor",#N/A,FALSE,"Porta";"LRDOS1",#N/A,FALSE,"Rdos";"LRDOS2",#N/A,FALSE,"Rdos";"LBAL1",#N/A,FALSE,"Bala";"LTES1",#N/A,FALSE,"Teso"}
Name __________A330: {"Lpor",#N/A,FALSE,"Porta";"LRDOS1",#N/A,FALSE,"Rdos";"LRDOS2",#N/A,FALSE,"Rdos";"LBAL1",#N/A,FALSE,"Bala";"LTES1",#N/A,FALSE,"Teso"}
Name __________FR1: {"Lpor",#N/A,FALSE,"Porta";"LRDOS1",#N/A,FALSE,"Rdos";"LRDOS2",#N/A,FALSE,"Rdos";"LBAL1",#N/A,FALSE,"Bala";"LTES1",#N/A,FALSE,"Teso"}
Name __________FR1: {"Lpor",#N/A,FALSE,"Porta";"LRDOS1",#N/A,FALSE,"Rdos";"LRDOS2",#N/A,FALSE,"Rdos";"LBAL1",#N/A,FALSE,"Bala";"LTES1",#N/A,FALSE,"Teso"}
Name _________A330: {"Lpor",#N/A,FALSE,"Porta";"LRDOS1",#N/A,FALSE,"Rdos";"LRDOS2",#N/A,FALSE,"Rdos";"LBAL1",#N/A,FALSE,"Bala";"LTES1",#N/A,FALSE,"Teso"}
Name _________A330: {"Lpor",#N/A,FALSE,"Porta";"LRDOS1",#N/A,FALSE,"Rdos";"LRDOS2",#N/A,FALSE,"Rdos";"LBAL1",#N/A,FALSE,"Bala";"LTES1",#N/A,FALSE,"Teso"}
Name _________FR1: {"Lpor",#N/A,FALSE,"Porta";"LRDOS1",#N/A,FALSE,"Rdos";"LRDOS2",#N/A,FALSE,"Rdos";"LBAL1",#N/A,FALSE,"Bala";"LTES1",#N/A,FALSE,"Teso"}
Name _________FR1: {"Lpor",#N/A,FALSE,"Porta";"LRDOS1",#N/A,FALSE,"Rdos";"LRDOS2",#N/A,FALSE,"Rdos";"LBAL1",#N/A,FALSE,"Bala";"LTES1",#N/A,FALSE,"Teso"}
Name ________A330: {"Lpor",#N/A,FALSE,"Porta";"LRDOS1",#N/A,FALSE,"Rdos";"LRDOS2",#N/A,FALSE,"Rdos";"LBAL1",#N/A,FALSE,"Bala";"LTES1",#N/A,FALSE,"Teso"}
Name ________A330: {"Lpor",#N/A,FALSE,"Porta";"LRDOS1",#N/A,FALSE,"Rdos";"LRDOS2",#N/A,FALSE,"Rdos";"LBAL1",#N/A,FALSE,"Bala";"LTES1",#N/A,FALSE,"Teso"}
Name ________FR1: {"Lpor",#N/A,FALSE,"Porta";"LRDOS1",#N/A,FALSE,"Rdos";"LRDOS2",#N/A,FALSE,"Rdos";"LBAL1",#N/A,FALSE,"Bala";"LTES1",#N/A,FALSE,"Teso"}
Name ________FR1: {"Lpor",#N/A,FALSE,"Porta";"LRDOS1",#N/A,FALSE,"Rdos";"LRDOS2",#N/A,FALSE,"Rdos";"LBAL1",#N/A,FALSE,"Bala";"LTES1",#N/A,FALSE,"Teso"}
Name _______A330: {"Lpor",#N/A,FALSE,"Porta";"LRDOS1",#N/A,FALSE,"Rdos";"LRDOS2",#N/A,FALSE,"Rdos";"LBAL1",#N/A,FALSE,"Bala";"LTES1",#N/A,FALSE,"Teso"}
Name _______A330: {"Lpor",#N/A,FALSE,"Porta";"LRDOS1",#N/A,FALSE,"Rdos";"LRDOS2",#N/A,FALSE,"Rdos";"LBAL1",#N/A,FALSE,"Bala";"LTES1",#N/A,FALSE,"Teso"}
Name _______FR1: {"Lpor",#N/A,FALSE,"Porta";"LRDOS1",#N/A,FALSE,"Rdos";"LRDOS2",#N/A,FALSE,"Rdos";"LBAL1",#N/A,FALSE,"Bala";"LTES1",#N/A,FALSE,"Teso"}
Name _______FR1: {"Lpor",#N/A,FALSE,"Porta";"LRDOS1",#N/A,FALSE,"Rdos";"LRDOS2",#N/A,FALSE,"Rdos";"LBAL1",#N/A,FALSE,"Bala";"LTES1",#N/A,FALSE,"Teso"}
Name ______A330: {"Lpor",#N/A,FALSE,"Porta";"LRDOS1",#N/A,FALSE,"Rdos";"LRDOS2",#N/A,FALSE,"Rdos";"LBAL1",#N/A,FALSE,"Bala";"LTES1",#N/A,FALSE,"Teso"}
Name ______A330: {"Lpor",#N/A,FALSE,"Porta";"LRDOS1",#N/A,FALSE,"Rdos";"LRDOS2",#N/A,FALSE,"Rdos";"LBAL1",#N/A,FALSE,"Bala";"LTES1",#N/A,FALSE,"Teso"}
Name ______FR1: {"Lpor",#N/A,FALSE,"Porta";"LRDOS1",#N/A,FALSE,"Rdos";"LRDOS2",#N/A,FALSE,"Rdos";"LBAL1",#N/A,FALSE,"Bala";"LTES1",#N/A,FALSE,"Teso"}

Sheet Seller Case >>

Sheet Phase II Outputs
A1: TS_Output_Annual
A2: Project Ardagh
A3: Phase II Seller
A4: EV (€'m): 1,020,452.3 | EqV (€'m): 726,982.2
A5: Tab_Check | F5: #VALUE!
A6: Master_Check | F6: #VALUE!
F8: Units | G8: Input_1 | H8: Input_2 | I8: Totals | BU8: Check
D9: Period Beginning | K9: 45292 | L9: 45658 | M9: 46023 | N9: 46388 | O9: 46753 | P9: 47119 | Q9: 47484 | R9: 47849 | S9: 48214 | T9: 48580 | U9: 48945 | V9: 49310 | W9: 49675 | X9: 50041 | Y9: 50406 | Z9: 50771 | AA9: 51136 | AB9: 51502 | AC9: 51867 | AD9: 52232 | AE9: 52597 | AF9: 52963 | AG9: 53328 | AH9: 53693 | AI9: 54058 | AJ9: 54424 | AK9: 54789 | AL9: 55154 | AM9: 55519 | AN9: 55885 | AO9: 56250 | AP9: 56615 | AQ9: 56980 | AR9: 57346 | AS9: 57711 | AT9: 58076 | AU9: 58441 | AV9: 58807 | AW9: 59172 | AX9: 59537 | AY9: 59902 | AZ9: 60268 | BA9: 60633 | BB9: 60998 | BC9: 61363 | BD9: 61729 | BE9: 62094 | BF9: 62459 | BG9: 62824 | BH9: 63190 | BI9: 63555 | BJ9: 63920 | BK9: 64285 | BL9: 64651 | BM9: 65016 | BN9: 65381 | BO9: 65746 | BP9: 66112 | BQ9: 66477 | BR9: 66842 | BS9: 67207
D10: Period End | K10: 45657 | L10: 46022 | M10: 46387 | N10: 46752 | O10: 47118 | P10: 47483 | Q10: 47848 | R10: 48213 | S10: 48579 | T10: 48944 | U10: 49309 | V10: 49674 | W10: 50040 | X10: 50405 | Y10: 50770 | Z10: 51135 | AA10: 51501 | AB10: 51866 | AC10: 52231 | AD10: 52596 | AE10: 52962 | AF10: 53327 | AG10: 53692 | AH10: 54057 | AI10: 54423 | AJ10: 54788 | AK10: 55153 | AL10: 55518 | AM10: 55884 | AN10: 56249 | AO10: 56614 | AP10: 56979 | AQ10: 57345 | AR10: 57710 | AS10: 58075 | AT10: 58440 | AU10: 58806 | AV10: 59171 | AW10: 59536 | AX10: 59901 | AY10: 60267 | AZ10: 60632 | BA10: 60997 | BB10: 61362 | BC10: 61728 | BD10: 62093 | BE10: 62458 | BF10: 62823 | BG10: 63189 | BH10: 63554 | BI10: 63919 | BJ10: 64284 | BK10: 64650 | BL10: 65015 | BM10: 65380 | BN10: 65745 | BO10: 66111 | BP10: 66476 | BQ10: 66841 | BR10: 67206 | BS10: 67572
D11: Year | K11: 2024 | L11: 2025 | M11: 2026 | N11: 2027 | O11: 2028 | P11: 2029 | Q11: 2030 | R11: 2031 | S11: 2032 | T11: 2033 | U11: 2034 | V11: 2035 | W11: 2036 | X11: 2037 | Y11: 2038 | Z11: 2039 | AA11: 2040 | AB11: 2041 | AC11: 2042 | AD11: 2043 | AE11: 2044 | AF11: 2045 | AG11: 2046 | AH11: 2047 | AI11: 2048 | AJ11: 2049 | AK11: 2050 | AL11: 2051 | AM11: 2052 | AN11: 2053 | AO11: 2054 | AP11: 2055 | AQ11: 2056 | AR11: 2057 | AS11: 2058 | AT11: 2059 | AU11: 2060 | AV11: 2061 | AW11: 2062 | AX11: 2063 | AY11: 2064 | AZ11: 2065 | BA11: 2066 | BB11: 2067 | BC11: 2068 | BD11: 2069 | BE11: 2070 | BF11: 2071 | BG11: 2072 | BH11: 2073 | BI11: 2074 | BJ11: 2075 | BK11: 2076 | BL11: 2077 | BM11: 2078 | BN11: 2079 | BO11: 2080 | BP11: 2081 | BQ11: 2082 | BR11: 2083 | BS11: 2084
D12: Periods | K12: 1 | L12: 1 | M12: 2 | N12: 2 | O12: 2 | P12: 2 | Q12: 2 | R12: 2 | S12: 2 | T12: 2 | U12: 2 | V12: 2 | W12: 2 | X12: 2 | Y12: 2 | Z12: 2 | AA12: 2 | AB12: 2 | AC12: 2 | AD12: 2 | AE12: 2 | AF12: 2 | AG12: 2 | AH12: 2 | AI12: 2 | AJ12: 2 | AK12: 2 | AL12: 2 | AM12: 2 | AN12: 2 | AO12: 2 | AP12: 2 | AQ12: 2 | AR12: 2 | AS12: 2 | AT12: 2 | AU12: 2 | AV12: 2 | AW12: 2 | AX12: 2 | AY12: 2 | AZ12: 2 | BA12: 2 | BB12: 2 | BC12: 2 | BD12: 2 | BE12: 2 | BF12: 2 | BG12: 2 | BH12: 2 | BI12: 2 | BJ12: 2 | BK12: 2 | BL12: 2 | BM12: 2 | BN12: 2 | BO12: 2 | BP12: 2 | BQ12: 2 | BR12: 2 | BS12: 1
D13: Days | K13: 366 | L13: 365 | M13: 365 | N13: 365 | O13: 366 | P13: 365 | Q13: 365 | R13: 365 | S13: 366 | T13: 365 | U13: 365 | V13: 365 | W13: 366 | X13: 365 | Y13: 365 | Z13: 365 | AA13: 366 | AB13: 365 | AC13: 365 | AD13: 365 | AE13: 366 | AF13: 365 | AG13: 365 | AH13: 365 | AI13: 366 | AJ13: 365 | AK13: 365 | AL13: 365 | AM13: 366 | AN13: 365 | AO13: 365 | AP13: 365 | AQ13: 366 | AR13: 365 | AS13: 365 | AT13: 365 | AU13: 366 | AV13: 365 | AW13: 365 | AX13: 365 | AY13: 366 | AZ13: 365 | BA13: 365 | BB13: 365 | BC13: 366 | BD13: 365 | BE13: 365 | BF13: 365 | BG13: 366 | BH13: 365 | BI13: 365 | BJ13: 365 | BK13: 366 | BL13: 365 | BM13: 365 | BN13: 365 | BO13: 366 | BP13: 365 | BQ13: 365 | BR13: 365 | BS13: 182
D14: Days vs full year | K14: 0 | L14: 0 | M14: 0 | N14: 0 | O14: 0 | P14: 0 | Q14: 0 | R14: 0 | S14: 0 | T14: 0 | U14: 0 | V14: 0 | W14: 0 | X14: 0 | Y14: 0 | Z14: 0 | AA14: 0 | AB14: 0 | AC14: 0 | AD14: 0 | AE14: 0 | AF14: 0 | AG14: 0 | AH14: 0 | AI14: 0 | AJ14: 0 | AK14: 0 | AL14: 0 | AM14: 0 | AN14: 0 | AO14: 0 | AP14: 0 | AQ14: 0 | AR14: 0 | AS14: 0 | AT14: 0 | AU14: 0 | AV14: 0 | AW14: 0 | AX14: 0 | AY14: 0 | AZ14: 0 | BA14: 0 | BB14: 0 | BC14: 0 | BD14: 0 | BE14: 0 | BF14: 0 | BG14: 0 | BH14: 0 | BI14: 0 | BJ14: 0 | BK14: 0 | BL14: 0 | BM14: 0 | BN14: 0 | BO14: 0 | BP14: 0 | BQ14: 0 | BR14: 0 | BS14: -184
D15: Year Counter | K15: 1 | L15: 2 | M15: 3 | N15: 4 | O15: 5 | P15: 6 | Q15: 7 | R15: 8 | S15: 9 | T15: 10 | U15: 11 | V15: 12 | W15: 13 | X15: 14 | Y15: 15 | Z15: 16 | AA15: 17 | AB15: 18 | AC15: 19 | AD15: 20 | AE15: 21 | AF15: 22 | AG15: 23 | AH15: 24 | AI15: 25 | AJ15: 26 | AK15: 27 | AL15: 28 | AM15: 29 | AN15: 30 | AO15: 31 | AP15: 32 | AQ15: 33 | AR15: 34 | AS15: 35 | AT15: 36 | AU15: 37 | AV15: 38 | AW15: 39 | AX15: 40 | AY15: 41 | AZ15: 42 | BA15: 43 | BB15: 44 | BC15: 45 | BD15: 46 | BE15: 47 | BF15: 48 | BG15: 49 | BH15: 50 | BI15: 51 | BJ15: 52 | BK15: 53 | BL15: 54 | BM15: 55 | BN15: 56 | BO15: 57 | BP15: 58 | BQ15: 59 | BR15: 60 | BS15: 61
B17: 1 | E17: Valuation Summary
K19: 1 | L19: 2 | M19: 3 | N19: 4 | O19: 5 | P19: 6 | Q19: 7 | R19: 8 | S19: 9 | T19: 10 | U19: 11 | V19: 12 | W19: 13 | X19: 14 | Y19: 15 | Z19: 16 | AA19: 17 | AB19: 18 | AC19: 19 | AD19: 20 | AE19: 21 | AF19: 22 | AG19: 23 | AH19: 24 | AI19: 25 | AJ19: 26 | AK19: 27 | AL19: 28 | AM19: 29 | AN19: 30 | AO19: 31 | AP19: 32 | AQ19: 33 | AR19: 34 | AS19: 35 | AT19: 36 | AU19: 37 | AV19: 38 | AW19: 39 | AX19: 40 | AY19: 41 | AZ19: 42 | BA19: 43 | BB19: 44 | BC19: 45 | BD19: 46 | BE19: 47 | BF19: 48 | BG19: 49 | BH19: 50 | BI19: 51 | BJ19: 52 | BK19: 53 | BL19: 54 | BM19: 55 | BN19: 56 | BO19: 57 | BP19: 58 | BQ19: 59 | BR19: 60 | BS19: 61
E28: MW | F28: 254
E30: Production | F30: 284
E32: PPA Revenue | F32: 356
E33: Merchant Revenue | F33: 357
E34: GoOs Revenue | F34: 358
E35: Total BESS Revenue | F35: 429
E36: Other Revenue Cost/Income | F36: 430
E38: EBITDA | F38: 24
E40: Production | F40: 284
E42: OPEX | F42: 662
C46: o | E46: MW
B50: GR_W1 | E50: GR_W1 | I50: 293 | K50: 293 | L50: 0 | M50: 0 | N50: 0 | O50: 0 | P50: 0 | Q50: 0 | R50: 0 | S50: 0 | T50: 0 | U50: 0 | V50: 0 | W50: 0 | X50: 0 | Y50: 0 | Z50: 0 | AA50: 0 | AB50: 0 | AC50: 0 | AD50: 0 | AE50: 0 | AF50: 0 | AG50: 0 | AH50: 0 | AI50: 0 | AJ50: 0 | AK50: 0 | AL50: 0 | AM50: 0 | AN50: 0 | AO50: 0 | AP50: 0 | AQ50: 0 | AR50: 0 | AS50: 0 | AT50: 0 | AU50: 0 | AV50: 0 | AW50: 0 | AX50: 0 | AY50: 0 | AZ50: 0 | BA50: 0 | BB50: 0 | BC50: 0 | BD50: 0 | BE50: 0 | BF50: 0 | BG50: 0 | BH50: 0 | BI50: 0 | BJ50: 0 | BK50: 0 | BL50: 0 | BM50: 0 | BN50: 0 | BO50: 0 | BP50: 0 | BQ50: 0 | BR50: 0 | BS50: 0
E51: GR_W2 | I51: 0 | K51: 0 | L51: 0 | M51: 0 | N51: 0 | O51: 0 | P51: 0 | Q51: 0 | R51: 0 | S51: 0 | T51: 0 | U51: 0 | V51: 0 | W51: 0 | X51: 0 | Y51: 0 | Z51: 0 | AA51: 0 | AB51: 0 | AC51: 0 | AD51: 0 | AE51: 0 | AF51: 0 | AG51: 0 | AH51: 0 | AI51: 0 | AJ51: 0 | AK51: 0 | AL51: 0 | AM51: 0 | AN51: 0 | AO51: 0 | AP51: 0 | AQ51: 0 | AR51: 0 | AS51: 0 | AT51: 0 | AU51: 0 | AV51: 0 | AW51: 0 | AX51: 0 | AY51: 0 | AZ51: 0 | BA51: 0 | BB51: 0 | BC51: 0 | BD51: 0 | BE51: 0 | BF51: 0 | BG51: 0 | BH51: 0 | BI51: 0 | BJ51: 0 | BK51: 0 | BL51: 0 | BM51: 0 | BN51: 0 | BO51: 0 | BP51: 0 | BQ51: 0 | BR51: 0 | BS51: 0
E52: GR_W3 | I52: 0 | K52: 0 | L52: 0 | M52: 0 | N52: 0 | O52: 0 | P52: 0 | Q52: 0 | R52: 0 | S52: 0 | T52: 0 | U52: 0 | V52: 0 | W52: 0 | X52: 0 | Y52: 0 | Z52: 0 | AA52: 0 | AB52: 0 | AC52: 0 | AD52: 0 | AE52: 0 | AF52: 0 | AG52: 0 | AH52: 0 | AI52: 0 | AJ52: 0 | AK52: 0 | AL52: 0 | AM52: 0 | AN52: 0 | AO52: 0 | AP52: 0 | AQ52: 0 | AR52: 0 | AS52: 0 | AT52: 0 | AU52: 0 | AV52: 0 | AW52: 0 | AX52: 0 | AY52: 0 | AZ52: 0 | BA52: 0 | BB52: 0 | BC52: 0 | BD52: 0 | BE52: 0 | BF52: 0 | BG52: 0 | BH52: 0 | BI52: 0 | BJ52: 0 | BK52: 0 | BL52: 0 | BM52: 0 | BN52: 0 | BO52: 0 | BP52: 0 | BQ52: 0 | BR52: 0 | BS52: 0
E53: GR_W4 | I53: 0 | K53: 0 | L53: 0 | M53: 0 | N53: 0 | O53: 0 | P53: 0 | Q53: 0 | R53: 0 | S53: 0 | T53: 0 | U53: 0 | V53: 0 | W53: 0 | X53: 0 | Y53: 0 | Z53: 0 | AA53: 0 | AB53: 0 | AC53: 0 | AD53: 0 | AE53: 0 | AF53: 0 | AG53: 0 | AH53: 0 | AI53: 0 | AJ53: 0 | AK53: 0 | AL53: 0 | AM53: 0 | AN53: 0 | AO53: 0 | AP53: 0 | AQ53: 0 | AR53: 0 | AS53: 0 | AT53: 0 | AU53: 0 | AV53: 0 | AW53: 0 | AX53: 0 | AY53: 0 | AZ53: 0 | BA53: 0 | BB53: 0 | BC53: 0 | BD53: 0 | BE53: 0 | BF53: 0 | BG53: 0 | BH53: 0 | BI53: 0 | BJ53: 0 | BK53: 0 | BL53: 0 | BM53: 0 | BN53: 0 | BO53: 0 | BP53: 0 | BQ53: 0 | BR53: 0 | BS53: 0
E54: GR_W5 | I54: 0 | K54: 0 | L54: 0 | M54: 0 | N54: 0 | O54: 0 | P54: 0 | Q54: 0 | R54: 0 | S54: 0 | T54: 0 | U54: 0 | V54: 0 | W54: 0 | X54: 0 | Y54: 0 | Z54: 0 | AA54: 0 | AB54: 0 | AC54: 0 | AD54: 0 | AE54: 0 | AF54: 0 | AG54: 0 | AH54: 0 | AI54: 0 | AJ54: 0 | AK54: 0 | AL54: 0 | AM54: 0 | AN54: 0 | AO54: 0 | AP54: 0 | AQ54: 0 | AR54: 0 | AS54: 0 | AT54: 0 | AU54: 0 | AV54: 0 | AW54: 0 | AX54: 0 | AY54: 0 | AZ54: 0 | BA54: 0 | BB54: 0 | BC54: 0 | BD54: 0 | BE54: 0 | BF54: 0 | BG54: 0 | BH54: 0 | BI54: 0 | BJ54: 0 | BK54: 0 | BL54: 0 | BM54: 0 | BN54: 0 | BO54: 0 | BP54: 0 | BQ54: 0 | BR54: 0 | BS54: 0
E55: IT_W1 | I55: 0 | K55: 0 | L55: 0 | M55: 0 | N55: 0 | O55: 0 | P55: 0 | Q55: 0 | R55: 0 | S55: 0 | T55: 0 | U55: 0 | V55: 0 | W55: 0 | X55: 0 | Y55: 0 | Z55: 0 | AA55: 0 | AB55: 0 | AC55: 0 | AD55: 0 | AE55: 0 | AF55: 0 | AG55: 0 | AH55: 0 | AI55: 0 | AJ55: 0 | AK55: 0 | AL55: 0 | AM55: 0 | AN55: 0 | AO55: 0 | AP55: 0 | AQ55: 0 | AR55: 0 | AS55: 0 | AT55: 0 | AU55: 0 | AV55: 0 | AW55: 0 | AX55: 0 | AY55: 0 | AZ55: 0 | BA55: 0 | BB55: 0 | BC55: 0 | BD55: 0 | BE55: 0 | BF55: 0 | BG55: 0 | BH55: 0 | BI55: 0 | BJ55: 0 | BK55: 0 | BL55: 0 | BM55: 0 | BN55: 0 | BO55: 0 | BP55: 0 | BQ55: 0 | BR55: 0 | BS55: 0
E56: IT_W2 | I56: 0 | K56: 0 | L56: 0 | M56: 0 | N56: 0 | O56: 0 | P56: 0 | Q56: 0 | R56: 0 | S56: 0 | T56: 0 | U56: 0 | V56: 0 | W56: 0 | X56: 0 | Y56: 0 | Z56: 0 | AA56: 0 | AB56: 0 | AC56: 0 | AD56: 0 | AE56: 0 | AF56: 0 | AG56: 0 | AH56: 0 | AI56: 0 | AJ56: 0 | AK56: 0 | AL56: 0 | AM56: 0 | AN56: 0 | AO56: 0 | AP56: 0 | AQ56: 0 | AR56: 0 | AS56: 0 | AT56: 0 | AU56: 0 | AV56: 0 | AW56: 0 | AX56: 0 | AY56: 0 | AZ56: 0 | BA56: 0 | BB56: 0 | BC56: 0 | BD56: 0 | BE56: 0 | BF56: 0 | BG56: 0 | BH56: 0 | BI56: 0 | BJ56: 0 | BK56: 0 | BL56: 0 | BM56: 0 | BN56: 0 | BO56: 0 | BP56: 0 | BQ56: 0 | BR56: 0 | BS56: 0
E57: IT_W3 | I57: 0 | K57: 0 | L57: 0 | M57: 0 | N57: 0 | O57: 0 | P57: 0 | Q57: 0 | R57: 0 | S57: 0 | T57: 0 | U57: 0 | V57: 0 | W57: 0 | X57: 0 | Y57: 0 | Z57: 0 | AA57: 0 | AB57: 0 | AC57: 0 | AD57: 0 | AE57: 0 | AF57: 0 | AG57: 0 | AH57: 0 | AI57: 0 | AJ57: 0 | AK57: 0 | AL57: 0 | AM57: 0 | AN57: 0 | AO57: 0 | AP57: 0 | AQ57: 0 | AR57: 0 | AS57: 0 | AT57: 0 | AU57: 0 | AV57: 0 | AW57: 0 | AX57: 0 | AY57: 0 | AZ57: 0 | BA57: 0 | BB57: 0 | BC57: 0 | BD57: 0 | BE57: 0 | BF57: 0 | BG57: 0 | BH57: 0 | BI57: 0 | BJ57: 0 | BK57: 0 | BL57: 0 | BM57: 0 | BN57: 0 | BO57: 0 | BP57: 0 | BQ57: 0 | BR57: 0 | BS57: 0
E58: IT_W4 | I58: 0 | K58: 0 | L58: 0 | M58: 0 | N58: 0 | O58: 0 | P58: 0 | Q58: 0 | R58: 0 | S58: 0 | T58: 0 | U58: 0 | V58: 0 | W58: 0 | X58: 0 | Y58: 0 | Z58: 0 | AA58: 0 | AB58: 0 | AC58: 0 | AD58: 0 | AE58: 0 | AF58: 0 | AG58: 0 | AH58: 0 | AI58: 0 | AJ58: 0 | AK58: 0 | AL58: 0 | AM58: 0 | AN58: 0 | AO58: 0 | AP58: 0 | AQ58: 0 | AR58: 0 | AS58: 0 | AT58: 0 | AU58: 0 | AV58: 0 | AW58: 0 | AX58: 0 | AY58: 0 | AZ58: 0 | BA58: 0 | BB58: 0 | BC58: 0 | BD58: 0 | BE58: 0 | BF58: 0 | BG58: 0 | BH58: 0 | BI58: 0 | BJ58: 0 | BK58: 0 | BL58: 0 | BM58: 0 | BN58: 0 | BO58: 0 | BP58: 0 | BQ58: 0 | BR58: 0 | BS58: 0
E59: IT_W5 | I59: 0 | K59: 0 | L59: 0 | M59: 0 | N59: 0 | O59: 0 | P59: 0 | Q59: 0 | R59: 0 | S59: 0 | T59: 0 | U59: 0 | V59: 0 | W59: 0 | X59: 0 | Y59: 0 | Z59: 0 | AA59: 0 | AB59: 0 | AC59: 0 | AD59: 0 | AE59: 0 | AF59: 0 | AG59: 0 | AH59: 0 | AI59: 0 | AJ59: 0 | AK59: 0 | AL59: 0 | AM59: 0 | AN59: 0 | AO59: 0 | AP59: 0 | AQ59: 0 | AR59: 0 | AS59: 0 | AT59: 0 | AU59: 0 | AV59: 0 | AW59: 0 | AX59: 0 | AY59: 0 | AZ59: 0 | BA59: 0 | BB59: 0 | BC59: 0 | BD59: 0 | BE59: 0 | BF59: 0 | BG59: 0 | BH59: 0 | BI59: 0 | BJ59: 0 | BK59: 0 | BL59: 0 | BM59: 0 | BN59: 0 | BO59: 0 | BP59: 0 | BQ59: 0 | BR59: 0 | BS59: 0
E60: IT_W6 | I60: 0 | K60: 0 | L60: 0 | M60: 0 | N60: 0 | O60: 0 | P60: 0 | Q60: 0 | R60: 0 | S60: 0 | T60: 0 | U60: 0 | V60: 0 | W60: 0 | X60: 0 | Y60: 0 | Z60: 0 | AA60: 0 | AB60: 0 | AC60: 0 | AD60: 0 | AE60: 0 | AF60: 0 | AG60: 0 | AH60: 0 | AI60: 0 | AJ60: 0 | AK60: 0 | AL60: 0 | AM60: 0 | AN60: 0 | AO60: 0 | AP60: 0 | AQ60: 0 | AR60: 0 | AS60: 0 | AT60: 0 | AU60: 0 | AV60: 0 | AW60: 0 | AX60: 0 | AY60: 0 | AZ60: 0 | BA60: 0 | BB60: 0 | BC60: 0 | BD60: 0 | BE60: 0 | BF60: 0 | BG60: 0 | BH60: 0 | BI60: 0 | BJ60: 0 | BK60: 0 | BL60: 0 | BM60: 0 | BN60: 0 | BO60: 0 | BP60: 0 | BQ60: 0 | BR60: 0 | BS60: 0
E61: IT_W7 | I61: 0 | K61: 0 | L61: 0 | M61: 0 | N61: 0 | O61: 0 | P61: 0 | Q61: 0 | R61: 0 | S61: 0 | T61: 0 | U61: 0 | V61: 0 | W61: 0 | X61: 0 | Y61: 0 | Z61: 0 | AA61: 0 | AB61: 0 | AC61: 0 | AD61: 0 | AE61: 0 | AF61: 0 | AG61: 0 | AH61: 0 | AI61: 0 | AJ61: 0 | AK61: 0 | AL61: 0 | AM61: 0 | AN61: 0 | AO61: 0 | AP61: 0 | AQ61: 0 | AR61: 0 | AS61: 0 | AT61: 0 | AU61: 0 | AV61: 0 | AW61: 0 | AX61: 0 | AY61: 0 | AZ61: 0 | BA61: 0 | BB61: 0 | BC61: 0 | BD61: 0 | BE61: 0 | BF61: 0 | BG61: 0 | BH61: 0 | BI61: 0 | BJ61: 0 | BK61: 0 | BL61: 0 | BM61: 0 | BN61: 0 | BO61: 0 | BP61: 0 | BQ61: 0 | BR61: 0 | BS61: 0
E62: IT_W8 | I62: 0 | K62: 0 | L62: 0 | M62: 0 | N62: 0 | O62: 0 | P62: 0 | Q62: 0 | R62: 0 | S62: 0 | T62: 0 | U62: 0 | V62: 0 | W62: 0 | X62: 0 | Y62: 0 | Z62: 0 | AA62: 0 | AB62: 0 | AC62: 0 | AD62: 0 | AE62: 0 | AF62: 0 | AG62: 0 | AH62: 0 | AI62: 0 | AJ62: 0 | AK62: 0 | AL62: 0 | AM62: 0 | AN62: 0 | AO62: 0 | AP62: 0 | AQ62: 0 | AR62: 0 | AS62: 0 | AT62: 0 | AU62: 0 | AV62: 0 | AW62: 0 | AX62: 0 | AY62: 0 | AZ62: 0 | BA62: 0 | BB62: 0 | BC62: 0 | BD62: 0 | BE62: 0 | BF62: 0 | BG62: 0 | BH62: 0 | BI62: 0 | BJ62: 0 | BK62: 0 | BL62: 0 | BM62: 0 | BN62: 0 | BO62: 0 | BP62: 0 | BQ62: 0 | BR62: 0 | BS62: 0
... E80: PT_W2 | I80: 0 | K80: 0 | L80: 0 | M80: 0 | N80: 0 | O80: 0 | P80: 0 | Q80: 0 | R80: 0 | S80: 0 | T80: 0 | U80: 0 | V80: 0 | W80: 0 | X80: 0 | Y80: 0 | Z80: 0 | AA80: 0 | AB80: 0 | AC80: 0 | AD80: 0 | AE80: 0 | AF80: 0 | AG80: 0 | AH80: 0 | AI80: 0 | AJ80: 0 | AK80: 0 | AL80: 0 | AM80: 0 | AN80: 0 | AO80: 0 | AP80: 0 | AQ80: 0 | AR80: 0 | AS80: 0 | AT80: 0 | AU80: 0 | AV80: 0 | AW80: 0 | AX80: 0 | AY80: 0 | AZ80: 0 | BA80: 0 | BB80: 0 | BC80: 0 | BD80: 0 | BE80: 0 | BF80: 0 | BG80: 0 | BH80: 0 | BI80: 0 | BJ80: 0 | BK80: 0 | BL80: 0 | BM80: 0 | BN80: 0 | BO80: 0 | BP80: 0 | BQ80: 0 | BR80: 0 | BS80: 0
C88: o | E88: Production
B90: Gr_W1 | E90: Production | F90: MWh | I90: 21081504 | K90: 0 | L90: 0 | M90: 316353.52 | N90: 576625.82 | O90: 591561.46 | P90: 602631.95 | Q90: 604277.92 | R90: 607646.6 | S90: 613226.18 | T90: 612927.17 | U90: 614091.47 | V90: 613853.41 | W90: 613107.63 | X90: 612137.33 | Y90: 611262.77 | Z90: 611336.59 | AA90: 610297.99 | AB90: 609696.46 | AC90: 608803.6 | AD90: 607550.47 | AE90: 607669.93 | AF90: 606967.12 | AG90: 603259.53 | AH90: 599963.36 | AI90: 599082.99 | AJ90: 598150.79 | AK90: 597272.19 | AL90: 593594.48 | AM90: 590318.21 | AN90: 589450.24 | AO90: 588531.17 | AP90: 587664.96 | AQ90: 584016.97 | AR90: 580760.52 | AS90: 579904.88 | AT90: 578998.87 | AU90: 578998.87 | AV90: 379510.4 | AW90: 0 | AX90: 0 | AY90: 0 | AZ90: 0 | BA90: 0 | BB90: 0 | BC90: 0 | BD90: 0 | BE90: 0 | BF90: 0 | BG90: 0 | BH90: 0 | BI90: 0 | BJ90: 0 | BK90: 0 | BL90: 0 | BM90: 0 | BN90: 0 | BO90: 0 | BP90: 0 | BQ90: 0 | BR90: 0 | BS90: 0 | BU90: 0
B92: Gr_W2 | E92: Production | F92: MWh | I92: 2687137.1 | K92: 0 | L92: 0 | M92: 52778.88 | N92: 73842.438 | O92: 75613.485 | P92: 76875.148 | Q92: 76953.308 | R92: 77371.997 | S92: 78065.084 | T92: 78051.496 | U92: 78165.604 | V92: 78130.211 | W92: 78042.763 | X92: 77916.916 | Y92: 77807.93 | Z92: 77818.206 | AA92: 77694.041 | AB92: 77612.375 | AC92: 77498.804 | AD92: 77341.459 | AE92: 77354.691 | AF92: 77265.025 | AG92: 76620.938 | AH92: 75993.417 | AI92: 75881.99 | AJ92: 75763.83 | AK92: 75652.627 | AL92: 75187.551 | AM92: 74771.729 | AN92: 74661.871 | AO92: 74545.376 | AP92: 74435.741 | AQ92: 73974.427 | AR92: 73561.119 | AS92: 73452.822 | AT92: 73337.982 | AU92: 73337.982 | AV92: 43757.881 | AW92: 0 | AX92: 0 | AY92: 0 | AZ92: 0 | BA92: 0 | BB92: 0 | BC92: 0 | BD92: 0 | BE92: 0 | BF92: 0 | BG92: 0 | BH92: 0 | BI92: 0 | BJ92: 0 | BK92: 0 | BL92: 0 | BM92: 0 | BN92: 0 | BO92: 0 | BP92: 0 | BQ92: 0 | BR92: 0 | BS92: 0 | BU92: 0
B94: Gr_W3 | E94: Production | F94: MWh | I94: 2472418.5 | K94: 0 | L94: 0 | M94: 48207.753 | N94: 67936.683 | O94: 69577.564 | P94: 70734.321 | Q94: 70804.306 | R94: 71187.184 | S94: 71818.976 | T94: 71809.054 | U94: 71910.375 | V94: 71880.297 | W94: 71797.427 | X94: 71682.452 | Y94: 71581.387 | Z94: 71591.493 | AA94: 71479.557 | AB94: 71402.592 | AC94: 71298.778 | AD94: 71153.804 | AE94: 71164.647 | AF94: 71083.703 | AG94: 70500.39 | AH94: 69913.167 | AI94: 69811.314 | AJ94: 69701.949 | AK94: 69600.301 | AL94: 69178.345 | AM94: 68789.226 | AN94: 68688.808 | AO94: 68580.984 | AP94: 68480.769 | AQ94: 68062.243 | AR94: 67675.478 | AS94: 67576.486 | AT94: 67470.193 | AU94: 67470.193 | AV94: 40816.349 | AW94: 0 | AX94: 0 | AY94: 0 | AZ94: 0 | BA94: 0 | BB94: 0 | BC94: 0 | BD94: 0 | BE94: 0 | BF94: 0 | BG94: 0 | BH94: 0 | BI94: 0 | BJ94: 0 | BK94: 0 | BL94: 0 | BM94: 0 | BN94: 0 | BO94: 0 | BP94: 0 | BQ94: 0 | BR94: 0 | BS94: 0 | BU94: 0
B96: Gr_W4 | E96: Production | F96: MWh | I96: 3568607.6 | K96: 0 | L96: 0 | M96: 0 | N96: 0 | O96: 71513.887 | P96: 102484.59 | Q96: 102425.25 | R96: 102853.64 | S96: 103818.89 | T96: 103769.79 | U96: 103870.69 | V96: 103885.14 | W96: 103752.35 | X96: 103584.1 | Y96: 103440.21 | Z96: 103401 | AA96: 103277.23 | AB96: 103177.43 | AC96: 103020.14 | AD96: 102809.81 | AE96: 102784.05 | AF96: 102709.42 | AG96: 102555.99 | AH96: 102502.66 | AI96: 100870.98 | AJ96: 100720.14 | AK96: 100566.13 | AL96: 100415.6 | AM96: 100363.28 | AN96: 99249.152 | AO96: 99100.438 | AP96: 98948.599 | AQ96: 98800.186 | AR96: 98748.602 | AS96: 97642.035 | AT96: 97495.433 | AU96: 97444.48 | AV96: 97444.48 | AW96: 97444.48 | AX96: 51717.285 | AY96: 0 | AZ96: 0 | BA96: 0 | BB96: 0 | BC96: 0 | BD96: 0 | BE96: 0 | BF96: 0 | BG96: 0 | BH96: 0 | BI96: 0 | BJ96: 0 | BK96: 0 | BL96: 0 | BM96: 0 | BN96: 0 | BO96: 0 | BP96: 0 | BQ96: 0 | BR96: 0 | BS96: 0 | BU96: 0
B98: Gr_W5 | E98: Production | F98: MWh | I98: 1372276.6 | K98: 0 | L98: 0 | M98: 0 | N98: 0 | O98: 18406.272 | P98: 39098.36 | Q98: 39276.387 | R98: 39460.839 | S98: 39812.085 | T98: 39792.045 | U98: 39851.208 | V98: 39837.493 | W98: 39785.262 | X98: 39722.028 | Y98: 39665.548 | Z98: 39671.078 | AA98: 39604.413 | AB98: 39564.783 | AC98: 39505.773 | AD98: 39423.804 | AE98: 39434.382 | AF98: 39386.601 | AG98: 39326.441 | AH98: 39326.441 | AI98: 38984.738 | AJ98: 38622.442 | AK98: 38564.664 | AL98: 38505.64 | AM98: 38505.64 | AN98: 38260.497 | AO98: 38001.306 | AP98: 37944.342 | AQ98: 37886.151 | AR98: 37886.151 | AS98: 37642.955 | AT98: 37385.807 | AU98: 37385.807 | AV98: 37385.807 | AW98: 37385.807 | AX98: 31977.564 | AY98: 0 | AZ98: 0 | BA98: 0 | BB98: 0 | BC98: 0 | BD98: 0 | BE98: 0 | BF98: 0 | BG98: 0 | BH98: 0 | BI98: 0 | BJ98: 0 | BK98: 0 | BL98: 0 | BM98: 0 | BN98: 0 | BO98: 0 | BP98: 0 | BQ98: 0 | BR98: 0 | BS98: 0 | BU98: 0
C100: 0 | E100: Greece | I100: 31181944 | K100: 0 | L100: 0 | M100: 417340.15 | N100: 718404.94 | O100: 826672.67 | P100: 891824.36 | Q100: 893737.18 | R100: 898520.26 | S100: 906741.21 | T100: 906349.56 | U100: 907889.35 | V100: 907586.55 | W100: 906485.43 | X100: 905042.83 | Y100: 903757.85 | Z100: 903818.37 | AA100: 902353.24 | AB100: 901453.64 | AC100: 900127.1 | AD100: 898279.35 | AE100: 898407.7 | AF100: 897411.87 | AG100: 892263.28 | AH100: 887699.05 | AI100: 884632.01 | AJ100: 882959.15 | AK100: 881655.91 | AL100: 876881.61 | AM100: 872748.08 | AN100: 870310.57 | AO100: 868759.28 | AP100: 867474.41 | AQ100: 862739.98 | AR100: 858631.87 | AS100: 856219.18 | AT100: 854688.28 | AU100: 854637.33 | AV100: 598914.92 | AW100: 134830.29 | AX100: 83694.849 | AY100: 0 | AZ100: 0 | BA100: 0 | BB100: 0 | BC100: 0 | BD100: 0 | BE100: 0 | BF100: 0 | BG100: 0 | BH100: 0 | BI100: 0 | BJ100: 0 | BK100: 0 | BL100: 0 | BM100: 0 | BN100: 0 | BO100: 0 | BP100: 0 | BQ100: 0 | BR100: 0 | BS100: 0 | BU100: 0
B102: IT_W1 | E102: Production | F102: MWh | I102: 7756680.9 | K102: 0 | L102: 0 | M102: 0 | N102: 0 | O102: 0 | P102: 0 | Q102: 3225.0625 | R102: 224481.32 | S102: 224481.32 | T102: 224481.32 | U102: 224481.32 | V102: 224481.32 | W102: 224481.32 | X102: 224481.32 | Y102: 224481.32 | Z102: 224481.32 | AA102: 224481.32 | AB102: 224481.32 | AC102: 224481.32 | AD102: 224481.32 | AE102: 224481.32 | AF102: 224481.32 | AG102: 224481.32 | AH102: 224481.32 | AI102: 224481.32 | AJ102: 224481.32 | AK102: 223415.04 | AL102: 222236.51 | AM102: 222236.51 | AN102: 222236.51 | AO102: 222236.51 | AP102: 221170.22 | AQ102: 219991.7 | AR102: 219991.7 | AS102: 219991.7 | AT102: 219991.7 | AU102: 218925.41 | AV102: 217746.88 | AW102: 217746.88 | AX102: 217746.88 | AY102: 217746.88 | AZ102: 184899.62 | BA102: 0 | BB102: 0 | BC102: 0 | BD102: 0 | BE102: 0 | BF102: 0 | BG102: 0 | BH102: 0 | BI102: 0 | BJ102: 0 | BK102: 0 | BL102: 0 | BM102: 0 | BN102: 0 | BO102: 0 | BP102: 0 | BQ102: 0 | BR102: 0 | BS102: 0 | BU102: 0
B104: IT_W2 | E104: Production | F104: MWh | I104: 1291761.5 | K104: 0 | L104: 0 | M104: 0 | N104: 0 | O104: 0 | P104: 0 | Q104: 12433.19 | R104: 37366.565 | S104: 37366.565 | T104: 37366.565 | U104: 37366.565 | V104: 37366.565 | W104: 37366.565 | X104: 37366.565 | Y104: 37366.565 | Z104: 37366.565 | AA104: 37366.565 | AB104: 37366.565 | AC104: 37366.565 | AD104: 37366.565 | AE104: 37366.565 | AF104: 37366.565 | AG104: 37366.565 | AH104: 37366.565 | AI104: 37366.565 | AJ104: 37366.565 | AK104: 37189.074 | AL104: 36992.899 | AM104: 36992.899 | AN104: 36992.899 | AO104: 36992.899 | AP104: 36815.408 | AQ104: 36619.234 | AR104: 36619.234 | AS104: 36619.234 | AT104: 36619.234 | AU104: 36441.742 | AV104: 36245.568 | AW104: 36245.568 | AX104: 36245.568 | AY104: 36245.568 | AZ104: 19486.596 | BA104: 0 | BB104: 0 | BC104: 0 | BD104: 0 | BE104: 0 | BF104: 0 | BG104: 0 | BH104: 0 | BI104: 0 | BJ104: 0 | BK104: 0 | BL104: 0 | BM104: 0 | BN104: 0 | BO104: 0 | BP104: 0 | BQ104: 0 | BR104: 0 | BS104: 0 | BU104: 0
B106: IT_W3 | E106: Production | F106: MWh | I106: 5842898 | K106: 0 | L106: 0 | M106: 0 | N106: 0 | O106: 0 | P106: 0 | Q106: 0 | R106: 103616 | S106: 169685.14 | T106: 169685.14 | U106: 169685.14 | V106: 169685.14 | W106: 169685.14 | X106: 169685.14 | Y106: 169685.14 | Z106: 169685.14 | AA106: 169685.14 | AB106: 169685.14 | AC106: 169685.14 | AD106: 169685.14 | AE106: 169685.14 | AF106: 169685.14 | AG106: 169685.14 | AH106: 169685.14 | AI106: 169685.14 | AJ106: 169685.14 | AK106: 169685.14 | AL106: 167988.29 | AM106: 167988.29 | AN106: 167988.29 | AO106: 167988.29 | AP106: 167988.29 | AQ106: 166291.44 | AR106: 166291.44 | AS106: 166291.44 | AT106: 166291.44 | AU106: 166291.44 | AV106: 164594.58 | AW106: 164594.58 | AX106: 164594.58 | AY106: 164594.58 | AZ106: 164594.58 | BA106: 20892.851 | BB106: 0 | BC106: 0 | BD106: 0 | BE106: 0 | BF106: 0 | BG106: 0 | BH106: 0 | BI106: 0 | BJ106: 0 | BK106: 0 | BL106: 0 | BM106: 0 | BN106: 0 | BO106: 0 | BP106: 0 | BQ106: 0 | BR106: 0 | BS106: 0 | BU106: 0
B108: IT_W4 | E108: Production | F108: MWh | I108: 4294840.2 | K108: 0 | L108: 0 | M108: 0 | N108: 0 | O108: 0 | P108: 0 | Q108: 0 | R108: 26433.121 | S108: 124531.8 | T108: 124531.8 | U108: 124531.8 | V108: 124531.8 | W108: 124531.8 | X108: 124531.8 | Y108: 124531.8 | Z108: 124531.8 | AA108: 124531.8 | AB108: 124531.8 | AC108: 124531.8 | AD108: 124531.8 | AE108: 124531.8 | AF108: 124531.8 | AG108: 124531.8 | AH108: 124531.8 | AI108: 124531.8 | AJ108: 124531.8 | AK108: 124531.8 | AL108: 123940.27 | AM108: 123286.48 | AN108: 123286.48 | AO108: 123286.48 | AP108: 123286.48 | AQ108: 122694.95 | AR108: 122041.16 | AS108: 122041.16 | AT108: 122041.16 | AU108: 122041.16 | AV108: 121449.64 | AW108: 120795.85 | AX108: 120795.85 | AY108: 120795.85 | AZ108: 120795.85 | BA108: 69724.046 | BB108: 0 | BC108: 0 | BD108: 0 | BE108: 0 | BF108: 0 | BG108: 0 | BH108: 0 | BI108: 0 | BJ108: 0 | BK108: 0 | BL108: 0 | BM108: 0 | BN108: 0 | BO108: 0 | BP108: 0 | BQ108: 0 | BR108: 0 | BS108: 0 | BU108: 0
B110: IT_W5 | E110: Production | F110: MWh | I110: 3650416.3 | K110: 0 | L110: 0 | M110: 0 | N110: 0 | O110: 0 | P110: 0 | Q110: 0 | R110: 75978.859 | S110: 105902.07 | T110: 105902.07 | U110: 105902.07 | V110: 105902.07 | W110: 105902.07 | X110: 105902.07 | Y110: 105902.07 | Z110: 105902.07 | AA110: 105902.07 | AB110: 105902.07 | AC110: 105902.07 | AD110: 105902.07 | AE110: 105902.07 | AF110: 105902.07 | AG110: 105902.07 | AH110: 105902.07 | AI110: 105902.07 | AJ110: 105902.07 | AK110: 105902.07 | AL110: 104843.05 | AM110: 104843.05 | AN110: 104843.05 | AO110: 104843.05 | AP110: 104843.05 | AQ110: 103784.03 | AR110: 103784.03 | AS110: 103784.03 | AT110: 103784.03 | AU110: 103784.03 | AV110: 102725.01 | AW110: 102725.01 | AX110: 102725.01 | AY110: 102725.01 | AZ110: 102725.01 | BA110: 5537.7624 | BB110: 0 | BC110: 0 | BD110: 0 | BE110: 0 | BF110: 0 | BG110: 0 | BH110: 0 | BI110: 0 | BJ110: 0 | BK110: 0 | BL110: 0 | BM110: 0 | BN110: 0 | BO110: 0 | BP110: 0 | BQ110: 0 | BR110: 0 | BS110: 0 | BU110: 0
B112: IT_W6 | E112: Production | F112: MWh | I112: 1348713.6 | K112: 0 | L112: 0 | M112: 0 | N112: 0 | O112: 0 | P112: 0 | Q112: 12981.353 | R112: 39014.007 | S112: 39014.007 | T112: 39014.007 | U112: 39014.007 | V112: 39014.007 | W112: 39014.007 | X112: 39014.007 | Y112: 39014.007 | Z112: 39014.007 | AA112: 39014.007 | AB112: 39014.007 | AC112: 39014.007 | AD112: 39014.007 | AE112: 39014.007 | AF112: 39014.007 | AG112: 39014.007 | AH112: 39014.007 | AI112: 39014.007 | AJ112: 39014.007 | AK112: 38828.69 | AL112: 38623.867 | AM112: 38623.867 | AN112: 38623.867 | AO112: 38623.867 | AP112: 38438.55 | AQ112: 38233.727 | AR112: 38233.727 | AS112: 38233.727 | AT112: 38233.727 | AU112: 38048.41 | AV112: 37843.586 | AW112: 37843.586 | AX112: 37843.586 | AY112: 37843.586 | AZ112: 20345.734 | BA112: 0 | BB112: 0 | BC112: 0 | BD112: 0 | BE112: 0 | BF112: 0 | BG112: 0 | BH112: 0 | BI112: 0 | BJ112: 0 | BK112: 0 | BL112: 0 | BM112: 0 | BN112: 0 | BO112: 0 | BP112: 0 | BQ112: 0 | BR112: 0 | BS112: 0 | BU112: 0
B114: IT_W7 | E114: Production | F114: MWh | I114: 993843.67 | K114: 0 | L114: 0 | M114: 0 | N114: 0 | O114: 0 | P114: 0 | Q114: 14110.567 | R114: 28773.578 | S114: 28773.578 | T114: 28773.578 | U114: 28773.578 | V114: 28773.578 | W114: 28773.578 | X114: 28773.578 | Y114: 28773.578 | Z114: 28773.578 | AA114: 28773.578 | AB114: 28773.578 | AC114: 28773.578 | AD114: 28773.578 | AE114: 28773.578 | AF114: 28773.578 | AG114: 28773.578 | AH114: 28773.578 | AI114: 28773.578 | AJ114: 28773.578 | AK114: 28485.842 | AL114: 28485.842 | AM114: 28485.842 | AN114: 28485.842 | AO114: 28485.842 | AP114: 28198.106 | AQ114: 28198.106 | AR114: 28198.106 | AS114: 28198.106 | AT114: 28198.106 | AU114: 27910.37 | AV114: 27910.37 | AW114: 27910.37 | AX114: 27910.37 | AY114: 27910.37 | AZ114: 10063.528 | BA114: 0 | BB114: 0 | BC114: 0 | BD114: 0 | BE114: 0 | BF114: 0 | BG114: 0 | BH114: 0 | BI114: 0 | BJ114: 0 | BK114: 0 | BL114: 0 | BM114: 0 | BN114: 0 | BO114: 0 | BP114: 0 | BQ114: 0 | BR114: 0 | BS114: 0 | BU114: 0
B116: IT_W8 | E116: Production | F116: MWh | I116: 1998121.2 | K116: 0 | L116: 0 | M116: 0 | N116: 0 | O116: 0 | P116: 0 | Q116: 0 | R116: 0 | S116: 0 | T116: 41589.089 | U116: 57968.369 | V116: 57968.369 | W116: 57968.369 | X116: 57968.369 | Y116: 57968.369 | Z116: 57968.369 | AA116: 57968.369 | AB116: 57968.369 | AC116: 57968.369 | AD116: 57968.369 | AE116: 57968.369 | AF116: 57968.369 | AG116: 57968.369 | AH116: 57968.369 | AI116: 57968.369 | AJ116: 57968.369 | AK116: 57968.369 | AL116: 57968.369 | AM116: 57968.369 | AN116: 57388.686 | AO116: 57388.686 | AP116: 57388.686 | AQ116: 57388.686 | AR116: 57388.686 | AS116: 56809.002 | AT116: 56809.002 | AU116: 56809.002 | AV116: 56809.002 | AW116: 56809.002 | AX116: 56229.318 | AY116: 56229.318 | AZ116: 56229.318 | BA116: 56229.318 | BB116: 56229.318 | BC116: 2998.0256 | BD116: 0 | BE116: 0 | BF116: 0 | BG116: 0 | BH116: 0 | BI116: 0 | BJ116: 0 | BK116: 0 | BL116: 0 | BM116: 0 | BN116: 0 | BO116: 0 | BP116: 0 | BQ116: 0 | BR116: 0 | BS116: 0 | BU116: 0
B118: IT_S1 | E118: Production | F118: MWh | I118: 2863290.1 | K118: 0 | L118: 0 | M118: 0 | N118: 0 | O118: 0 | P118: 1137.7305 | Q118: 77692.328 | R118: 77016.237 | S118: 76746.723 | T118: 76478.537 | U118: 76211.096 | V118: 75944.591 | W118: 75678.827 | X118: 75414.372 | Y118: 75150.653 | Z118: 74887.856 | AA118: 74625.79 | AB118: 74365.015 | AC118: 74104.966 | AD118: 73845.825 | AE118: 73587.406 | AF118: 73330.26 | AG118: 73073.828 | AH118: 72818.294 | AI118: 72563.47 | AJ118: 72309.902 | AK118: 72057.039 | AL118: 71805.06 | AM118: 71553.782 | AN118: 71303.742 | AO118: 71054.398 | AP118: 70805.925 | AQ118: 70558.144 | AR118: 70311.583 | AS118: 70125.171 | AT118: 69667.019 | AU118: 68814.519 | AV118: 68334.004 | AW118: 67856.503 | AX118: 67382.339 | AY118: 66911.151 | AZ118: 66443.927 | BA118: 65979.634 | BB118: 65518.584 | BC118: 65060.429 | BD118: 54763.456 | BE118: 0 | BF118: 0 | BG118: 0 | BH118: 0 | BI118: 0 | BJ118: 0 | BK118: 0 | BL118: 0 | BM118: 0 | BN118: 0 | BO118: 0 | BP118: 0 | BQ118: 0 | BR118: 0 | BS118: 0 | BU118: 0
B120: IT_S2 | E120: Production | F120: MWh | I120: 1260284.2 | K120: 0 | L120: 0 | M120: 0 | N120: 0 | O120: 0 | P120: 0.48761254 | Q120: 34096.796 | R120: 33800.08 | S120: 33681.799 | T120: 33564.1 | U120: 33446.728 | V120: 33329.767 | W120: 33213.132 | X120: 33097.071 | Y120: 32981.332 | Z120: 32865.999 | AA120: 32750.986 | AB120: 32636.54 | AC120: 32522.412 | AD120: 32408.683 | AE120: 32295.271 | AF120: 32182.417 | AG120: 32069.877 | AH120: 31957.731 | AI120: 31845.897 | AJ120: 31734.613 | AK120: 31623.639 | AL120: 31513.053 | AM120: 31402.775 | AN120: 31293.04 | AO120: 31183.61 | AP120: 31074.563 | AQ120: 30965.82 | AR120: 30857.612 | AS120: 30775.801 | AT120: 30574.733 | AU120: 30200.596 | AV120: 29989.713 | AW120: 29780.152 | AX120: 29572.056 | AY120: 29365.266 | AZ120: 29160.215 | BA120: 28956.451 | BB120: 28754.111 | BC120: 28553.04 | BD120: 28206.218 | BE120: 0 | BF120: 0 | BG120: 0 | BH120: 0 | BI120: 0 | BJ120: 0 | BK120: 0 | BL120: 0 | BM120: 0 | BN120: 0 | BO120: 0 | BP120: 0 | BQ120: 0 | BR120: 0 | BS120: 0 | BU120: 0
B122: IT_S3 | E122: Production | F122: MWh | I122: 1299024.2 | K122: 0 | L122: 0 | M122: 0 | N122: 0 | O122: 0 | P122: 0.50260131 | Q122: 35144.901 | R122: 34839.064 | S122: 34717.147 | T122: 34595.83 | U122: 34474.851 | V122: 34354.294 | W122: 34234.073 | X122: 34114.445 | Y122: 33995.148 | Z122: 33876.27 | AA122: 33757.722 | AB122: 33639.757 | AC122: 33522.121 | AD122: 33404.897 | AE122: 33287.998 | AF122: 33171.675 | AG122: 33055.676 | AH122: 32940.082 | AI122: 32824.811 | AJ122: 32710.106 | AK122: 32595.721 | AL122: 32481.736 | AM122: 32368.068 | AN122: 32254.96 | AO122: 32142.166 | AP122: 32029.767 | AQ122: 31917.681 | AR122: 31806.147 | AS122: 31721.822 | AT122: 31514.572 | AU122: 31128.935 | AV122: 30911.569 | AW122: 30695.567 | AX122: 30481.074 | AY122: 30267.927 | AZ122: 30056.574 | BA122: 29846.546 | BB122: 29637.986 | BC122: 29430.735 | BD122: 29073.252 | BE122: 0 | BF122: 0 | BG122: 0 | BH122: 0 | BI122: 0 | BJ122: 0 | BK122: 0 | BL122: 0 | BM122: 0 | BN122: 0 | BO122: 0 | BP122: 0 | BQ122: 0 | BR122: 0 | BS122: 0 | BU122: 0
B124: IT_B1 | E124: Production | F124: MWh | I124: 0 | K124: 0 | L124: 0 | M124: 0 | N124: 0 | O124: 0 | P124: 0 | Q124: 0 | R124: 0 | S124: 0 | T124: 0 | U124: 0 | V124: 0 | W124: 0 | X124: 0 | Y124: 0 | Z124: 0 | AA124: 0 | AB124: 0 | AC124: 0 | AD124: 0 | AE124: 0 | AF124: 0 | AG124: 0 | AH124: 0 | AI124: 0 | AJ124: 0 | AK124: 0 | AL124: 0 | AM124: 0 | AN124: 0 | AO124: 0 | AP124: 0 | AQ124: 0 | AR124: 0 | AS124: 0 | AT124: 0 | AU124: 0 | AV124: 0 | AW124: 0 | AX124: 0 | AY124: 0 | AZ124: 0 | BA124: 0 | BB124: 0 | BC124: 0 | BD124: 0 | BE124: 0 | BF124: 0 | BG124: 0 | BH124: 0 | BI124: 0 | BJ124: 0 | BK124: 0 | BL124: 0 | BM124: 0 | BN124: 0 | BO124: 0 | BP124: 0 | BQ124: 0 | BR124: 0 | BS124: 0 | BU124: 0
... B128: IT_B3 | E128: Production | F128: MWh | I128: 0 | K128: 0 | L128: 0 | M128: 0 | N128: 0 | O128: 0 | P128: 0 | Q128: 0 | R128: 0 | S128: 0 | T128: 0 | U128: 0 | V128: 0 | W128: 0 | X128: 0 | Y128: 0 | Z128: 0 | AA128: 0 | AB128: 0 | AC128: 0 | AD128: 0 | AE128: 0 | AF128: 0 | AG128: 0 | AH128: 0 | AI128: 0 | AJ128: 0 | AK128: 0 | AL128: 0 | AM128: 0 | AN128: 0 | AO128: 0 | AP128: 0 | AQ128: 0 | AR128: 0 | AS128: 0 | AT128: 0 | AU128: 0 | AV128: 0 | AW128: 0 | AX128: 0 | AY128: 0 | AZ128: 0 | BA128: 0 | BB128: 0 | BC128: 0 | BD128: 0 | BE128: 0 | BF128: 0 | BG128: 0 | BH128: 0 | BI128: 0 | BJ128: 0 | BK128: 0 | BL128: 0 | BM128: 0 | BN128: 0 | BO128: 0 | BP128: 0 | BQ128: 0 | BR128: 0 | BS128: 0 | BU128: 0
E130: Italy | I130: 32599874 | K130: 0 | L130: 0 | M130: 0 | N130: 0 | O130: 0 | P130: 1138.7207 | Q130: 189684.2 | R130: 681318.84 | S130: 874900.15 | T130: 915982.03 | U130: 931855.52 | V130: 931351.5 | W130: 930848.88 | X130: 930348.74 | Y130: 929849.98 | Z130: 929352.97 | AA130: 928857.35 | AB130: 928364.16 | AC130: 927872.35 | AD130: 927382.25 | AE130: 926893.52 | AF130: 926407.2 | AG130: 925922.23 | AH130: 925438.95 | AI130: 924957.03 | AJ130: 924477.47 | AK130: 922282.42 | AL130: 916878.94 | AM130: 915749.93 | AN130: 914697.36 | AO130: 914225.79 | AP130: 912039.04 | AQ130: 906643.51 | AR130: 905523.42 | AS130: 904591.18 | AT130: 903724.72 | AU130: 900395.61 | AV130: 894559.92 | AW130: 893003.07 | AX130: 891526.63 | AY130: 890635.51 | AZ130: 804800.95 | BA130: 277166.61 | BB130: 180140 | BC130: 126042.23 | BD130: 112042.93 | BE130: 0 | BF130: 0 | BG130: 0 | BH130: 0 | BI130: 0 | BJ130: 0 | BK130: 0 | BL130: 0 | BM130: 0 | BN130: 0 | BO130: 0 | BP130: 0 | BQ130: 0 | BR130: 0 | BS130: 0 | BU130: 0
B132: IE_S1 | E132: Production | F132: MWh | I132: 3331401.2 | K132: 0 | L132: 0 | M132: 0 | N132: 0 | O132: 0 | P132: 89416.744 | Q132: 89672.051 | R132: 90243.603 | S132: 90213.016 | T132: 89897.771 | U132: 89661.483 | V132: 89347.943 | W132: 89035.277 | X132: 88724.147 | Y132: 88413.884 | Z132: 88104.706 | AA132: 87796.391 | AB132: 87489.59 | AC132: 87183.645 | AD132: 86878.769 | AE132: 86574.743 | AF132: 83856.59 | AG132: 83391.408 | AH132: 83185.463 | AI132: 82979.732 | AJ132: 82519.62 | AK132: 82570.151 | AL132: 81943.497 | AM132: 81656.742 | AN132: 81287.508 | AO132: 81254.035 | AP132: 80803.29 | AQ132: 80603.536 | AR132: 80487.312 | AS132: 80248.724 | AT132: 79108.483 | AU132: 78474.482 | AV132: 77926.511 | AW132: 77381.98 | AX132: 76841.254 | AY132: 76303.925 | AZ132: 75771.111 | BA132: 75241.641 | BB132: 74715.872 | BC132: 74193.405 | BD132: 1.1617292 | BE132: 0 | BF132: 0 | BG132: 0 | BH132: 0 | BI132: 0 | BJ132: 0 | BK132: 0 | BL132: 0 | BM132: 0 | BN132: 0 | BO132: 0 | BP132: 0 | BQ132: 0 | BR132: 0 | BS132: 0 | BU132: 0
B134: IE_S2 | E134: Production | F134: MWh | I134: 2238456.5 | K134: 0 | L134: 0 | M134: 0 | N134: 0 | O134: 0 | P134: 59418.845 | Q134: 61081.522 | R134: 60867.923 | S134: 60654.926 | T134: 60442.965 | U134: 60231.6 | V134: 60020.974 | W134: 59810.94 | X134: 59601.928 | Y134: 59393.504 | Z134: 59185.809 | AA134: 58978.697 | AB134: 58772.594 | AC134: 58567.07 | AD134: 58362.265 | AE134: 58158.035 | AF134: 56332.066 | AG134: 56019.572 | AH134: 55881.225 | AI134: 55743.026 | AJ134: 55433.934 | AK134: 55467.879 | AL134: 55046.914 | AM134: 54854.285 | AN134: 54606.242 | AO134: 54583.756 | AP134: 54280.96 | AQ134: 54146.777 | AR134: 54068.697 | AS134: 53909.964 | AT134: 53140.922 | AU134: 52715.042 | AV134: 52346.936 | AW134: 51981.149 | AX134: 51617.917 | AY134: 51256.976 | AZ134: 50899.051 | BA134: 50543.382 | BB134: 50190.197 | BC134: 49839.239 | BD134: 0.75591708 | BE134: 0 | BF134: 0 | BG134: 0 | BH134: 0 | BI134: 0 | BJ134: 0 | BK134: 0 | BL134: 0 | BM134: 0 | BN134: 0 | BO134: 0 | BP134: 0 | BQ134: 0 | BR134: 0 | BS134: 0 | BU134: 0
B136: IE_B1 | E136: Production | F136: MWh | I136: 0 | K136: 0 | L136: 0 | M136: 0 | N136: 0 | O136: 0 | P136: 0 | Q136: 0 | R136: 0 | S136: 0 | T136: 0 | U136: 0 | V136: 0 | W136: 0 | X136: 0 | Y136: 0 | Z136: 0 | AA136: 0 | AB136: 0 | AC136: 0 | AD136: 0 | AE136: 0 | AF136: 0 | AG136: 0 | AH136: 0 | AI136: 0 | AJ136: 0 | AK136: 0 | AL136: 0 | AM136: 0 | AN136: 0 | AO136: 0 | AP136: 0 | AQ136: 0 | AR136: 0 | AS136: 0 | AT136: 0 | AU136: 0 | AV136: 0 | AW136: 0 | AX136: 0 | AY136: 0 | AZ136: 0 | BA136: 0 | BB136: 0 | BC136: 0 | BD136: 0 | BE136: 0 | BF136: 0 | BG136: 0 | BH136: 0 | BI136: 0 | BJ136: 0 | BK136: 0 | BL136: 0 | BM136: 0 | BN136: 0 | BO136: 0 | BP136: 0 | BQ136: 0 | BR136: 0 | BS136: 0 | BU136: 0
B138: IE_B2 | E138: Production | F138: MWh | I138: 0 | K138: 0 | L138: 0 | M138: 0 | N138: 0 | O138: 0 | P138: 0 | Q138: 0 | R138: 0 | S138: 0 | T138: 0 | U138: 0 | V138: 0 | W138: 0 | X138: 0 | Y138: 0 | Z138: 0 | AA138: 0 | AB138: 0 | AC138: 0 | AD138: 0 | AE138: 0 | AF138: 0 | AG138: 0 | AH138: 0 | AI138: 0 | AJ138: 0 | AK138: 0 | AL138: 0 | AM138: 0 | AN138: 0 | AO138: 0 | AP138: 0 | AQ138: 0 | AR138: 0 | AS138: 0 | AT138: 0 | AU138: 0 | AV138: 0 | AW138: 0 | AX138: 0 | AY138: 0 | AZ138: 0 | BA138: 0 | BB138: 0 | BC138: 0 | BD138: 0 | BE138: 0 | BF138: 0 | BG138: 0 | BH138: 0 | BI138: 0 | BJ138: 0 | BK138: 0 | BL138: 0 | BM138: 0 | BN138: 0 | BO138: 0 | BP138: 0 | BQ138: 0 | BR138: 0 | BS138: 0 | BU138: 0
A140: c | E140: Ireland | I140: 5569857.7 | K140: 0 | L140: 0 | M140: 0 | N140: 0 | O140: 0 | P140: 148835.59 | Q140: 150753.57 | R140: 151111.53 | S140: 150867.94 | T140: 150340.74 | U140: 149893.08 | V140: 149368.92 | W140: 148846.22 | X140: 148326.08 | Y140: 147807.39 | Z140: 147290.52 | AA140: 146775.09 | AB140: 146262.18 | AC140: 145750.71 | AD140: 145241.03 | AE140: 144732.78 | AF140: 140188.66 | AG140: 139410.98 | AH140: 139066.69 | AI140: 138722.76 | AJ140: 137953.55 | AK140: 138038.03 | AL140: 136990.41 | AM140: 136511.03 | AN140: 135893.75 | AO140: 135837.79 | AP140: 135084.25 | AQ140: 134750.31 | AR140: 134556.01 | AS140: 134158.69 | AT140: 132249.41 | AU140: 131189.52 | AV140: 130273.45 | AW140: 129363.13 | AX140: 128459.17 | AY140: 127560.9 | AZ140: 126670.16 | BA140: 125785.02 | BB140: 124906.07 | BC140: 124032.64 | BD140: 1.9176463 | BE140: 0 | BF140: 0 | BG140: 0 | BH140: 0 | BI140: 0 | BJ140: 0 | BK140: 0 | BL140: 0 | BM140: 0 | BN140: 0 | BO140: 0 | BP140: 0 | BQ140: 0 | BR140: 0 | BS140: 0 | BU140: 0
B142: ES_W1 | E142: Production | F142: MWh | I142: 1883706.9 | K142: 0 | L142: 0 | M142: 0 | N142: 0 | O142: 0 | P142: 0 | Q142: 0 | R142: 755.63312 | S142: 52901.372 | T142: 53572.825 | U142: 54054.387 | V142: 54301.656 | W142: 54439.636 | X142: 54494.281 | Y142: 54535.948 | Z142: 54522.97 | AA142: 54520.237 | AB142: 54645.238 | AC142: 54645.238 | AD142: 54645.238 | AE142: 54645.238 | AF142: 54645.238 | AG142: 54645.238 | AH142: 54645.238 | AI142: 54645.238 | AJ142: 54645.238 | AK142: 54645.238 | AL142: 54385.673 | AM142: 54098.786 | AN142: 54098.786 | AO142: 54098.786 | AP142: 54098.786 | AQ142: 53839.221 | AR142: 53552.333 | AS142: 53552.333 | AT142: 53552.333 | AU142: 53552.333 | AV142: 53292.769 | AW142: 53005.881 | AX142: 53005.881 | AY142: 53005.881 | AZ142: 53005.881 | BA142: 45009.909 | BB142: 0 | BC142: 0 | BD142: 0 | BE142: 0 | BF142: 0 | BG142: 0 | BH142: 0 | BI142: 0 | BJ142: 0 | BK142: 0 | BL142: 0 | BM142: 0 | BN142: 0 | BO142: 0 | BP142: 0 | BQ142: 0 | BR142: 0 | BS142: 0 | BU142: 0
B144: ES_W2 | E144: Production | F144: MWh | I144: 1405896.9 | K144: 0 | L144: 0 | M144: 0 | N144: 0 | O144: 0 | P144: 0 | Q144: 0 | R144: 19266.633 | S144: 39518.869 | T144: 40020.465 | U144: 40380.205 | V144: 40564.923 | W144: 40667.997 | X144: 40708.819 | Y144: 40739.945 | Z144: 40730.25 | AA144: 40728.209 | AB144: 40821.588 | AC144: 40821.588 | AD144: 40821.588 | AE144: 40821.588 | AF144: 40821.588 | AG144: 40821.588 | AH144: 40821.588 | AI144: 40821.588 | AJ144: 40821.588 | AK144: 40821.588 | AL144: 40413.373 | AM144: 40413.373 | AN144: 40413.373 | AO144: 40413.373 | AP144: 40413.373 | AQ144: 40005.157 | AR144: 40005.157 | AS144: 40005.157 | AT144: 40005.157 | AU144: 40005.157 | AV144: 39596.941 | AW144: 39596.941 | AX144: 39596.941 | AY144: 39596.941 | AZ144: 39596.941 | BA144: 14277.307 | BB144: 0 | BC144: 0 | BD144: 0 | BE144: 0 | BF144: 0 | BG144: 0 | BH144: 0 | BI144: 0 | BJ144: 0 | BK144: 0 | BL144: 0 | BM144: 0 | BN144: 0 | BO144: 0 | BP144: 0 | BQ144: 0 | BR144: 0 | BS144: 0 | BU144: 0
B146: ES_S1 | E146: Production | F146: MWh | I146: 587556.63 | K146: 0 | L146: 0 | M146: 0 | N146: 0 | O146: 0 | P146: 0 | Q146: 0 | R146: 207.9484 | S146: 14331.519 | T146: 14737.429 | U146: 15003.279 | V146: 15215.169 | W146: 15352.768 | X146: 15368.427 | Y146: 15327.67 | Z146: 15269.944 | AA146: 15228.284 | AB146: 15252.166 | AC146: 15198.83 | AD146: 15145.681 | AE146: 15092.68 | AF146: 15039.939 | AG146: 14987.346 | AH146: 14934.936 | AI146: 14882.672 | AJ146: 14830.665 | AK146: 14778.803 | AL146: 14727.123 | AM146: 14675.586 | AN146: 14624.303 | AO146: 14573.163 | AP146: 14522.202 | AQ146: 14471.382 | AR146: 14420.813 | AS146: 14370.384 | AT146: 14320.132 | AU146: 14282.183 | AV146: 14188.212 | AW146: 14015.148 | AX146: 13917.214 | AY146: 13819.895 | AZ146: 13723.393 | BA146: 15096.239 | BB146: 14990.75 | BC146: 14878.711 | BD146: 14767.153 | BE146: 14663.963 | BF146: 12322.526 | BG146: 0 | BH146: 0 | BI146: 0 | BJ146: 0 | BK146: 0 | BL146: 0 | BM146: 0 | BN146: 0 | BO146: 0 | BP146: 0 | BQ146: 0 | BR146: 0 | BS146: 0 | BU146: 0
B148: ES_S2 | E148: Production | F148: MWh | I148: 4259437.5 | K148: 0 | L148: 0 | M148: 0 | N148: 0 | O148: 0 | P148: 0 | Q148: 0 | R148: 52262.226 | S148: 104987.95 | T148: 108250.97 | U148: 110048.78 | V148: 111476.67 | W148: 112395.2 | X148: 112477.71 | Y148: 112173.42 | Z148: 111752.86 | AA148: 111442.54 | AB148: 111581.77 | AC148: 111191.58 | AD148: 110802.75 | AE148: 110415 | AF148: 110029.16 | AG148: 109644.4 | AH148: 109260.98 | AI148: 108878.63 | AJ148: 108498.16 | AK148: 108118.75 | AL148: 107740.66 | AM148: 107363.63 | AN148: 106988.45 | AO148: 106614.32 | AP148: 106241.5 | AQ148: 105869.71 | AR148: 105499.76 | AS148: 105130.83 | AT148: 104763.2 | AU148: 104667.73 | AV148: 103074.48 | AW148: 102354.23 | AX148: 101639 | AY148: 100928.27 | AZ148: 100223.51 | BA148: 103337.43 | BB148: 102615.33 | BC148: 101848.4 | BD148: 101084.75 | BE148: 100378.4 | BF148: 35384.439 | BG148: 0 | BH148: 0 | BI148: 0 | BJ148: 0 | BK148: 0 | BL148: 0 | BM148: 0 | BN148: 0 | BO148: 0 | BP148: 0 | BQ148: 0 | BR148: 0 | BS148: 0 | BU148: 0
E150: Spain | I150: 8136597.9 | K150: 0 | L150: 0 | M150: 0 | N150: 0 | O150: 0 | P150: 0 | Q150: 0 | R150: 72492.44 | S150: 211739.71 | T150: 216581.69 | U150: 219486.65 | V150: 221558.42 | W150: 222855.6 | X150: 223049.23 | Y150: 222776.98 | Z150: 222276.03 | AA150: 221919.27 | AB150: 222300.77 | AC150: 221857.24 | AD150: 221415.26 | AE150: 220974.51 | AF150: 220535.93 | AG150: 220098.57 | AH150: 219662.74 | AI150: 219228.13 | AJ150: 218795.65 | AK150: 218364.38 | AL150: 217266.83 | AM150: 216551.38 | AN150: 216124.91 | AO150: 215699.64 | AP150: 215275.86 | AQ150: 214185.47 | AR150: 213478.06 | AS150: 213058.71 | AT150: 212640.82 | AU150: 212507.41 | AV150: 210152.41 | AW150: 208972.2 | AX150: 208159.04 | AY150: 207350.98 | AZ150: 206549.72 | BA150: 177720.89 | BB150: 117606.08 | BC150: 116727.11 | BD150: 115851.91 | BE150: 115042.36 | BF150: 47706.965 | BG150: 0 | BH150: 0 | BI150: 0 | BJ150: 0 | BK150: 0 | BL150: 0 | BM150: 0 | BN150: 0 | BO150: 0 | BP150: 0 | BQ150: 0 | BR150: 0 | BS150: 0 | BU150: 0
B152: PT_W1 | E152: Production | F152: MWh | I152: 1979265.6 | K152: 0 | L152: 0 | M152: 0 | N152: 0 | O152: 0 | P152: 0 | Q152: 0 | R152: 0 | S152: 0 | T152: 34702.902 | U152: 57118.065 | V152: 57290.851 | W152: 57436.279 | X152: 57480.196 | Y152: 57466.517 | Z152: 57408.922 | AA152: 57392.363 | AB152: 57480.196 | AC152: 57507.554 | AD152: 57568.029 | AE152: 57507.554 | AF152: 57595.387 | AG152: 57595.387 | AH152: 57568.029 | AI152: 57480.196 | AJ152: 57507.554 | AK152: 57595.387 | AL152: 57581.708 | AM152: 57551.47 | AN152: 57019.433 | AO152: 57005.891 | AP152: 56935.329 | AQ152: 56861.917 | AR152: 56932.478 | AS152: 56416.668 | AT152: 56330.592 | AU152: 56330.592 | AV152: 56330.592 | AW152: 56330.592 | AX152: 55755.79 | AY152: 55755.79 | AZ152: 55755.79 | BA152: 55755.79 | BB152: 55755.79 | BC152: 7157.9971 | BD152: 0 | BE152: 0 | BF152: 0 | BG152: 0 | BH152: 0 | BI152: 0 | BJ152: 0 | BK152: 0 | BL152: 0 | BM152: 0 | BN152: 0 | BO152: 0 | BP152: 0 | BQ152: 0 | BR152: 0 | BS152: 0 | BU152: 0
B154: PT_W2 | E154: Production | F154: MWh | I154: 2051084 | K154: 0 | L154: 0 | M154: 0 | N154: 0 | O154: 0 | P154: 0 | Q154: 0 | R154: 0 | S154: 0 | T154: 49195.6 | U154: 58955.484 | V154: 59133.957 | W154: 59312.43 | X154: 59371.92 | Y154: 59371.92 | Z154: 59312.43 | AA154: 59252.939 | AB154: 59371.92 | AC154: 59371.92 | AD154: 59490.902 | AE154: 59371.92 | AF154: 59490.902 | AG154: 59490.902 | AH154: 59490.902 | AI154: 59371.92 | AJ154: 59371.92 | AK154: 59490.902 | AL154: 59490.902 | AM154: 59431.411 | AN154: 58895.993 | AO154: 58895.993 | AP154: 58837.097 | AQ154: 58719.305 | AR154: 58778.201 | AS154: 58301.084 | AT154: 58184.482 | AU154: 58184.482 | AV154: 58184.482 | AW154: 58184.482 | AX154: 57590.763 | AY154: 57590.763 | AZ154: 57590.763 | BA154: 57590.763 | BB154: 57590.763 | BC154: 821.50813 | BD154: 0 | BE154: 0 | BF154: 0 | BG154: 0 | BH154: 0 | BI154: 0 | BJ154: 0 | BK154: 0 | BL154: 0 | BM154: 0 | BN154: 0 | BO154: 0 | BP154: 0 | BQ154: 0 | BR154: 0 | BS154: 0 | BU154: 0
E156: Portugal | I156: 4030349.6 | K156: 0 | L156: 0 | M156: 0 | N156: 0 | O156: 0 | P156: 0 | Q156: 0 | R156: 0 | S156: 0 | T156: 83898.502 | U156: 116073.55 | V156: 116424.81 | W156: 116748.71 | X156: 116852.12 | Y156: 116838.44 | Z156: 116721.35 | AA156: 116645.3 | AB156: 116852.12 | AC156: 116879.47 | AD156: 117058.93 | AE156: 116879.47 | AF156: 117086.29 | AG156: 117086.29 | AH156: 117058.93 | AI156: 116852.12 | AJ156: 116879.47 | AK156: 117086.29 | AL156: 117072.61 | AM156: 116982.88 | AN156: 115915.43 | AO156: 115901.88 | AP156: 115772.43 | AQ156: 115581.22 | AR156: 115710.68 | AS156: 114717.75 | AT156: 114515.07 | AU156: 114515.07 | AV156: 114515.07 | AW156: 114515.07 | AX156: 113346.55 | AY156: 113346.55 | AZ156: 113346.55 | BA156: 113346.55 | BB156: 113346.55 | BC156: 7979.5053 | BD156: 0 | BE156: 0 | BF156: 0 | BG156: 0 | BH156: 0 | BI156: 0 | BJ156: 0 | BK156: 0 | BL156: 0 | BM156: 0 | BN156: 0 | BO156: 0 | BP156: 0 | BQ156: 0 | BR156: 0 | BS156: 0 | BU156: 0
C159: o | E159: Revenue
B161: GR_W1 | E161: PPA Revenue | I161: 667760.83 | K161: 0 | L161: 0 | M161: 14592.562 | N161: 42670.31 | O161: 43775.548 | P161: 44594.764 | Q161: 44716.566 | R161: 44965.849 | S161: 45378.737 | T161: 45356.611 | U161: 45442.769 | V161: 45425.152 | W161: 45369.965 | X161: 45298.162 | Y161: 45233.445 | Z161: 45238.908 | AA161: 45162.051 | AB161: 24539.429 | AC161: 0 | AD161: 0 | AE161: 0 | AF161: 0 | AG161: 0 | AH161: 0 | AI161: 0 | AJ161: 0 | AK161: 0 | AL161: 0 | AM161: 0 | AN161: 0 | AO161: 0 | AP161: 0 | AQ161: 0 | AR161: 0 | AS161: 0 | AT161: 0 | AU161: 0 | AV161: 0 | AW161: 0 | AX161: 0 | AY161: 0 | AZ161: 0 | BA161: 0 | BB161: 0 | BC161: 0 | BD161: 0 | BE161: 0 | BF161: 0 | BG161: 0 | BH161: 0 | BI161: 0 | BJ161: 0 | BK161: 0 | BL161: 0 | BM161: 0 | BN161: 0 | BO161: 0 | BP161: 0 | BQ161: 0 | BR161: 0 | BS161: 0 | BU161: 0
B162: GR_W1 | E162: Merchant Revenue | F162: €'000 | I162: 1614312.2 | K162: 0 | L162: 0 | M162: 12806.804 | N162: 0 | O162: 0 | P162: 0 | Q162: 0 | R162: 0 | S162: 0 | T162: 0 | U162: 0 | V162: 0 | W162: 0 | X162: 0 | Y162: 0 | Z162: 0 | AA162: 0 | AB162: 31610.332 | AC162: 71444.951 | AD162: 71154.27 | AE162: 72146.824 | AF162: 74139.092 | AG162: 74976.18 | AH162: 75685.014 | AI162: 75566.51 | AJ162: 76667.86 | AK162: 76806.247 | AL162: 77360.875 | AM162: 78168.805 | AN162: 80439.973 | AO162: 82971.11 | AP162: 84719.909 | AQ162: 85444.157 | AR162: 86667.079 | AS162: 88606.232 | AT162: 88982.276 | AU162: 88667.416 | AV162: 59280.273 | AW162: 0 | AX162: 0 | AY162: 0 | AZ162: 0 | BA162: 0 | BB162: 0 | BC162: 0 | BD162: 0 | BE162: 0 | BF162: 0 | BG162: 0 | BH162: 0 | BI162: 0 | BJ162: 0 | BK162: 0 | BL162: 0 | BM162: 0 | BN162: 0 | BO162: 0 | BP162: 0 | BQ162: 0 | BR162: 0 | BS162: 0 | BU162: 0
B163: GR_W1 | E163: GoOs Revenue | F163: €'000 | I163: 55941.759 | K163: 0 | L163: 0 | M163: 100.14077 | N163: 0 | O163: 0 | P163: 0 | Q163: 0 | R163: 0 | S163: 0 | T163: 0 | U163: 0 | V163: 0 | W163: 0 | X163: 0 | Y163: 0 | Z163: 0 | AA163: 0 | AB163: 1189.2237 | AC163: 2655.6277 | AD163: 2659.5652 | AE163: 2668.8098 | AF163: 2673.7203 | AG163: 2664.5946 | AH163: 2703.0362 | AI163: 2705.5848 | AJ163: 2658.7215 | AK163: 2658.6778 | AL163: 2645.2428 | AM163: 2683.2556 | AN163: 2732.8965 | AO163: 2783.2081 | AP163: 2834.6939 | AQ163: 2873.4393 | AR163: 2914.5655 | AS163: 2968.4768 | AT163: 3023.1158 | AU163: 3083.5781 | AV163: 2061.5843 | AW163: 0 | AX163: 0 | AY163: 0 | AZ163: 0 | BA163: 0 | BB163: 0 | BC163: 0 | BD163: 0 | BE163: 0 | BF163: 0 | BG163: 0 | BH163: 0 | BI163: 0 | BJ163: 0 | BK163: 0 | BL163: 0 | BM163: 0 | BN163: 0 | BO163: 0 | BP163: 0 | BQ163: 0 | BR163: 0 | BS163: 0 | BU163: 0
B164: GR_W1 | E164: Total Wind / Solar Revenue | F164: €'000 | I164: 2338014.8 | K164: 0 | L164: 0 | M164: 27499.506 | N164: 42670.31 | O164: 43775.548 | P164: 44594.764 | Q164: 44716.566 | R164: 44965.849 | S164: 45378.737 | T164: 45356.611 | U164: 45442.769 | V164: 45425.152 | W164: 45369.965 | X164: 45298.162 | Y164: 45233.445 | Z164: 45238.908 | AA164: 45162.051 | AB164: 57338.985 | AC164: 74100.578 | AD164: 73813.835 | AE164: 74815.634 | AF164: 76812.812 | AG164: 77640.775 | AH164: 78388.05 | AI164: 78272.094 | AJ164: 79326.582 | AK164: 79464.925 | AL164: 80006.118 | AM164: 80852.061 | AN164: 83172.869 | AO164: 85754.318 | AP164: 87554.603 | AQ164: 88317.596 | AR164: 89581.644 | AS164: 91574.709 | AT164: 92005.392 | AU164: 91750.994 | AV164: 61341.857 | AW164: 0 | AX164: 0 | AY164: 0 | AZ164: 0 | BA164: 0 | BB164: 0 | BC164: 0 | BD164: 0 | BE164: 0 | BF164: 0 | BG164: 0 | BH164: 0 | BI164: 0 | BJ164: 0 | BK164: 0 | BL164: 0 | BM164: 0 | BN164: 0 | BO164: 0 | BP164: 0 | BQ164: 0 | BR164: 0 | BS164: 0 | BU164: 0
B165: GR_W1 | E165: Total BESS Revenue | F165: €'000 | I165: 0 | K165: 0 | L165: 0 | M165: 0 | N165: 0 | O165: 0 | P165: 0 | Q165: 0 | R165: 0 | S165: 0 | T165: 0 | U165: 0 | V165: 0 | W165: 0 | X165: 0 | Y165: 0 | Z165: 0 | AA165: 0 | AB165: 0 | AC165: 0 | AD165: 0 | AE165: 0 | AF165: 0 | AG165: 0 | AH165: 0 | AI165: 0 | AJ165: 0 | AK165: 0 | AL165: 0 | AM165: 0 | AN165: 0 | AO165: 0 | AP165: 0 | AQ165: 0 | AR165: 0 | AS165: 0 | AT165: 0 | AU165: 0 | AV165: 0 | AW165: 0 | AX165: 0 | AY165: 0 | AZ165: 0 | BA165: 0 | BB165: 0 | BC165: 0 | BD165: 0 | BE165: 0 | BF165: 0 | BG165: 0 | BH165: 0 | BI165: 0 | BJ165: 0 | BK165: 0 | BL165: 0 | BM165: 0 | BN165: 0 | BO165: 0 | BP165: 0 | BQ165: 0 | BR165: 0 | BS165: 0 | BU165: 0
B166: GR_W1 | E166: Other Revenue Cost/Income | F166: €'000 | I166: -34360.502 | K166: 0 | L166: 0 | M166: -525.36008 | N166: -1153.2516 | O166: -1183.1229 | P166: 6486.2301 | Q166: -1208.5558 | R166: -1215.2932 | S166: -1226.4524 | T166: -1225.8543 | U166: -1228.1829 | V166: -1227.7068 | W166: -1226.2153 | X166: -1224.2747 | Y166: -1222.5255 | Z166: -1222.6732 | AA166: -1220.596 | AB166: -1215.7287 | AC166: -1217.6072 | AD166: -1215.1009 | AE166: -1215.3399 | AF166: -1213.9342 | AG166: -1206.5191 | AH166: -1199.9267 | AI166: -1198.166 | AJ166: -1196.3016 | AK166: -1194.5444 | AL166: -1187.189 | AM166: -1180.6364 | AN166: -1178.9005 | AO166: -1177.0623 | AP166: -1175.3299 | AQ166: -1168.0339 | AR166: -1161.521 | AS166: -1159.8098 | AT166: -1157.9977 | AU166: -1157.9977 | AV166: -759.02081 | AW166: 0 | AX166: 0 | AY166: 0 | AZ166: 0 | BA166: 0 | BB166: 0 | BC166: 0 | BD166: 0 | BE166: 0 | BF166: 0 | BG166: 0 | BH166: 0 | BI166: 0 | BJ166: 0 | BK166: 0 | BL166: 0 | BM166: 0 | BN166: 0 | BO166: 0 | BP166: 0 | BQ166: 0 | BR166: 0 | BS166: 0 | BU166: 0
E167: GR_W1 | F167: €'000 | I167: 2303654.3 | K167: 0 | L167: 0 | M167: 26974.146 | N167: 41517.059 | O167: 42592.425 | P167: 51080.994 | Q167: 43508.011 | R167: 43750.555 | S167: 44152.285 | T167: 44130.756 | U167: 44214.586 | V167: 44197.446 | W167: 44143.749 | X167: 44073.888 | Y167: 44010.92 | Z167: 44016.234 | AA167: 43941.455 | AB167: 56123.256 | AC167: 72882.971 | AD167: 72598.734 | AE167: 73600.294 | AF167: 75598.878 | AG167: 76434.256 | AH167: 77188.123 | AI167: 77073.928 | AJ167: 78130.28 | AK167: 78270.38 | AL167: 78818.929 | AM167: 79671.424 | AN167: 81993.969 | AO167: 84577.255 | AP167: 86379.273 | AQ167: 87149.562 | AR167: 88420.123 | AS167: 90414.899 | AT167: 90847.394 | AU167: 90592.996 | AV167: 60582.837 | AW167: 0 | AX167: 0 | AY167: 0 | AZ167: 0 | BA167: 0 | BB167: 0 | BC167: 0 | BD167: 0 | BE167: 0 | BF167: 0 | BG167: 0 | BH167: 0 | BI167: 0 | BJ167: 0 | BK167: 0 | BL167: 0 | BM167: 0 | BN167: 0 | BO167: 0 | BP167: 0 | BQ167: 0 | BR167: 0 | BS167: 0 | BU167: 0
B169: GR_W2 | E169: PPA Revenue | I169: 85160.313 | K169: 0 | L169: 0 | M169: 1643.1206 | N169: 5316.6556 | O169: 5444.1709 | P169: 5535.0106 | Q169: 5540.6382 | R169: 5570.7838 | S169: 5620.686 | T169: 5619.7077 | U169: 5627.9235 | V169: 5625.3752 | W169: 5619.0789 | X169: 5610.018 | Y169: 5602.171 | Z169: 5602.9108 | AA169: 5593.9709 | AB169: 5588.091 | AC169: 0 | AD169: 0 | AE169: 0 | AF169: 0 | AG169: 0 | AH169: 0 | AI169: 0 | AJ169: 0 | AK169: 0 | AL169: 0 | AM169: 0 | AN169: 0 | AO169: 0 | AP169: 0 | AQ169: 0 | AR169: 0 | AS169: 0 | AT169: 0 | AU169: 0 | AV169: 0 | AW169: 0 | AX169: 0 | AY169: 0 | AZ169: 0 | BA169: 0 | BB169: 0 | BC169: 0 | BD169: 0 | BE169: 0 | BF169: 0 | BG169: 0 | BH169: 0 | BI169: 0 | BJ169: 0 | BK169: 0 | BL169: 0 | BM169: 0 | BN169: 0 | BO169: 0 | BP169: 0 | BQ169: 0 | BR169: 0 | BS169: 0 | BU169: 0
B170: GR_W2 | E170: Merchant Revenue | F170: €'000 | I170: 201554 | K170: 0 | L170: 0 | M170: 3169.6198 | N170: 0 | O170: 0 | P170: 0 | Q170: 0 | R170: 0 | S170: 0 | T170: 0 | U170: 0 | V170: 0 | W170: 0 | X170: 0 | Y170: 0 | Z170: 0 | AA170: 0 | AB170: 0 | AC170: 9094.7198 | AD170: 9057.9718 | AE170: 9184.0899 | AF170: 9437.6756 | AG170: 9522.8422 | AH170: 9586.5234 | AI170: 9571.5238 | AJ170: 9711.0141 | AK170: 9728.5534 | AL170: 9798.9031 | AM170: 9901.1289 | AN170: 10188.814 | AO170: 10509.405 | AP170: 10730.926 | AQ170: 10822.772 | AR170: 10977.549 | AS170: 11223.182 | AT170: 11270.8 | AU170: 11230.919 | AV170: 6835.0673 | AW170: 0 | AX170: 0 | AY170: 0 | AZ170: 0 | BA170: 0 | BB170: 0 | BC170: 0 | BD170: 0 | BE170: 0 | BF170: 0 | BG170: 0 | BH170: 0 | BI170: 0 | BJ170: 0 | BK170: 0 | BL170: 0 | BM170: 0 | BN170: 0 | BO170: 0 | BP170: 0 | BQ170: 0 | BR170: 0 | BS170: 0 | BU170: 0
B171: GR_W2 | E171: GoOs Revenue | F171: €'000 | I171: 6906.7339 | K171: 0 | L171: 0 | M171: 0 | N171: 0 | O171: 0 | P171: 0 | Q171: 0 | R171: 0 | S171: 0 | T171: 0 | U171: 0 | V171: 0 | W171: 0 | X171: 0 | Y171: 0 | Z171: 0 | AA171: 0 | AB171: 0 | AC171: 338.05313 | AD171: 338.5639 | AE171: 339.73206 | AF171: 340.35627 | AG171: 338.43434 | AH171: 342.37583 | AI171: 342.69903 | AJ171: 336.76278 | AK171: 336.75762 | AL171: 335.05927 | AM171: 339.87036 | AN171: 346.15843 | AO171: 352.53068 | AP171: 359.05245 | AQ171: 363.96378 | AR171: 369.16886 | AS171: 375.99787 | AT171: 382.91821 | AU171: 390.57658 | AV171: 237.70247 | AW171: 0 | AX171: 0 | AY171: 0 | AZ171: 0 | BA171: 0 | BB171: 0 | BC171: 0 | BD171: 0 | BE171: 0 | BF171: 0 | BG171: 0 | BH171: 0 | BI171: 0 | BJ171: 0 | BK171: 0 | BL171: 0 | BM171: 0 | BN171: 0 | BO171: 0 | BP171: 0 | BQ171: 0 | BR171: 0 | BS171: 0 | BU171: 0
B172: GR_W2 | E172: Total Wind / Solar Revenue | F172: €'000 | I172: 293621.05 | K172: 0 | L172: 0 | M172: 4812.7404 | N172: 5316.6556 | O172: 5444.1709 | P172: 5535.0106 | Q172: 5540.6382 | R172: 5570.7838 | S172: 5620.686 | T172: 5619.7077 | U172: 5627.9235 | V172: 5625.3752 | W172: 5619.0789 | X172: 5610.018 | Y172: 5602.171 | Z172: 5602.9108 | AA172: 5593.9709 | AB172: 5588.091 | AC172: 9432.7729 | AD172: 9396.5357 | AE172: 9523.822 | AF172: 9778.0318 | AG172: 9861.2765 | AH172: 9928.8992 | AI172: 9914.2229 | AJ172: 10047.777 | AK172: 10065.311 | AL172: 10133.962 | AM172: 10240.999 | AN172: 10534.973 | AO172: 10861.936 | AP172: 11089.979 | AQ172: 11186.736 | AR172: 11346.718 | AS172: 11599.18 | AT172: 11653.718 | AU172: 11621.495 | AV172: 7072.7698 | AW172: 0 | AX172: 0 | AY172: 0 | AZ172: 0 | BA172: 0 | BB172: 0 | BC172: 0 | BD172: 0 | BE172: 0 | BF172: 0 | BG172: 0 | BH172: 0 | BI172: 0 | BJ172: 0 | BK172: 0 | BL172: 0 | BM172: 0 | BN172: 0 | BO172: 0 | BP172: 0 | BQ172: 0 | BR172: 0 | BS172: 0 | BU172: 0
B173: GR_W2 | E173: Total BESS Revenue | F173: €'000 | I173: 0 | K173: 0 | L173: 0 | M173: 0 | N173: 0 | O173: 0 | P173: 0 | Q173: 0 | R173: 0 | S173: 0 | T173: 0 | U173: 0 | V173: 0 | W173: 0 | X173: 0 | Y173: 0 | Z173: 0 | AA173: 0 | AB173: 0 | AC173: 0 | AD173: 0 | AE173: 0 | AF173: 0 | AG173: 0 | AH173: 0 | AI173: 0 | AJ173: 0 | AK173: 0 | AL173: 0 | AM173: 0 | AN173: 0 | AO173: 0 | AP173: 0 | AQ173: 0 | AR173: 0 | AS173: 0 | AT173: 0 | AU173: 0 | AV173: 0 | AW173: 0 | AX173: 0 | AY173: 0 | AZ173: 0 | BA173: 0 | BB173: 0 | BC173: 0 | BD173: 0 | BE173: 0 | BF173: 0 | BG173: 0 | BH173: 0 | BI173: 0 | BJ173: 0 | BK173: 0 | BL173: 0 | BM173: 0 | BN173: 0 | BO173: 0 | BP173: 0 | BQ173: 0 | BR173: 0 | BS173: 0 | BU173: 0
B174: GR_W2 | E174: Other Revenue Cost/Income | F174: €'000 | I174: -8611.9607 | K174: 0 | L174: 0 | M174: -219.25696 | N174: -147.68488 | O174: -151.22697 | P174: -153.7503 | Q174: -153.90662 | R174: -154.74399 | S174: -156.13017 | T174: -156.10299 | U174: -156.33121 | V174: -156.26042 | W174: -156.08553 | X174: -155.83383 | Y174: -155.61586 | Z174: -155.63641 | AA174: -155.38808 | AB174: -108.01196 | AC174: -321.79761 | AD174: -317.88292 | AE174: -316.90938 | AF174: -318.13005 | AG174: -316.44188 | AH174: -314.38683 | AI174: -310.96398 | AJ174: -310.12766 | AK174: -307.30525 | AL174: -305.3751 | AM174: -303.94346 | AN174: -305.32374 | AO174: -307.09075 | AP174: -307.27148 | AQ174: -305.54885 | AR174: -304.72224 | AS174: -305.10564 | AT174: -302.67596 | AU174: -299.07596 | AV174: -239.91576 | AW174: 0 | AX174: 0 | AY174: 0 | AZ174: 0 | BA174: 0 | BB174: 0 | BC174: 0 | BD174: 0 | BE174: 0 | BF174: 0 | BG174: 0 | BH174: 0 | BI174: 0 | BJ174: 0 | BK174: 0 | BL174: 0 | BM174: 0 | BN174: 0 | BO174: 0 | BP174: 0 | BQ174: 0 | BR174: 0 | BS174: 0 | BU174: 0
E175: GR_W2 | F175: €'000 | I175: 285009.09 | K175: 0 | L175: 0 | M175: 4593.4834 | N175: 5168.9707 | O175: 5292.944 | P175: 5381.2603 | Q175: 5386.7316 | R175: 5416.0398 | S175: 5464.5559 | T175: 5463.6047 | U175: 5471.5923 | V175: 5469.1148 | W175: 5462.9934 | X175: 5454.1841 | Y175: 5446.5551 | Z175: 5447.2744 | AA175: 5438.5828 | AB175: 5480.0791 | AC175: 9110.9753 | AD175: 9078.6528 | AE175: 9206.9126 | AF175: 9459.9018 | AG175: 9544.8346 | AH175: 9614.5124 | AI175: 9603.2589 | AJ175: 9737.6492 | AK175: 9758.0058 | AL175: 9828.5872 | AM175: 9937.0558 | AN175: 10229.649 | AO175: 10554.845 | AP175: 10782.707 | AQ175: 10881.187 | AR175: 11041.996 | AS175: 11294.074 | AT175: 11351.042 | AU175: 11322.42 | AV175: 6832.854 | AW175: 0 | AX175: 0 | AY175: 0 | AZ175: 0 | BA175: 0 | BB175: 0 | BC175: 0 | BD175: 0 | BE175: 0 | BF175: 0 | BG175: 0 | BH175: 0 | BI175: 0 | BJ175: 0 | BK175: 0 | BL175: 0 | BM175: 0 | BN175: 0 | BO175: 0 | BP175: 0 | BQ175: 0 | BR175: 0 | BS175: 0 | BU175: 0
B177: GR_W3 | E177: PPA Revenue | I177: 78318.613 | K177: 0 | L177: 0 | M177: 1480.6687 | N177: 4891.4412 | O177: 5009.5846 | P177: 5092.8711 | Q177: 5097.91 | R177: 5125.4773 | S177: 5170.9663 | T177: 5170.2519 | U177: 5177.547 | V177: 5175.3814 | W177: 5169.4147 | X177: 5161.1366 | Y177: 5153.8598 | Z177: 5154.5875 | AA177: 5146.5281 | AB177: 5140.9866 | AC177: 0 | AD177: 0 | AE177: 0 | AF177: 0 | AG177: 0 | AH177: 0 | AI177: 0 | AJ177: 0 | AK177: 0 | AL177: 0 | AM177: 0 | AN177: 0 | AO177: 0 | AP177: 0 | AQ177: 0 | AR177: 0 | AS177: 0 | AT177: 0 | AU177: 0 | AV177: 0 | AW177: 0 | AX177: 0 | AY177: 0 | AZ177: 0 | BA177: 0 | BB177: 0 | BC177: 0 | BD177: 0 | BE177: 0 | BF177: 0 | BG177: 0 | BH177: 0 | BI177: 0 | BJ177: 0 | BK177: 0 | BL177: 0 | BM177: 0 | BN177: 0 | BO177: 0 | BP177: 0 | BQ177: 0 | BR177: 0 | BS177: 0 | BU177: 0
B178: GR_W3 | E178: Merchant Revenue | F178: €'000 | I178: 185524.91 | K178: 0 | L178: 0 | M178: 2922.306 | N178: 0 | O178: 0 | P178: 0 | Q178: 0 | R178: 0 | S178: 0 | T178: 0 | U178: 0 | V178: 0 | W178: 0 | X178: 0 | Y178: 0 | Z178: 0 | AA178: 0 | AB178: 0 | AC178: 8367.128 | AD178: 8333.2944 | AE178: 8449.1646 | AF178: 8682.6469 | AG178: 8762.1491 | AH178: 8819.5035 | AI178: 8805.7871 | AJ178: 8934.0337 | AK178: 8950.2542 | AL178: 9015.7465 | AM178: 9108.9373 | AN178: 9373.6934 | AO178: 9668.5454 | AP178: 9872.4358 | AQ178: 9957.7944 | AR178: 10099.233 | AS178: 10325.31 | AT178: 10369.021 | AU178: 10332.331 | AV178: 6375.5941 | AW178: 0 | AX178: 0 | AY178: 0 | AZ178: 0 | BA178: 0 | BB178: 0 | BC178: 0 | BD178: 0 | BE178: 0 | BF178: 0 | BG178: 0 | BH178: 0 | BI178: 0 | BJ178: 0 | BK178: 0 | BL178: 0 | BM178: 0 | BN178: 0 | BO178: 0 | BP178: 0 | BQ178: 0 | BR178: 0 | BS178: 0 | BU178: 0
B179: GR_W3 | E179: GoOs Revenue | F179: €'000 | I179: 6357.2886 | K179: 0 | L179: 0 | M179: 0 | N179: 0 | O179: 0 | P179: 0 | Q179: 0 | R179: 0 | S179: 0 | T179: 0 | U179: 0 | V179: 0 | W179: 0 | X179: 0 | Y179: 0 | Z179: 0 | AA179: 0 | AB179: 0 | AC179: 311.00836 | AD179: 311.4773 | AE179: 312.54616 | AF179: 313.12724 | AG179: 311.39991 | AH179: 314.98227 | AI179: 315.28258 | AJ179: 309.81832 | AK179: 309.81649 | AL179: 308.28036 | AM179: 312.67725 | AN179: 318.46523 | AO179: 324.32462 | AP179: 330.32771 | AQ179: 334.87507 | AR179: 339.63157 | AS179: 345.91747 | AT179: 352.28084 | AU179: 359.32646 | AV179: 221.72342 | AW179: 0 | AX179: 0 | AY179: 0 | AZ179: 0 | BA179: 0 | BB179: 0 | BC179: 0 | BD179: 0 | BE179: 0 | BF179: 0 | BG179: 0 | BH179: 0 | BI179: 0 | BJ179: 0 | BK179: 0 | BL179: 0 | BM179: 0 | BN179: 0 | BO179: 0 | BP179: 0 | BQ179: 0 | BR179: 0 | BS179: 0 | BU179: 0
B180: GR_W3 | E180: Total Wind / Solar Revenue | F180: €'000 | I180: 270200.81 | K180: 0 | L180: 0 | M180: 4402.9747 | N180: 4891.4412 | O180: 5009.5846 | P180: 5092.8711 | Q180: 5097.91 | R180: 5125.4773 | S180: 5170.9663 | T180: 5170.2519 | U180: 5177.547 | V180: 5175.3814 | W180: 5169.4147 | X180: 5161.1366 | Y180: 5153.8598 | Z180: 5154.5875 | AA180: 5146.5281 | AB180: 5140.9866 | AC180: 8678.1364 | AD180: 8644.7717 | AE180: 8761.7107 | AF180: 8995.7741 | AG180: 9073.549 | AH180: 9134.4857 | AI180: 9121.0697 | AJ180: 9243.852 | AK180: 9260.0707 | AL180: 9324.0268 | AM180: 9421.6146 | AN180: 9692.1586 | AO180: 9992.87 | AP180: 10202.763 | AQ180: 10292.669 | AR180: 10438.865 | AS180: 10671.228 | AT180: 10721.302 | AU180: 10691.657 | AV180: 6597.3175 | AW180: 0 | AX180: 0 | AY180: 0 | AZ180: 0 | BA180: 0 | BB180: 0 | BC180: 0 | BD180: 0 | BE180: 0 | BF180: 0 | BG180: 0 | BH180: 0 | BI180: 0 | BJ180: 0 | BK180: 0 | BL180: 0 | BM180: 0 | BN180: 0 | BO180: 0 | BP180: 0 | BQ180: 0 | BR180: 0 | BS180: 0 | BU180: 0
B181: GR_W3 | E181: Total BESS Revenue | F181: €'000 | I181: 0 | K181: 0 | L181: 0 | M181: 0 | N181: 0 | O181: 0 | P181: 0 | Q181: 0 | R181: 0 | S181: 0 | T181: 0 | U181: 0 | V181: 0 | W181: 0 | X181: 0 | Y181: 0 | Z181: 0 | AA181: 0 | AB181: 0 | AC181: 0 | AD181: 0 | AE181: 0 | AF181: 0 | AG181: 0 | AH181: 0 | AI181: 0 | AJ181: 0 | AK181: 0 | AL181: 0 | AM181: 0 | AN181: 0 | AO181: 0 | AP181: 0 | AQ181: 0 | AR181: 0 | AS181: 0 | AT181: 0 | AU181: 0 | AV181: 0 | AW181: 0 | AX181: 0 | AY181: 0 | AZ181: 0 | BA181: 0 | BB181: 0 | BC181: 0 | BD181: 0 | BE181: 0 | BF181: 0 | BG181: 0 | BH181: 0 | BI181: 0 | BJ181: 0 | BK181: 0 | BL181: 0 | BM181: 0 | BN181: 0 | BO181: 0 | BP181: 0 | BQ181: 0 | BR181: 0 | BS181: 0 | BU181: 0
B182: GR_W3 | E182: Other Revenue Cost/Income | F182: €'000 | I182: -8189.432 | K182: 0 | L182: 0 | M182: -212.35264 | N182: -135.87337 | O182: -139.15513 | P182: -141.46864 | Q182: -141.60861 | R182: -142.37437 | S182: -143.63795 | T182: -143.61811 | U182: -143.82075 | V182: -143.76059 | W182: -143.59485 | X182: -143.3649 | Y182: -143.16277 | Z182: -143.18299 | AA182: -142.95911 | AB182: -100.26299 | AC182: -309.39756 | AD182: -305.50761 | AE182: -304.52929 | AF182: -305.76741 | AG182: -304.20078 | AH182: -302.22633 | AI182: -298.82263 | AJ182: -298.0039 | AK182: -295.2006 | AL182: -293.35669 | AM182: -291.97845 | AN182: -293.37762 | AO182: -295.16197 | AP182: -295.36154 | AQ182: -293.72449 | AR182: -292.95096 | AS182: -293.35297 | AT182: -290.94039 | AU182: -287.34039 | AV182: -234.0327 | AW182: 0 | AX182: 0 | AY182: 0 | AZ182: 0 | BA182: 0 | BB182: 0 | BC182: 0 | BD182: 0 | BE182: 0 | BF182: 0 | BG182: 0 | BH182: 0 | BI182: 0 | BJ182: 0 | BK182: 0 | BL182: 0 | BM182: 0 | BN182: 0 | BO182: 0 | BP182: 0 | BQ182: 0 | BR182: 0 | BS182: 0 | BU182: 0
E183: GR_W3 | F183: €'000 | I183: 262011.38 | K183: 0 | L183: 0 | M183: 4190.622 | N183: 4755.5678 | O183: 4870.4295 | P183: 4951.4025 | Q183: 4956.3014 | R183: 4983.1029 | S183: 5027.3283 | T183: 5026.6338 | U183: 5033.7263 | V183: 5031.6208 | W183: 5025.8199 | X183: 5017.7717 | Y183: 5010.6971 | Z183: 5011.4045 | AA183: 5003.569 | AB183: 5040.7236 | AC183: 8368.7388 | AD183: 8339.2641 | AE183: 8457.1815 | AF183: 8690.0067 | AG183: 8769.3482 | AH183: 8832.2594 | AI183: 8822.2471 | AJ183: 8945.8481 | AK183: 8964.8701 | AL183: 9030.6701 | AM183: 9129.6361 | AN183: 9398.781 | AO183: 9697.708 | AP183: 9907.4019 | AQ183: 9998.945 | AR183: 10145.914 | AS183: 10377.875 | AT183: 10430.361 | AU183: 10404.317 | AV183: 6363.2848 | AW183: 0 | AX183: 0 | AY183: 0 | AZ183: 0 | BA183: 0 | BB183: 0 | BC183: 0 | BD183: 0 | BE183: 0 | BF183: 0 | BG183: 0 | BH183: 0 | BI183: 0 | BJ183: 0 | BK183: 0 | BL183: 0 | BM183: 0 | BN183: 0 | BO183: 0 | BP183: 0 | BQ183: 0 | BR183: 0 | BS183: 0 | BU183: 0
B185: GR_W4 | E185: PPA Revenue | I185: 108424.55 | K185: 0 | L185: 0 | M185: 0 | N185: 0 | O185: 4934.4582 | P185: 7071.4365 | Q185: 7067.3424 | R185: 7096.9013 | S185: 7163.5031 | T185: 7160.1157 | U185: 7167.0776 | V185: 7168.0745 | W185: 7158.9122 | X185: 7147.303 | Y185: 7137.3745 | Z185: 7134.6689 | AA185: 7126.129 | AB185: 7119.2425 | AC185: 7108.3895 | AD185: 3663.6164 | AE185: 0 | AF185: 0 | AG185: 0 | AH185: 0 | AI185: 0 | AJ185: 0 | AK185: 0 | AL185: 0 | AM185: 0 | AN185: 0 | AO185: 0 | AP185: 0 | AQ185: 0 | AR185: 0 | AS185: 0 | AT185: 0 | AU185: 0 | AV185: 0 | AW185: 0 | AX185: 0 | AY185: 0 | AZ185: 0 | BA185: 0 | BB185: 0 | BC185: 0 | BD185: 0 | BE185: 0 | BF185: 0 | BG185: 0 | BH185: 0 | BI185: 0 | BJ185: 0 | BK185: 0 | BL185: 0 | BM185: 0 | BN185: 0 | BO185: 0 | BP185: 0 | BQ185: 0 | BR185: 0 | BS185: 0 | BU185: 0
B186: GR_W4 | E186: Merchant Revenue | F186: €'000 | I186: 276137.93 | K186: 0 | L186: 0 | M186: 0 | N186: 0 | O186: 0 | P186: 0 | Q186: 0 | R186: 0 | S186: 0 | T186: 0 | U186: 0 | V186: 0 | W186: 0 | X186: 0 | Y186: 0 | Z186: 0 | AA186: 0 | AB186: 0 | AC186: 0 | AD186: 5822.3274 | AE186: 12203.241 | AF186: 12545.627 | AG186: 12746.183 | AH186: 12930.648 | AI186: 12723.559 | AJ186: 12909.784 | AK186: 12932.307 | AL186: 13086.777 | AM186: 13289.912 | AN186: 13544.144 | AO186: 13971.177 | AP186: 14264.789 | AQ186: 14454.886 | AR186: 14736.285 | AS186: 14919.159 | AT186: 14983.39 | AU186: 14922.568 | AV186: 15221.02 | AW186: 15525.44 | AX186: 8404.7069 | AY186: 0 | AZ186: 0 | BA186: 0 | BB186: 0 | BC186: 0 | BD186: 0 | BE186: 0 | BF186: 0 | BG186: 0 | BH186: 0 | BI186: 0 | BJ186: 0 | BK186: 0 | BL186: 0 | BM186: 0 | BN186: 0 | BO186: 0 | BP186: 0 | BQ186: 0 | BR186: 0 | BS186: 0 | BU186: 0
B187: GR_W4 | E187: GoOs Revenue | F187: €'000 | I187: 9568.0297 | K187: 0 | L187: 0 | M187: 0 | N187: 0 | O187: 0 | P187: 0 | Q187: 0 | R187: 0 | S187: 0 | T187: 0 | U187: 0 | V187: 0 | W187: 0 | X187: 0 | Y187: 0 | Z187: 0 | AA187: 0 | AB187: 0 | AC187: 0 | AD187: 217.62376 | AE187: 451.4146 | AF187: 452.4401 | AG187: 452.98933 | AH187: 461.80886 | AI187: 455.55457 | AJ187: 447.69113 | AK187: 447.65677 | AL187: 447.48333 | AM187: 456.19518 | AN187: 460.15362 | AO187: 468.65341 | AP187: 477.29406 | AQ187: 486.10973 | AR187: 495.57305 | AS187: 499.82011 | AT187: 509.05105 | AU187: 518.96071 | AV187: 529.33993 | AW187: 539.92673 | AX187: 292.28968 | AY187: 0 | AZ187: 0 | BA187: 0 | BB187: 0 | BC187: 0 | BD187: 0 | BE187: 0 | BF187: 0 | BG187: 0 | BH187: 0 | BI187: 0 | BJ187: 0 | BK187: 0 | BL187: 0 | BM187: 0 | BN187: 0 | BO187: 0 | BP187: 0 | BQ187: 0 | BR187: 0 | BS187: 0 | BU187: 0
...

Sheet Phase II Charts
B2: Charts - Phase II Seller
P6: Date | W6: =+DATE(W7,12,31) -> 46022 | X6: =+DATE(X7,12,31) -> 46387 | Y6: =+DATE(Y7,12,31) -> 46752 | Z6: =+DATE(Z7,12,31) -> 47118 | AA6: =+DATE(AA7,12,31) -> 47483 | AB6: =+DATE(AB7,12,31) -> 47848 | AC6: =+DATE(AC7,12,31) -> 48213 | AD6: =+DATE(AD7,12,31) -> 48579 | ... BQ6: =+DATE(BQ7,12,31) -> 62823
P7: Year | W7: 2025 | X7: =W7+1 -> 2026 | Y7: =X7+1 -> 2027 | Z7: =Y7+1 -> 2028 | AA7: =Z7+1 -> 2029 | AB7: =AA7+1 -> 2030 | AC7: =AB7+1 -> 2031 | AD7: =AC7+1 -> 2032 | AE7: =AD7+1 -> 2033 | ... BQ7: =BP7+1 -> 2071
B10: =+MAX($B$6:B9)+1 -> 1 | C10: Electricity prices
C12: =+MAX($B$10:C11)+0.1 -> 1.1 | D12: Greece
P14: Electricity price - Greece | R14: €/MWh | S14: =IFERROR(AVERAGE(X14:BQ14),0) -> 0 | V14: Input
C33: =+MAX($B$10:C32)+0.1 -> 1.2 | D33: Italy
P35: Electricity price - Italy | R35: €/MWh | S35: =IFERROR(AVERAGE(X35:BQ35),0) -> 0 | V35: Input
B55: =+MAX($B$6:B54)+1 -> 2 | C55: Greek portfolio
C57: =+MAX($B$10:C56)+0.1 -> 2.1 | D57: Production
P59: Vermio North | Q59: GR_W1 | R59: GWh | S59: =SUM(X59:BQ59) -> 21081.504 | X59: ='Phase II Outputs'!M90/1000 -> 316.35352 | Y59: ='Phase II Outputs'!N90/1000 -> 576.62582 | Z59: ='Phase II Outputs'!O90/1000 -> 591.56146 | AA59: ='Phase II Outputs'!P90/1000 -> 602.63195 | AB59: ='Phase II Outputs'!Q90/1000 -> 604.27792 | AC59: ='Phase II Outputs'!R90/1000 -> 607.6466 | AD59: ='Phase II Outputs'!S90/1000 -> 613.22618 | AE59: ='Phase II Outputs'!T90/1000 -> 612.92717 | ... BQ59: ='Phase II Outputs'!BF90/1000 -> 0
P60: Vermio South | Q60: GR_W2 | R60: GWh | S60: =SUM(X60:BQ60) -> 2687.1371 | X60: ='Phase II Outputs'!M92/1000 -> 52.77888 | Y60: ='Phase II Outputs'!N92/1000 -> 73.842438 | Z60: ='Phase II Outputs'!O92/1000 -> 75.613485 | AA60: ='Phase II Outputs'!P92/1000 -> 76.875148 | AB60: ='Phase II Outputs'!Q92/1000 -> 76.953308 | AC60: ='Phase II Outputs'!R92/1000 -> 77.371997 | AD60: ='Phase II Outputs'!S92/1000 -> 78.065084 | AE60: ='Phase II Outputs'!T92/1000 -> 78.051496 | ... BQ60: ='Phase II Outputs'!BF92/1000 -> 0
P61: Mesokorfi | Q61: GR_W3 | R61: GWh | S61: =SUM(X61:BQ61) -> 2472.4185 | X61: ='Phase II Outputs'!M94/1000 -> 48.207753 | Y61: ='Phase II Outputs'!N94/1000 -> 67.936683 | Z61: ='Phase II Outputs'!O94/1000 -> 69.577564 | AA61: ='Phase II Outputs'!P94/1000 -> 70.734321 | AB61: ='Phase II Outputs'!Q94/1000 -> 70.804306 | AC61: ='Phase II Outputs'!R94/1000 -> 71.187184 | AD61: ='Phase II Outputs'!S94/1000 -> 71.818976 | AE61: ='Phase II Outputs'!T94/1000 -> 71.809054 | ... BQ61: ='Phase II Outputs'!BF94/1000 -> 0
P62: Koukouras | Q62: GR_W4 | R62: GWh | S62: =SUM(X62:BQ62) -> 3568.6076 | X62: ='Phase II Outputs'!M96/1000 -> 0 | Y62: ='Phase II Outputs'!N96/1000 -> 0 | Z62: ='Phase II Outputs'!O96/1000 -> 71.513887 | AA62: ='Phase II Outputs'!P96/1000 -> 102.48459 | AB62: ='Phase II Outputs'!Q96/1000 -> 102.42525 | AC62: ='Phase II Outputs'!R96/1000 -> 102.85364 | AD62: ='Phase II Outputs'!S96/1000 -> 103.81889 | AE62: ='Phase II Outputs'!T96/1000 -> 103.76979 | ... BQ62: ='Phase II Outputs'!BF96/1000 -> 0
P63: Panachaiko III | Q63: GR_W5 | R63: GWh | S63: =SUM(X63:BQ63) -> 1372.2766 | X63: ='Phase II Outputs'!M98/1000 -> 0 | Y63: ='Phase II Outputs'!N98/1000 -> 0 | Z63: ='Phase II Outputs'!O98/1000 -> 18.406272 | AA63: ='Phase II Outputs'!P98/1000 -> 39.09836 | AB63: ='Phase II Outputs'!Q98/1000 -> 39.276387 | AC63: ='Phase II Outputs'!R98/1000 -> 39.460839 | AD63: ='Phase II Outputs'!S98/1000 -> 39.812085 | AE63: ='Phase II Outputs'!T98/1000 -> 39.792045 | ... BQ63: ='Phase II Outputs'!BF98/1000 -> 0
P64: Total production | R64: GWh | S64: =SUM(X64:BQ64) -> 31181.944 | X64: =SUM(X59:X63) -> 417.34015 | Y64: =SUM(Y59:Y63) -> 718.40494 | Z64: =SUM(Z59:Z63) -> 826.67267 | AA64: =SUM(AA59:AA63) -> 891.82436 | AB64: =SUM(AB59:AB63) -> 893.73718 | AC64: =SUM(AC59:AC63) -> 898.52026 | AD64: =SUM(AD59:AD63) -> 906.74121 | AE64: =SUM(AE59:AE63) -> 906.34956 | ... BQ64: =SUM(BQ59:BQ63) -> 0
C78: =+MAX($B$10:C77)+0.1 -> 2.2 | D78: Revenues
P80: Vermio North | Q80: GR_W1 | R80: €m | S80: =SUM(X80:BQ80) -> 667.76083 | X80: ='Phase II Outputs'!M161/1000 -> 14.592562 | Y80: ='Phase II Outputs'!N161/1000 -> 42.67031 | Z80: ='Phase II Outputs'!O161/1000 -> 43.775548 | AA80: ='Phase II Outputs'!P161/1000 -> 44.594764 | AB80: ='Phase II Outputs'!Q161/1000 -> 44.716566 | AC80: ='Phase II Outputs'!R161/1000 -> 44.965849 | AD80: ='Phase II Outputs'!S161/1000 -> 45.378737 | AE80: ='Phase II Outputs'!T161/1000 -> 45.356611 | ... BQ80: ='Phase II Outputs'!BF161/1000 -> 0
P81: Vermio South | Q81: GR_W2 | R81: €m | S81: =SUM(X81:BQ81) -> 85.160313 | X81: ='Phase II Outputs'!M169/1000 -> 1.6431206 | Y81: ='Phase II Outputs'!N169/1000 -> 5.3166556 | Z81: ='Phase II Outputs'!O169/1000 -> 5.4441709 | AA81: ='Phase II Outputs'!P169/1000 -> 5.5350106 | AB81: ='Phase II Outputs'!Q169/1000 -> 5.5406382 | AC81: ='Phase II Outputs'!R169/1000 -> 5.5707838 | AD81: ='Phase II Outputs'!S169/1000 -> 5.620686 | AE81: ='Phase II Outputs'!T169/1000 -> 5.6197077 | ... BQ81: ='Phase II Outputs'!BF169/1000 -> 0
P82: Mesokorfi | Q82: GR_W3 | R82: €m | S82: =SUM(X82:BQ82) -> 78.318613 | X82: ='Phase II Outputs'!M177/1000 -> 1.4806687 | Y82: ='Phase II Outputs'!N177/1000 -> 4.8914412 | Z82: ='Phase II Outputs'!O177/1000 -> 5.0095846 | AA82: ='Phase II Outputs'!P177/1000 -> 5.0928711 | AB82: ='Phase II Outputs'!Q177/1000 -> 5.09791 | AC82: ='Phase II Outputs'!R177/1000 -> 5.1254773 | AD82: ='Phase II Outputs'!S177/1000 -> 5.1709663 | AE82: ='Phase II Outputs'!T177/1000 -> 5.1702519 | ... BQ82: ='Phase II Outputs'!BF177/1000 -> 0
P83: Koukouras | Q83: GR_W4 | R83: €m | S83: =SUM(X83:BQ83) -> 108.42455 | X83: ='Phase II Outputs'!M185/1000 -> 0 | Y83: ='Phase II Outputs'!N185/1000 -> 0 | Z83: ='Phase II Outputs'!O185/1000 -> 4.9344582 | AA83: ='Phase II Outputs'!P185/1000 -> 7.0714365 | AB83: ='Phase II Outputs'!Q185/1000 -> 7.0673424 | AC83: ='Phase II Outputs'!R185/1000 -> 7.0969013 | AD83: ='Phase II Outputs'!S185/1000 -> 7.1635031 | AE83: ='Phase II Outputs'!T185/1000 -> 7.1601157 | ... BQ83: ='Phase II Outputs'!BF185/1000 -> 0
P84: Panachaiko III | Q84: GR_W5 | R84: €m | S84: =SUM(X84:BQ84) -> 0 | X84: ='Phase II Outputs'!M193/1000 -> 0 | Y84: ='Phase II Outputs'!N193/1000 -> 0 | Z84: ='Phase II Outputs'!O193/1000 -> 0 | AA84: ='Phase II Outputs'!P193/1000 -> 0 | AB84: ='Phase II Outputs'!Q193/1000 -> 0 | AC84: ='Phase II Outputs'!R193/1000 -> 0 | AD84: ='Phase II Outputs'!S193/1000 -> 0 | AE84: ='Phase II Outputs'!T193/1000 -> 0 | ... BQ84: ='Phase II Outputs'!BF193/1000 -> 0
P85: PPA revenue | R85: €m | S85: =SUM(X85:BQ85) -> 939.6643 | X85: =SUM(X80:X84) -> 17.716351 | Y85: =SUM(Y80:Y84) -> 52.878407 | Z85: =SUM(Z80:Z84) -> 59.163762 | AA85: =SUM(AA80:AA84) -> 62.294082 | AB85: =SUM(AB80:AB84) -> 62.422457 | AC85: =SUM(AC80:AC84) -> 62.759011 | AD85: =SUM(AD80:AD84) -> 63.333893 | AE85: =SUM(AE80:AE84) -> 63.306686 | ... BQ85: =SUM(BQ80:BQ84) -> 0
P86: Vermio North | Q86: GR_W1 | R86: €m | S86: =SUM(X86:BQ86) -> 1614.3122 | X86: ='Phase II Outputs'!M162/1000 -> 12.806804 | Y86: ='Phase II Outputs'!N162/1000 -> 0 | Z86: ='Phase II Outputs'!O162/1000 -> 0 | AA86: ='Phase II Outputs'!P162/1000 -> 0 | AB86: ='Phase II Outputs'!Q162/1000 -> 0 | AC86: ='Phase II Outputs'!R162/1000 -> 0 | AD86: ='Phase II Outputs'!S162/1000 -> 0 | AE86: ='Phase II Outputs'!T162/1000 -> 0 | ... BQ86: ='Phase II Outputs'!BF162/1000 -> 0
P87: Vermio South | Q87: GR_W2 | R87: €m | S87: =SUM(X87:BQ87) -> 201.554 | X87: ='Phase II Outputs'!M170/1000 -> 3.1696198 | Y87: ='Phase II Outputs'!N170/1000 -> 0 | Z87: ='Phase II Outputs'!O170/1000 -> 0 | AA87: ='Phase II Outputs'!P170/1000 -> 0 | AB87: ='Phase II Outputs'!Q170/1000 -> 0 | AC87: ='Phase II Outputs'!R170/1000 -> 0 | AD87: ='Phase II Outputs'!S170/1000 -> 0 | AE87: ='Phase II Outputs'!T170/1000 -> 0 | ... BQ87: ='Phase II Outputs'!BF170/1000 -> 0
P88: Mesokorfi | Q88: GR_W3 | R88: €m | S88: =SUM(X88:BQ88) -> 185.52491 | X88: ='Phase II Outputs'!M178/1000 -> 2.922306 | Y88: ='Phase II Outputs'!N178/1000 -> 0 | Z88: ='Phase II Outputs'!O178/1000 -> 0 | AA88: ='Phase II Outputs'!P178/1000 -> 0 | AB88: ='Phase II Outputs'!Q178/1000 -> 0 | AC88: ='Phase II Outputs'!R178/1000 -> 0 | AD88: ='Phase II Outputs'!S178/1000 -> 0 | AE88: ='Phase II Outputs'!T178/1000 -> 0 | ... BQ88: ='Phase II Outputs'!BF178/1000 -> 0
P89: Koukouras | Q89: GR_W4 | R89: €m | S89: =SUM(X89:BQ89) -> 276.13793 | X89: ='Phase II Outputs'!M186/1000 -> 0 | Y89: ='Phase II Outputs'!N186/1000 -> 0 | Z89: ='Phase II Outputs'!O186/1000 -> 0 | AA89: ='Phase II Outputs'!P186/1000 -> 0 | AB89: ='Phase II Outputs'!Q186/1000 -> 0 | AC89: ='Phase II Outputs'!R186/1000 -> 0 | AD89: ='Phase II Outputs'!S186/1000 -> 0 | AE89: ='Phase II Outputs'!T186/1000 -> 0 | ... BQ89: ='Phase II Outputs'!BF186/1000 -> 0
P90: Panachaiko III | Q90: GR_W5 | R90: €m | S90: =SUM(X90:BQ90) -> 174.12671 | X90: ='Phase II Outputs'!M194/1000 -> 0 | Y90: ='Phase II Outputs'!N194/1000 -> 0 | Z90: ='Phase II Outputs'!O194/1000 -> 2.0688658 | AA90: ='Phase II Outputs'!P194/1000 -> 4.2188711 | AB90: ='Phase II Outputs'!Q194/1000 -> 3.9698685 | AC90: ='Phase II Outputs'!R194/1000 -> 4.2201171 | AD90: ='Phase II Outputs'!S194/1000 -> 4.315261 | AE90: ='Phase II Outputs'!T194/1000 -> 4.4930535 | ... BQ90: ='Phase II Outputs'!BF194/1000 -> 0
P91: Merchant revenue | R91: €m | S91: =SUM(X91:BQ91) -> 2451.6557 | X91: =SUM(X86:X90) -> 18.898729 | Y91: =SUM(Y86:Y90) -> 0 | Z91: =SUM(Z86:Z90) -> 2.0688658 | AA91: =SUM(AA86:AA90) -> 4.2188711 | AB91: =SUM(AB86:AB90) -> 3.9698685 | AC91: =SUM(AC86:AC90) -> 4.2201171 | AD91: =SUM(AD86:AD90) -> 4.315261 | AE91: =SUM(AE86:AE90) -> 4.4930535 | ... BQ91: =SUM(BQ86:BQ90) -> 0
P92: Vermio North | Q92: GR_W1 | R92: €m | S92: =SUM(X92:BQ92) -> 55.941759 | X92: ='Phase II Outputs'!M163/1000 -> 0.10014077 | Y92: ='Phase II Outputs'!N163/1000 -> 0 | Z92: ='Phase II Outputs'!O163/1000 -> 0 | AA92: ='Phase II Outputs'!P163/1000 -> 0 | AB92: ='Phase II Outputs'!Q163/1000 -> 0 | AC92: ='Phase II Outputs'!R163/1000 -> 0 | AD92: ='Phase II Outputs'!S163/1000 -> 0 | AE92: ='Phase II Outputs'!T163/1000 -> 0 | ... BQ92: ='Phase II Outputs'!BF163/1000 -> 0
P93: Vermio South | Q93: GR_W2 | R93: €m | S93: =SUM(X93:BQ93) -> 6.9067339 | X93: ='Phase II Outputs'!M171/1000 -> 0 | Y93: ='Phase II Outputs'!N171/1000 -> 0 | Z93: ='Phase II Outputs'!O171/1000 -> 0 | AA93: ='Phase II Outputs'!P171/1000 -> 0 | AB93: ='Phase II Outputs'!Q171/1000 -> 0 | AC93: ='Phase II Outputs'!R171/1000 -> 0 | AD93: ='Phase II Outputs'!S171/1000 -> 0 | AE93: ='Phase II Outputs'!T171/1000 -> 0 | ... BQ93: ='Phase II Outputs'!BF171/1000 -> 0
P94: Mesokorfi | Q94: GR_W3 | R94: €m | S94: =SUM(X94:BQ94) -> 6.3572886 | X94: ='Phase II Outputs'!M179/1000 -> 0 | Y94: ='Phase II Outputs'!N179/1000 -> 0 | Z94: ='Phase II Outputs'!O179/1000 -> 0 | AA94: ='Phase II Outputs'!P179/1000 -> 0 | AB94: ='Phase II Outputs'!Q179/1000 -> 0 | AC94: ='Phase II Outputs'!R179/1000 -> 0 | AD94: ='Phase II Outputs'!S179/1000 -> 0 | AE94: ='Phase II Outputs'!T179/1000 -> 0 | ... BQ94: ='Phase II Outputs'!BF179/1000 -> 0
P95: Koukouras | Q95: GR_W4 | R95: €m | S95: =SUM(X95:BQ95) -> 9.5680297 | X95: ='Phase II Outputs'!M187/1000 -> 0 | Y95: ='Phase II Outputs'!N187/1000 -> 0 | Z95: ='Phase II Outputs'!O187/1000 -> 0 | AA95: ='Phase II Outputs'!P187/1000 -> 0 | AB95: ='Phase II Outputs'!Q187/1000 -> 0 | AC95: ='Phase II Outputs'!R187/1000 -> 0 | AD95: ='Phase II Outputs'!S187/1000 -> 0 | AE95: ='Phase II Outputs'!T187/1000 -> 0 | ... BQ95: ='Phase II Outputs'!BF187/1000 -> 0
P96: Panachaiko III | Q96: GR_W5 | R96: €m | S96: =SUM(X96:BQ96) -> 6.1665263 | X96: ='Phase II Outputs'!M195/1000 -> 0 | Y96: ='Phase II Outputs'!N195/1000 -> 0 | Z96: ='Phase II Outputs'!O195/1000 -> 0.049071769 | AA96: ='Phase II Outputs'!P195/1000 -> 0.12333393 | AB96: ='Phase II Outputs'!Q195/1000 -> 0.13944653 | AC96: ='Phase II Outputs'!R195/1000 -> 0.15406777 | AD96: ='Phase II Outputs'!S195/1000 -> 0.16314352 | AE96: ='Phase II Outputs'!T195/1000 -> 0.1686652 | ... BQ96: ='Phase II Outputs'!BF195/1000 -> 0
P97: GoOs revenue | R97: €m | S97: =SUM(X97:BQ97) -> 84.940338 | X97: =SUM(X92:X96) -> 0.10014077 | Y97: =SUM(Y92:Y96) -> 0 | Z97: =SUM(Z92:Z96) -> 0.049071769 | AA97: =SUM(AA92:AA96) -> 0.12333393 | AB97: =SUM(AB92:AB96) -> 0.13944653 | AC97: =SUM(AC92:AC96) -> 0.15406777 | AD97: =SUM(AD92:AD96) -> 0.16314352 | AE97: =SUM(AE92:AE96) -> 0.1686652 | ... BQ97: =SUM(BQ92:BQ96) -> 0
P98: Vermio North | Q98: GR_W1 | R98: €m | S98: =SUM(X98:BQ98) -> -34.360502 | X98: ='Phase II Outputs'!M166/1000 -> -0.52536008 | Y98: ='Phase II Outputs'!N166/1000 -> -1.1532516 | Z98: ='Phase II Outputs'!O166/1000 -> -1.1831229 | AA98: ='Phase II Outputs'!P166/1000 -> 6.4862301 | AB98: ='Phase II Outputs'!Q166/1000 -> -1.2085558 | AC98: ='Phase II Outputs'!R166/1000 -> -1.2152932 | AD98: ='Phase II Outputs'!S166/1000 -> -1.2264524 | AE98: ='Phase II Outputs'!T166/1000 -> -1.2258543 | ... BQ98: ='Phase II Outputs'!BF166/1000 -> 0
P99: Vermio South | Q99: GR_W2 | R99: €m | S99: =SUM(X99:BQ99) -> -8.6119607 | X99: ='Phase II Outputs'!M174/1000 -> -0.21925696 | Y99: ='Phase II Outputs'!N174/1000 -> -0.14768488 | Z99: ='Phase II Outputs'!O174/1000 -> -0.15122697 | AA99: ='Phase II Outputs'!P174/1000 -> -0.1537503 | AB99: ='Phase II Outputs'!Q174/1000 -> -0.15390662 | AC99: ='Phase II Outputs'!R174/1000 -> -0.15474399 | AD99: ='Phase II Outputs'!S174/1000 -> -0.15613017 | AE99: ='Phase II Outputs'!T174/1000 -> -0.15610299 | ... BQ99: ='Phase II Outputs'!BF174/1000 -> 0
P100: Mesokorfi | Q100: GR_W3 | R100: €m | S100: =SUM(X100:BQ100) -> -8.189432 | X100: ='Phase II Outputs'!M182/1000 -> -0.21235264 | Y100: ='Phase II Outputs'!N182/1000 -> -0.13587337 | Z100: ='Phase II Outputs'!O182/1000 -> -0.13915513 | AA100: ='Phase II Outputs'!P182/1000 -> -0.14146864 | AB100: ='Phase II Outputs'!Q182/1000 -> -0.14160861 | AC100: ='Phase II Outputs'!R182/1000 -> -0.14237437 | AD100: ='Phase II Outputs'!S182/1000 -> -0.14363795 | AE100: ='Phase II Outputs'!T182/1000 -> -0.14361811 | ... BQ100: ='Phase II Outputs'!BF182/1000 -> 0
P101: Koukouras | Q101: GR_W4 | R101: €m | S101: =SUM(X101:BQ101) -> -2.3599945 | X101: ='Phase II Outputs'!M190/1000 -> 0 | Y101: ='Phase II Outputs'!N190/1000 -> 0 | Z101: ='Phase II Outputs'!O190/1000 -> -0.12791396 | AA101: ='Phase II Outputs'!P190/1000 -> -0.20496917 | AB101: ='Phase II Outputs'!Q190/1000 -> -0.2048505 | AC101: ='Phase II Outputs'!R190/1000 -> 7.7124227 | AD101: ='Phase II Outputs'!S190/1000 -> -0.20763777 | AE101: ='Phase II Outputs'!T190/1000 -> -0.20753959 | ... BQ101: ='Phase II Outputs'!BF190/1000 -> 0
P102: Panachaiko III | Q102: GR_W5 | R102: €m | S102: =SUM(X102:BQ102) -> -8.6785531 | X102: ='Phase II Outputs'!M198/1000 -> 0 | Y102: ='Phase II Outputs'!N198/1000 -> 0 | Z102: ='Phase II Outputs'!O198/1000 -> -0.14221254 | AA102: ='Phase II Outputs'!P198/1000 -> -0.27659672 | AB102: ='Phase II Outputs'!Q198/1000 -> -0.26075277 | AC102: ='Phase II Outputs'!R198/1000 -> -0.26792168 | AD102: ='Phase II Outputs'!S198/1000 -> -0.26742417 | AE102: ='Phase II Outputs'!T198/1000 -> -0.27138409 | ... BQ102: ='Phase II Outputs'!BF198/1000 -> 0
P103: Other revenue / (cost) | R103: €m | S103: =SUM(X103:BQ103) -> -62.200443 | X103: =SUM(X98:X102) -> -0.95696968 | Y103: =SUM(Y98:Y102) -> -1.4368099 | Z103: =SUM(Z98:Z102) -> -1.7436315 | AA103: =SUM(AA98:AA102) -> 5.7094453 | AB103: =SUM(AB98:AB102) -> -1.9696744 | AC103: =SUM(AC98:AC102) -> 5.9320895 | AD103: =SUM(AD98:AD102) -> -2.0012824 | AE103: =SUM(AE98:AE102) -> -2.0044991 | ... BQ103: =SUM(BQ98:BQ102) -> 0
P104: Total revenues | R104: €m | S104: =SUM(X104:BQ104) -> 3414.0599 | X104: =X85+X91+X97+X103 -> 35.758252 | Y104: =Y85+Y91+Y97+Y103 -> 51.441597 | Z104: =Z85+Z91+Z97+Z103 -> 59.538068 | AA104: =AA85+AA91+AA97+AA103 -> 72.345733 | AB104: =AB85+AB91+AB97+AB103 -> 64.562098 | AC104: =AC85+AC91+AC97+AC103 -> 73.065285 | AD104: =AD85+AD91+AD97+AD103 -> 65.811015 | AE104: =AE85+AE91+AE97+AE103 -> 65.963906 | ... BQ104: =BQ85+BQ91+BQ97+BQ103 -> 0
C107: =+MAX($B$10:C106)+0.1 -> 2.3 | D107: EBITDA
P109: Vermio North | Q109: GR_W1 | R109: €m | S109: =SUM(X109:BQ109) -> 1947.9123 | X109: ='Phase II Outputs'!M409/1000 -> 17.240434 | Y109: ='Phase II Outputs'!N409/1000 -> 34.863006 | Z109: ='Phase II Outputs'!O409/1000 -> 35.238108 | AA109: ='Phase II Outputs'!P409/1000 -> 43.610205 | AB109: ='Phase II Outputs'!Q409/1000 -> 35.981661 | AC109: ='Phase II Outputs'!R409/1000 -> 36.297034 | AD109: ='Phase II Outputs'!S409/1000 -> 36.289649 | AE109: ='Phase II Outputs'!T409/1000 -> 36.182589 | ... BQ109: ='Phase II Outputs'!BF409/1000 -> 0
P110: Vermio South | Q110: GR_W2 | R110: €m | S110: =SUM(X110:BQ110) -> 234.26886 | X110: ='Phase II Outputs'!M411/1000 -> 2.7959234 | Y110: ='Phase II Outputs'!N411/1000 -> 4.214736 | Z110: ='Phase II Outputs'!O411/1000 -> 4.2465797 | AA110: ='Phase II Outputs'!P411/1000 -> 4.3204678 | AB110: ='Phase II Outputs'!Q411/1000 -> 4.3133128 | AC110: ='Phase II Outputs'!R411/1000 -> 4.3415373 | AD110: ='Phase II Outputs'!S411/1000 -> 4.3734759 | AE110: ='Phase II Outputs'!T411/1000 -> 4.3591961 | ... BQ110: ='Phase II Outputs'!BF411/1000 -> 0
P111: Mesokorfi | Q111: GR_W3 | R111: €m | S111: =SUM(X111:BQ111) -> 216.40995 | X111: ='Phase II Outputs'!M413/1000 -> 2.5221791 | Y111: ='Phase II Outputs'!N413/1000 -> 3.9045014 | Z111: ='Phase II Outputs'!O413/1000 -> 3.9342986 | AA111: ='Phase II Outputs'!P413/1000 -> 4.0017251 | AB111: ='Phase II Outputs'!Q413/1000 -> 3.9947351 | AC111: ='Phase II Outputs'!R413/1000 -> 4.0191846 | AD111: ='Phase II Outputs'!S413/1000 -> 4.0480781 | AE111: ='Phase II Outputs'!T413/1000 -> 4.0348323 | ... BQ111: ='Phase II Outputs'!BF413/1000 -> 0
P112: Koukouras | Q112: GR_W4 | R112: €m | S112: =SUM(X112:BQ112) -> 331.09442 | X112: ='Phase II Outputs'!M415/1000 -> -1.6137975 | Y112: ='Phase II Outputs'!N415/1000 -> -1.1735525 | Z112: ='Phase II Outputs'!O415/1000 -> 3.7266341 | AA112: ='Phase II Outputs'!P415/1000 -> 5.5950062 | AB112: ='Phase II Outputs'!Q415/1000 -> 5.5800177 | AC112: ='Phase II Outputs'!R415/1000 -> 13.490787 | AD112: ='Phase II Outputs'!S415/1000 -> 5.6473279 | AE112: ='Phase II Outputs'!T415/1000 -> 5.6777712 | ... BQ112: ='Phase II Outputs'!BF415/1000 -> 0
P113: Panachaiko III | Q113: GR_W5 | R113: €m | S113: =SUM(X113:BQ113) -> 147.97932 | X113: ='Phase II Outputs'!M417/1000 -> 0 | Y113: ='Phase II Outputs'!N417/1000 -> -1.6137975 | Z113: ='Phase II Outputs'!O417/1000 -> 1.7619086 | AA113: ='Phase II Outputs'!P417/1000 -> 3.6284877 | AB113: ='Phase II Outputs'!Q417/1000 -> 3.4066711 | AC113: ='Phase II Outputs'!R417/1000 -> 3.6580118 | AD113: ='Phase II Outputs'!S417/1000 -> 3.7563805 | AE113: ='Phase II Outputs'!T417/1000 -> 3.9255553 | ... BQ113: ='Phase II Outputs'!BF417/1000 -> 0
P114: Total EBITDA | R114: €m | S114: =SUM(X114:BQ114) -> 2877.6648 | X114: =SUM(X109:X113) -> 20.944739 | Y114: =SUM(Y109:Y113) -> 40.194894 | Z114: =SUM(Z109:Z113) -> 48.907529 | AA114: =SUM(AA109:AA113) -> 61.155892 | AB114: =SUM(AB109:AB113) -> 53.276397 | AC114: =SUM(AC109:AC113) -> 61.806555 | AD114: =SUM(AD109:AD113) -> 54.114911 | AE114: =SUM(AE109:AE113) -> 54.179944 | ... BQ114: =SUM(BQ109:BQ113) -> 0
C128: =+MAX($B$10:C127)+0.1 -> 2.4 | D128: Opex
P130: Vermio North | Q130: GR_W1 | R130: €m | S130: =SUM(X130:BQ130) -> 349.34571 | X130: =-'Phase II Outputs'!M479/1000 -> 3.3374453 | Y130: =-'Phase II Outputs'!N479/1000 -> 6.6540526 | Z130: =-'Phase II Outputs'!O479/1000 -> 7.3543175 | AA130: =-'Phase II Outputs'!P479/1000 -> 7.4707893 | AB130: =-'Phase II Outputs'!Q479/1000 -> 7.5263501 | AC130: =-'Phase II Outputs'!R479/1000 -> 7.4535211 | AD130: =-'Phase II Outputs'!S479/1000 -> 7.8626358 | AE130: =-'Phase II Outputs'!T479/1000 -> 7.948167 | ... BQ130: =-'Phase II Outputs'!BF479/1000 -> 0
P131: Vermio South | Q131: GR_W2 | R131: €m | S131: =SUM(X131:BQ131) -> 49.313943 | X131: =-'Phase II Outputs'!M481/1000 -> 0.3712726 | Y131: =-'Phase II Outputs'!N481/1000 -> 0.95423468 | Z131: =-'Phase II Outputs'!O481/1000 -> 1.0463642 | AA131: =-'Phase II Outputs'!P481/1000 -> 1.0607926 | AB131: =-'Phase II Outputs'!Q481/1000 -> 1.0734188 | AC131: =-'Phase II Outputs'!R481/1000 -> 1.0745025 | AD131: =-'Phase II Outputs'!S481/1000 -> 1.09108 | AE131: =-'Phase II Outputs'!T481/1000 -> 1.1044087 | ... BQ131: =-'Phase II Outputs'!BF481/1000 -> 0
P132: Mesokorfi | Q132: GR_W3 | R132: €m | S132: =SUM(X132:BQ132) -> 44.262103 | X132: =-'Phase II Outputs'!M483/1000 -> 0.32911287 | Y132: =-'Phase II Outputs'!N483/1000 -> 0.85106641 | Z132: =-'Phase II Outputs'!O483/1000 -> 0.93613086 | AA132: =-'Phase II Outputs'!P483/1000 -> 0.94967739 | AB132: =-'Phase II Outputs'!Q483/1000 -> 0.96156627 | AC132: =-'Phase II Outputs'!R483/1000 -> 0.96391834 | AD132: =-'Phase II Outputs'!S483/1000 -> 0.97925026 | AE132: =-'Phase II Outputs'!T483/1000 -> 0.99180147 | ... BQ132: =-'Phase II Outputs'!BF483/1000 -> 0
P133: Koukouras | Q133: GR_W4 | R133: €m | S133: =SUM(X133:BQ133) -> 57.888741 | X133: =-'Phase II Outputs'!M485/1000 -> 0 | Y133: =-'Phase II Outputs'!N485/1000 -> 0 | Z133: =-'Phase II Outputs'!O485/1000 -> 1.0799102 | AA133: =-'Phase II Outputs'!P485/1000 -> 1.2714611 | AB133: =-'Phase II Outputs'!Q485/1000 -> 1.2824742 | AC133: =-'Phase II Outputs'!R485/1000 -> 1.3185367 | AD133: =-'Phase II Outputs'!S485/1000 -> 1.3085374 | AE133: =-'Phase II Outputs'!T485/1000 -> 1.2748049 | ... BQ133: =-'Phase II Outputs'!BF485/1000 -> 0
P134: Panachaiko III | Q134: GR_W5 | R134: €m | S134: =SUM(X134:BQ134) -> 22.021569 | X134: =-'Phase II Outputs'!M487/1000 -> 0 | Y134: =-'Phase II Outputs'!N487/1000 -> 0 | Z134: =-'Phase II Outputs'!O487/1000 -> 0.21381643 | AA134: =-'Phase II Outputs'!P487/1000 -> 0.43712061 | AB134: =-'Phase II Outputs'!Q487/1000 -> 0.44189114 | AC134: =-'Phase II Outputs'!R487/1000 -> 0.44825146 | AD134: =-'Phase II Outputs'!S487/1000 -> 0.4545999 | AE134: =-'Phase II Outputs'!T487/1000 -> 0.46477936 | ... BQ134: =-'Phase II Outputs'!BF487/1000 -> 0
P135: Total opex | R135: €m | S135: =SUM(X135:BQ135) -> 522.83206 | X135: =SUM(X130:X134) -> 4.0378308 | Y135: =SUM(Y130:Y134) -> 8.4593537 | Z135: =SUM(Z130:Z134) -> 10.630539 | AA135: =SUM(AA130:AA134) -> 11.189841 | AB135: =SUM(AB130:AB134) -> 11.2857 | AC135: =SUM(AC130:AC134) -> 11.25873 | AD135: =SUM(AD130:AD134) -> 11.696103 | AE135: =SUM(AE130:AE134) -> 11.783961 | ... BQ135: =SUM(BQ130:BQ134) -> 0
C149: =+MAX($B$10:C148)+0.1 -> 2.5 | D149: FCFE
P151: Vermio North | Q151: GR_W1 | R151: €m | S151: =SUM(X151:BQ151) -> 0 | V151: Input
P152: Vermio South | Q152: GR_W2 | R152: €m | S152: =SUM(X152:BQ152) -> 0 | V152: Input
P153: Mesokorfi | Q153: GR_W3 | R153: €m | S153: =SUM(X153:BQ153) -> 0 | V153: Input
P154: Koukouras | Q154: GR_W4 | R154: €m | S154: =SUM(X154:BQ154) -> 0 | V154: Input
P155: Panachaiko III | Q155: GR_W5 | R155: €m | S155: =SUM(X155:BQ155) -> 0 | V155: Input
P156: Total FCFE | R156: €m | S156: =SUM(X156:BQ156) -> 0 | X156: =SUM(X151:X155) -> 0 | Y156: =SUM(Y151:Y155) -> 0 | Z156: =SUM(Z151:Z155) -> 0 | AA156: =SUM(AA151:AA155) -> 0 | AB156: =SUM(AB151:AB155) -> 0 | AC156: =SUM(AC151:AC155) -> 0 | AD156: =SUM(AD151:AD155) -> 0 | AE156: =SUM(AE151:AE155) -> 0 | ... BQ156: =SUM(BQ151:BQ155) -> 0
B171: =+MAX($B$6:B170)+1 -> 3 | C171: Italian portfolio - Rondissone
C173: =+MAX($B$10:C172)+0.1 -> 3.1 | D173: Installed capacity
P175: Rondissone | Q175: IT_B1 | R175: MW | S175: =MAX(X175:BQ175) -> 0 | X175: ='Phase II Outputs'!M68 -> 0 | Y175: ='Phase II Outputs'!N68 -> 0 | Z175: ='Phase II Outputs'!O68 -> 0 | AA175: ='Phase II Outputs'!P68 -> 0 | AB175: ='Phase II Outputs'!Q68 -> 0 | AC175: ='Phase II Outputs'!R68 -> 0 | AD175: ='Phase II Outputs'!S68 -> 0 | AE175: ='Phase II Outputs'!T68 -> 0 | ... BQ175: ='Phase II Outputs'!BF68 -> 0
C194: =+MAX($B$10:C193)+0.1 -> 3.2 | D194: Revenues
P196: Rondissone | Q196: IT_B1 | R196: €m | S196: =SUM(X196:BQ196) -> 854.119 | X196: ='Phase II Outputs'!M298/1000 -> 0 | Y196: ='Phase II Outputs'!N298/1000 -> 0 | Z196: ='Phase II Outputs'!O298/1000 -> 24.46433 | AA196: ='Phase II Outputs'!P298/1000 -> 24.6225 | AB196: ='Phase II Outputs'!Q298/1000 -> 24.6225 | AC196: ='Phase II Outputs'!R298/1000 -> 24.6225 | AD196: ='Phase II Outputs'!S298/1000 -> 24.6225 | AE196: ='Phase II Outputs'!T298/1000 -> 24.6225 | ... BQ196: ='Phase II Outputs'!BF298/1000 -> 0
C215: =+MAX($B$10:C214)+0.1 -> 3.3 | D215: EBITDA
P217: Rondissone | Q217: IT_B1 | R217: €m | S217: =SUM(X217:BQ217) -> 698.54039 | X217: ='Phase II Outputs'!M443/1000 -> 0 | Y217: ='Phase II Outputs'!N443/1000 -> 0 | Z217: ='Phase II Outputs'!O443/1000 -> 22.058756 | AA217: ='Phase II Outputs'!P443/1000 -> 21.348934 | AB217: ='Phase II Outputs'!Q443/1000 -> 21.300648 | AC217: ='Phase II Outputs'!R443/1000 -> 21.251397 | AD217: ='Phase II Outputs'!S443/1000 -> 20.960721 | AE217: ='Phase II Outputs'!T443/1000 -> 20.866297 | ... BQ217: ='Phase II Outputs'!BF443/1000 -> 0
C236: =+MAX($B$10:C235)+0.1 -> 3.4 | D236: Opex
P238: Rondissone | Q238: IT_B1 | R238: €m | S238: =SUM(X238:BQ238) -> 155.57861 | X238: =-'Phase II Outputs'!M513/1000 -> 0 | Y238: =-'Phase II Outputs'!N513/1000 -> 0 | Z238: =-'Phase II Outputs'!O513/1000 -> 2.4055744 | AA238: =-'Phase II Outputs'!P513/1000 -> 3.2735661 | AB238: =-'Phase II Outputs'!Q513/1000 -> 3.3218515 | AC238: =-'Phase II Outputs'!R513/1000 -> 3.3711026 | AD238: =-'Phase II Outputs'!S513/1000 -> 3.6617794 | AE238: =-'Phase II Outputs'!T513/1000 -> 3.7562033 | ... BQ238: =-'Phase II Outputs'!BF513/1000 -> 0
C257: =+MAX($B$10:C256)+0.1 -> 3.5 | D257: FCFE
P259: Rondissone | Q259: IT_B1 | R259: €m | S259: =SUM(X259:BQ259) -> 0 | V259: Input
B279: =+MAX($B$6:B278)+1 -> 4 | C279: Italian portfolio
C281: =+MAX($B$10:C280)+0.1 -> 4.1 | D281: Production
P283: Wind 1 | Q283: IT_W1 | R283: GWh | S283: =SUM(X283:BQ283) -> 7756.6809 | X283: ='Phase II Outputs'!M102/1000 -> 0 | Y283: ='Phase II Outputs'!N102/1000 -> 0 | Z283: ='Phase II Outputs'!O102/1000 -> 0 | AA283: ='Phase II Outputs'!P102/1000 -> 0 | AB283: ='Phase II Outputs'!Q102/1000 -> 3.2250625 | AC283: ='Phase II Outputs'!R102/1000 -> 224.48132 | AD283: ='Phase II Outputs'!S102/1000 -> 224.48132 | AE283: ='Phase II Outputs'!T102/1000 -> 224.48132 | ... BQ283: ='Phase II Outputs'!BF102/1000 -> 0
P284: Wind 2 | Q284: IT_W2 | R284: GWh | S284: =SUM(X284:BQ284) -> 1291.7615 | X284: ='Phase II Outputs'!M104/1000 -> 0 | Y284: ='Phase II Outputs'!N104/1000 -> 0 | Z284: ='Phase II Outputs'!O104/1000 -> 0 | AA284: ='Phase II Outputs'!P104/1000 -> 0 | AB284: ='Phase II Outputs'!Q104/1000 -> 12.43319 | AC284: ='Phase II Outputs'!R104/1000 -> 37.366565 | AD284: ='Phase II Outputs'!S104/1000 -> 37.366565 | AE284: ='Phase II Outputs'!T104/1000 -> 37.366565 | ... BQ284: ='Phase II Outputs'!BF104/1000 -> 0
P285: Wind 3 | Q285: IT_W3 | R285: GWh | S285: =SUM(X285:BQ285) -> 5842.898 | X285: ='Phase II Outputs'!M106/1000 -> 0 | Y285: ='Phase II Outputs'!N106/1000 -> 0 | Z285: ='Phase II Outputs'!O106/1000 -> 0 | AA285: ='Phase II Outputs'!P106/1000 -> 0 | AB285: ='Phase II Outputs'!Q106/1000 -> 0 | AC285: ='Phase II Outputs'!R106/1000 -> 103.616 | AD285: ='Phase II Outputs'!S106/1000 -> 169.68514 | AE285: ='Phase II Outputs'!T106/1000 -> 169.68514 | ... BQ285: ='Phase II Outputs'!BF106/1000 -> 0
P286: Wind 4 | Q286: IT_W4 | R286: GWh | S286: =SUM(X286:BQ286) -> 4294.8402 | X286: ='Phase II Outputs'!M108/1000 -> 0 | Y286: ='Phase II Outputs'!N108/1000 -> 0 | Z286: ='Phase II Outputs'!O108/1000 -> 0 | AA286: ='Phase II Outputs'!P108/1000 -> 0 | AB286: ='Phase II Outputs'!Q108/1000 -> 0 | AC286: ='Phase II Outputs'!R108/1000 -> 26.433121 | AD286: ='Phase II Outputs'!S108/1000 -> 124.5318 | AE286: ='Phase II Outputs'!T108/1000 -> 124.5318 | ... BQ286: ='Phase II Outputs'!BF108/1000 -> 0
P287: Wind 5 | Q287: IT_W5 | R287: GWh | S287: =SUM(X287:BQ287) -> 3650.4163 | X287: ='Phase II Outputs'!M110/1000 -> 0 | Y287: ='Phase II Outputs'!N110/1000 -> 0 | Z287: ='Phase II Outputs'!O110/1000 -> 0 | AA287: ='Phase II Outputs'!P110/1000 -> 0 | AB287: ='Phase II Outputs'!Q110/1000 -> 0 | AC287: ='Phase II Outputs'!R110/1000 -> 75.978859 | AD287: ='Phase II Outputs'!S110/1000 -> 105.90207 | AE287: ='Phase II Outputs'!T110/1000 -> 105.90207 | ... BQ287: ='Phase II Outputs'!BF110/1000 -> 0
P288: Wind 6 | Q288: IT_W6 | R288: GWh | S288: =SUM(X288:BQ288) -> 1348.7136 | X288: ='Phase II Outputs'!M112/1000 -> 0 | Y288: ='Phase II Outputs'!N112/1000 -> 0 | Z288: ='Phase II Outputs'!O112/1000 -> 0 | AA288: ='Phase II Outputs'!P112/1000 -> 0 | AB288: ='Phase II Outputs'!Q112/1000 -> 12.981353 | AC288: ='Phase II Outputs'!R112/1000 -> 39.014007 | AD288: ='Phase II Outputs'!S112/1000 -> 39.014007 | AE288: ='Phase II Outputs'!T112/1000 -> 39.014007 | ... BQ288: ='Phase II Outputs'!BF112/1000 -> 0
P289: Wind 7 | Q289: IT_W7 | R289: GWh | S289: =SUM(X289:BQ289) -> 993.84367 | X289: ='Phase II Outputs'!M114/1000 -> 0 | Y289: ='Phase II Outputs'!N114/1000 -> 0 | Z289: ='Phase II Outputs'!O114/1000 -> 0 | AA289: ='Phase II Outputs'!P114/1000 -> 0 | AB289: ='Phase II Outputs'!Q114/1000 -> 14.110567 | AC289: ='Phase II Outputs'!R114/1000 -> 28.773578 | AD289: ='Phase II Outputs'!S114/1000 -> 28.773578 | AE289: ='Phase II Outputs'!T114/1000 -> 28.773578 | ... BQ289: ='Phase II Outputs'!BF114/1000 -> 0
P290: Wind 8 | Q290: IT_W8 | R290: GWh | S290: =SUM(X290:BQ290) -> 1998.1212 | X290: ='Phase II Outputs'!M116/1000 -> 0 | Y290: ='Phase II Outputs'!N116/1000 -> 0 | Z290: ='Phase II Outputs'!O116/1000 -> 0 | AA290: ='Phase II Outputs'!P116/1000 -> 0 | AB290: ='Phase II Outputs'!Q116/1000 -> 0 | AC290: ='Phase II Outputs'!R116/1000 -> 0 | AD290: ='Phase II Outputs'!S116/1000 -> 0 | AE290: ='Phase II Outputs'!T116/1000 -> 41.589089 | ... BQ290: ='Phase II Outputs'!BF116/1000 -> 0
P291: Solar 1 | Q291: IT_S1 | R291: GWh | S291: =SUM(X291:BQ291) -> 2863.2901 | X291: ='Phase II Outputs'!M118/1000 -> 0 | Y291: ='Phase II Outputs'!N118/1000 -> 0 | Z291: ='Phase II Outputs'!O118/1000 -> 0 | AA291: ='Phase II Outputs'!P118/1000 -> 1.1377305 | AB291: ='Phase II Outputs'!Q118/1000 -> 77.692328 | AC291: ='Phase II Outputs'!R118/1000 -> 77.016237 | AD291: ='Phase II Outputs'!S118/1000 -> 76.746723 | AE291: ='Phase II Outputs'!T118/1000 -> 76.478537 | ... BQ291: ='Phase II Outputs'!BF118/1000 -> 0
P292: Solar 2 | Q292: IT_S2 | R292: GWh | S292: =SUM(X292:BQ292) -> 1260.2842 | X292: ='Phase II Outputs'!M120/1000 -> 0 | Y292: ='Phase II Outputs'!N120/1000 -> 0 | Z292: ='Phase II Outputs'!O120/1000 -> 0 | AA292: ='Phase II Outputs'!P120/1000 -> 0.00048761254 | AB292: ='Phase II Outputs'!Q120/1000 -> 34.096796 | AC292: ='Phase II Outputs'!R120/1000 -> 33.80008 | AD292: ='Phase II Outputs'!S120/1000 -> 33.681799 | AE292: ='Phase II Outputs'!T120/1000 -> 33.5641 | ... BQ292: ='Phase II Outputs'!BF120/1000 -> 0
P293: Solar 3 | Q293: IT_S3 | R293: GWh | S293: =SUM(X293:BQ293) -> 1299.0242 | X293: ='Phase II Outputs'!M122/1000 -> 0 | Y293: ='Phase II Outputs'!N122/1000 -> 0 | Z293: ='Phase II Outputs'!O122/1000 -> 0 | AA293: ='Phase II Outputs'!P122/1000 -> 0.00050260131 | AB293: ='Phase II Outputs'!Q122/1000 -> 35.144901 | AC293: ='Phase II Outputs'!R122/1000 -> 34.839064 | AD293: ='Phase II Outputs'!S122/1000 -> 34.717147 | AE293: ='Phase II Outputs'!T122/1000 -> 34.59583 | ... BQ293: ='Phase II Outputs'!BF122/1000 -> 0
P294: Wind | R294: GWh | S294: =SUM(X294:BQ294) -> 27177.275 | X294: =SUM(X283:X290) -> 0 | Y294: =SUM(Y283:Y290) -> 0 | Z294: =SUM(Z283:Z290) -> 0 | AA294: =SUM(AA283:AA290) -> 0 | AB294: =SUM(AB283:AB290) -> 42.750173 | AC294: =SUM(AC283:AC290) -> 535.66346 | AD294: =SUM(AD283:AD290) -> 729.75448 | AE294: =SUM(AE283:AE290) -> 771.34357 | ... BQ294: =SUM(BQ283:BQ290) -> 0
P295: Solar | R295: GWh | S295: =SUM(X295:BQ295) -> 5422.5985 | X295: =SUM(X291:X293) -> 0 | Y295: =SUM(Y291:Y293) -> 0 | Z295: =SUM(Z291:Z293) -> 0 | AA295: =SUM(AA291:AA293) -> 1.1387207 | AB295: =SUM(AB291:AB293) -> 146.93402 | AC295: =SUM(AC291:AC293) -> 145.65538 | AD295: =SUM(AD291:AD293) -> 145.14567 | AE295: =SUM(AE291:AE293) -> 144.63847 | ... BQ295: =SUM(BQ291:BQ293) -> 0
P296: Total production | R296: GWh | S296: =SUM(X296:BQ296) -> 32599.874 | X296: =SUM(X294:X295) -> 0 | Y296: =SUM(Y294:Y295) -> 0 | Z296: =SUM(Z294:Z295) -> 0 | AA296: =SUM(AA294:AA295) -> 1.1387207 | AB296: =SUM(AB294:AB295) -> 189.6842 | AC296: =SUM(AC294:AC295) -> 681.31884 | AD296: =SUM(AD294:AD295) -> 874.90015 | AE296: =SUM(AE294:AE295) -> 915.98203 | ... BQ296: =SUM(BQ294:BQ295) -> 0
C302: =+MAX($B$10:C301)+0.1 -> 4.2 | D302: Revenues
P304: Wind 1 | Q304: IT_W1 | R304: €m | S304: =SUM(X304:BQ304) -> 970.11792 | X304: ='Phase II Outputs'!M210/1000 -> 0 | Y304: ='Phase II Outputs'!N210/1000 -> -0.00086975 | Z304: ='Phase II Outputs'!O210/1000 -> -0.3183285 | AA304: ='Phase II Outputs'!P210/1000 -> -0.31745875 | AB304: ='Phase II Outputs'!Q210/1000 -> -0.024779021 | AC304: ='Phase II Outputs'!R210/1000 -> 20.517798 | AD304: ='Phase II Outputs'!S210/1000 -> 20.629576 | AE304: ='Phase II Outputs'!T210/1000 -> 20.728909 | ... BQ304: ='Phase II Outputs'!BF210/1000 -> 0
P305: Wind 2 | Q305: IT_W2 | R305: €m | S305: =SUM(X305:BQ305) -> 159.93218 | X305: ='Phase II Outputs'!M218/1000 -> 0 | Y305: ='Phase II Outputs'!N218/1000 -> -0.00012079861 | Z305: ='Phase II Outputs'!O218/1000 -> -0.044212292 | AA305: ='Phase II Outputs'!P218/1000 -> -0.044091493 | AB305: ='Phase II Outputs'!Q218/1000 -> 1.0941167 | AC305: ='Phase II Outputs'!R218/1000 -> 3.3898935 | AD305: ='Phase II Outputs'!S218/1000 -> 3.408268 | AE305: ='Phase II Outputs'!T218/1000 -> 3.4247154 | ... BQ305: ='Phase II Outputs'!BF218/1000 -> 0
P306: Wind 3 | Q306: IT_W3 | R306: €m | S306: =SUM(X306:BQ306) -> 726.52636 | X306: ='Phase II Outputs'!M226/1000 -> 0 | Y306: ='Phase II Outputs'!N226/1000 -> -0.00049285833 | Z306: ='Phase II Outputs'!O226/1000 -> -0.18038615 | AA306: ='Phase II Outputs'!P226/1000 -> -0.17989329 | AB306: ='Phase II Outputs'!Q226/1000 -> -0.17989329 | AC306: ='Phase II Outputs'!R226/1000 -> 9.2708118 | AD306: ='Phase II Outputs'!S226/1000 -> 15.338619 | AE306: ='Phase II Outputs'!T226/1000 -> 15.412837 | ... BQ306: ='Phase II Outputs'!BF226/1000 -> 0
P307: Wind 4 | Q307: IT_W4 | R307: €m | S307: =SUM(X307:BQ307) -> 539.11422 | X307: ='Phase II Outputs'!M234/1000 -> 0 | Y307: ='Phase II Outputs'!N234/1000 -> -0.00042245 | Z307: ='Phase II Outputs'!O234/1000 -> -0.1546167 | AA307: ='Phase II Outputs'!P234/1000 -> -0.15419425 | AB307: ='Phase II Outputs'!Q234/1000 -> -0.15419425 | AC307: ='Phase II Outputs'!R234/1000 -> 2.3015004 | AD307: ='Phase II Outputs'!S234/1000 -> 11.389798 | AE307: ='Phase II Outputs'!T234/1000 -> 11.444718 | ... BQ307: ='Phase II Outputs'!BF234/1000 -> 0
P308: Wind 5 | Q308: IT_W5 | R308: €m | S308: =SUM(X308:BQ308) -> 452.68213 | X308: ='Phase II Outputs'!M242/1000 -> 0 | Y308: ='Phase II Outputs'!N242/1000 -> -0.00032857222 | Z308: ='Phase II Outputs'!O242/1000 -> -0.12025743 | AA308: ='Phase II Outputs'!P242/1000 -> -0.11992886 | AB308: ='Phase II Outputs'!Q242/1000 -> -0.11992886 | AC308: ='Phase II Outputs'!R242/1000 -> 6.8008416 | AD308: ='Phase II Outputs'!S242/1000 -> 9.5584699 | AE308: ='Phase II Outputs'!T242/1000 -> 9.6047407 | ... BQ308: ='Phase II Outputs'!BF242/1000 -> 0
P309: Wind 6 | Q309: IT_W6 | R309: €m | S309: =SUM(X309:BQ309) -> 165.5846 | X309: ='Phase II Outputs'!M250/1000 -> 0 | Y309: ='Phase II Outputs'!N250/1000 -> -0.00012079861 | Z309: ='Phase II Outputs'!O250/1000 -> -0.044212292 | AA309: ='Phase II Outputs'!P250/1000 -> -0.044091493 | AB309: ='Phase II Outputs'!Q250/1000 -> 1.1473637 | AC309: ='Phase II Outputs'!R250/1000 -> 3.4711947 | AD309: ='Phase II Outputs'!S250/1000 -> 3.4901476 | AE309: ='Phase II Outputs'!T250/1000 -> 3.5070876 | ... BQ309: ='Phase II Outputs'!BF250/1000 -> 0
P310: Wind 7 | Q310: IT_W7 | R310: €m | S310: =SUM(X310:BQ310) -> 124.59803 | X310: ='Phase II Outputs'!M258/1000 -> 0 | Y310: ='Phase II Outputs'!N258/1000 -> -0.00013460417 | Z310: ='Phase II Outputs'!O258/1000 -> -0.049265125 | AA310: ='Phase II Outputs'!P258/1000 -> -0.049130521 | AB310: ='Phase II Outputs'!Q258/1000 -> 1.2487024 | AC310: ='Phase II Outputs'!R258/1000 -> 2.552392 | AD310: ='Phase II Outputs'!S258/1000 -> 2.566344 | AE310: ='Phase II Outputs'!T258/1000 -> 2.5788114 | ... BQ310: ='Phase II Outputs'!BF258/1000 -> 0
P311: Wind 8 | Q311: IT_W8 | R311: €m | S311: =SUM(X311:BQ311) -> 252.63948 | X311: ='Phase II Outputs'!M266/1000 -> 0 | Y311: ='Phase II Outputs'!N266/1000 -> 0 | Z311: ='Phase II Outputs'!O266/1000 -> 0 | AA311: ='Phase II Outputs'!P266/1000 -> -0.00015255139 | AB311: ='Phase II Outputs'!Q266/1000 -> -0.055681257 | AC311: ='Phase II Outputs'!R266/1000 -> -0.055681257 | AD311: ='Phase II Outputs'!S266/1000 -> -0.055833808 | AE311: ='Phase II Outputs'!T266/1000 -> 3.79491 | ... BQ311: ='Phase II Outputs'!BF266/1000 -> 0
P312: Solar 1 | Q312: IT_S1 | R312: €m | S312: =SUM(X312:BQ312) -> 225.86063 | X312: ='Phase II Outputs'!M274/1000 -> 0 | Y312: ='Phase II Outputs'!N274/1000 -> -7.1465625e-05 | Z312: ='Phase II Outputs'!O274/1000 -> -0.026156419 | AA312: ='Phase II Outputs'!P274/1000 -> 0.054564101 | AB312: ='Phase II Outputs'!Q274/1000 -> 5.3976632 | AC312: ='Phase II Outputs'!R274/1000 -> 5.3985157 | AD312: ='Phase II Outputs'!S274/1000 -> 5.4150759 | AE312: ='Phase II Outputs'!T274/1000 -> 5.4275417 | ... BQ312: ='Phase II Outputs'!BF274/1000 -> 0
...

Sheet NBO Case >>

Sheet NBO Case Outputs
A1: TS_Output_Annual
A2: Project Ardagh
A3: Phase II Seller
A4: EV (€'m): 1,020,452.3 | EqV (€'m): 726,982.2
A5: Tab_Check | F5: #VALUE!
A6: Master_Check | F6: #VALUE!
F8: Units | G8: Input_1 | H8: Input_2 | I8: Totals | BU8: Check
D9: Period Beginning | K9: 45292 | L9: 45658 | M9: 46023 | N9: 46388 | O9: 46753 | P9: 47119 | Q9: 47484 | R9: 47849 | S9: 48214 | T9: 48580 | U9: 48945 | V9: 49310 | W9: 49675 | X9: 50041 | Y9: 50406 | Z9: 50771 | AA9: 51136 | AB9: 51502 | AC9: 51867 | AD9: 52232 | AE9: 52597 | AF9: 52963 | AG9: 53328 | AH9: 53693 | AI9: 54058 | AJ9: 54424 | AK9: 54789 | AL9: 55154 | AM9: 55519 | AN9: 55885 | AO9: 56250 | AP9: 56615 | AQ9: 56980 | AR9: 57346 | AS9: 57711 | AT9: 58076 | AU9: 58441 | AV9: 58807 | AW9: 59172 | AX9: 59537 | AY9: 59902 | AZ9: 60268 | BA9: 60633 | BB9: 60998 | BC9: 61363 | BD9: 61729 | BE9: 62094 | BF9: 62459 | BG9: 62824 | BH9: 63190 | BI9: 63555 | BJ9: 63920 | BK9: 64285 | BL9: 64651 | BM9: 65016 | BN9: 65381 | BO9: 65746 | BP9: 66112 | BQ9: 66477 | BR9: 66842 | BS9: 67207
D10: Period End | K10: 45657 | L10: 46022 | M10: 46387 | N10: 46752 | O10: 47118 | P10: 47483 | Q10: 47848 | R10: 48213 | S10: 48579 | T10: 48944 | U10: 49309 | V10: 49674 | W10: 50040 | X10: 50405 | Y10: 50770 | Z10: 51135 | AA10: 51501 | AB10: 51866 | AC10: 52231 | AD10: 52596 | AE10: 52962 | AF10: 53327 | AG10: 53692 | AH10: 54057 | AI10: 54423 | AJ10: 54788 | AK10: 55153 | AL10: 55518 | AM10: 55884 | AN10: 56249 | AO10: 56614 | AP10: 56979 | AQ10: 57345 | AR10: 57710 | AS10: 58075 | AT10: 58440 | AU10: 58806 | AV10: 59171 | AW10: 59536 | AX10: 59901 | AY10: 60267 | AZ10: 60632 | BA10: 60997 | BB10: 61362 | BC10: 61728 | BD10: 62093 | BE10: 62458 | BF10: 62823 | BG10: 63189 | BH10: 63554 | BI10: 63919 | BJ10: 64284 | BK10: 64650 | BL10: 65015 | BM10: 65380 | BN10: 65745 | BO10: 66111 | BP10: 66476 | BQ10: 66841 | BR10: 67206 | BS10: 67572
D11: Year | K11: 2024 | L11: 2025 | M11: 2026 | N11: 2027 | O11: 2028 | P11: 2029 | Q11: 2030 | R11: 2031 | S11: 2032 | T11: 2033 | U11: 2034 | V11: 2035 | W11: 2036 | X11: 2037 | Y11: 2038 | Z11: 2039 | AA11: 2040 | AB11: 2041 | AC11: 2042 | AD11: 2043 | AE11: 2044 | AF11: 2045 | AG11: 2046 | AH11: 2047 | AI11: 2048 | AJ11: 2049 | AK11: 2050 | AL11: 2051 | AM11: 2052 | AN11: 2053 | AO11: 2054 | AP11: 2055 | AQ11: 2056 | AR11: 2057 | AS11: 2058 | AT11: 2059 | AU11: 2060 | AV11: 2061 | AW11: 2062 | AX11: 2063 | AY11: 2064 | AZ11: 2065 | BA11: 2066 | BB11: 2067 | BC11: 2068 | BD11: 2069 | BE11: 2070 | BF11: 2071 | BG11: 2072 | BH11: 2073 | BI11: 2074 | BJ11: 2075 | BK11: 2076 | BL11: 2077 | BM11: 2078 | BN11: 2079 | BO11: 2080 | BP11: 2081 | BQ11: 2082 | BR11: 2083 | BS11: 2084
D12: Periods | K12: 1 | L12: 1 | M12: 2 | N12: 2 | O12: 2 | P12: 2 | Q12: 2 | R12: 2 | S12: 2 | T12: 2 | U12: 2 | V12: 2 | W12: 2 | X12: 2 | Y12: 2 | Z12: 2 | AA12: 2 | AB12: 2 | AC12: 2 | AD12: 2 | AE12: 2 | AF12: 2 | AG12: 2 | AH12: 2 | AI12: 2 | AJ12: 2 | AK12: 2 | AL12: 2 | AM12: 2 | AN12: 2 | AO12: 2 | AP12: 2 | AQ12: 2 | AR12: 2 | AS12: 2 | AT12: 2 | AU12: 2 | AV12: 2 | AW12: 2 | AX12: 2 | AY12: 2 | AZ12: 2 | BA12: 2 | BB12: 2 | BC12: 2 | BD12: 2 | BE12: 2 | BF12: 2 | BG12: 2 | BH12: 2 | BI12: 2 | BJ12: 2 | BK12: 2 | BL12: 2 | BM12: 2 | BN12: 2 | BO12: 2 | BP12: 2 | BQ12: 2 | BR12: 2 | BS12: 1
D13: Days | K13: 366 | L13: 365 | M13: 365 | N13: 365 | O13: 366 | P13: 365 | Q13: 365 | R13: 365 | S13: 366 | T13: 365 | U13: 365 | V13: 365 | W13: 366 | X13: 365 | Y13: 365 | Z13: 365 | AA13: 366 | AB13: 365 | AC13: 365 | AD13: 365 | AE13: 366 | AF13: 365 | AG13: 365 | AH13: 365 | AI13: 366 | AJ13: 365 | AK13: 365 | AL13: 365 | AM13: 366 | AN13: 365 | AO13: 365 | AP13: 365 | AQ13: 366 | AR13: 365 | AS13: 365 | AT13: 365 | AU13: 366 | AV13: 365 | AW13: 365 | AX13: 365 | AY13: 366 | AZ13: 365 | BA13: 365 | BB13: 365 | BC13: 366 | BD13: 365 | BE13: 365 | BF13: 365 | BG13: 366 | BH13: 365 | BI13: 365 | BJ13: 365 | BK13: 366 | BL13: 365 | BM13: 365 | BN13: 365 | BO13: 366 | BP13: 365 | BQ13: 365 | BR13: 365 | BS13: 182
D14: Days vs full year | K14: 0 | L14: 0 | M14: 0 | N14: 0 | O14: 0 | P14: 0 | Q14: 0 | R14: 0 | S14: 0 | T14: 0 | U14: 0 | V14: 0 | W14: 0 | X14: 0 | Y14: 0 | Z14: 0 | AA14: 0 | AB14: 0 | AC14: 0 | AD14: 0 | AE14: 0 | AF14: 0 | AG14: 0 | AH14: 0 | AI14: 0 | AJ14: 0 | AK14: 0 | AL14: 0 | AM14: 0 | AN14: 0 | AO14: 0 | AP14: 0 | AQ14: 0 | AR14: 0 | AS14: 0 | AT14: 0 | AU14: 0 | AV14: 0 | AW14: 0 | AX14: 0 | AY14: 0 | AZ14: 0 | BA14: 0 | BB14: 0 | BC14: 0 | BD14: 0 | BE14: 0 | BF14: 0 | BG14: 0 | BH14: 0 | BI14: 0 | BJ14: 0 | BK14: 0 | BL14: 0 | BM14: 0 | BN14: 0 | BO14: 0 | BP14: 0 | BQ14: 0 | BR14: 0 | BS14: -184
D15: Year Counter | K15: 1 | L15: 2 | M15: 3 | N15: 4 | O15: 5 | P15: 6 | Q15: 7 | R15: 8 | S15: 9 | T15: 10 | U15: 11 | V15: 12 | W15: 13 | X15: 14 | Y15: 15 | Z15: 16 | AA15: 17 | AB15: 18 | AC15: 19 | AD15: 20 | AE15: 21 | AF15: 22 | AG15: 23 | AH15: 24 | AI15: 25 | AJ15: 26 | AK15: 27 | AL15: 28 | AM15: 29 | AN15: 30 | AO15: 31 | AP15: 32 | AQ15: 33 | AR15: 34 | AS15: 35 | AT15: 36 | AU15: 37 | AV15: 38 | AW15: 39 | AX15: 40 | AY15: 41 | AZ15: 42 | BA15: 43 | BB15: 44 | BC15: 45 | BD15: 46 | BE15: 47 | BF15: 48 | BG15: 49 | BH15: 50 | BI15: 51 | BJ15: 52 | BK15: 53 | BL15: 54 | BM15: 55 | BN15: 56 | BO15: 57 | BP15: 58 | BQ15: 59 | BR15: 60 | BS15: 61
B17: 1 | E17: Valuation Summary
K19: 1 | L19: 2 | M19: 3 | N19: 4 | O19: 5 | P19: 6 | Q19: 7 | R19: 8 | S19: 9 | T19: 10 | U19: 11 | V19: 12 | W19: 13 | X19: 14 | Y19: 15 | Z19: 16 | AA19: 17 | AB19: 18 | AC19: 19 | AD19: 20 | AE19: 21 | AF19: 22 | AG19: 23 | AH19: 24 | AI19: 25 | AJ19: 26 | AK19: 27 | AL19: 28 | AM19: 29 | AN19: 30 | AO19: 31 | AP19: 32 | AQ19: 33 | AR19: 34 | AS19: 35 | AT19: 36 | AU19: 37 | AV19: 38 | AW19: 39 | AX19: 40 | AY19: 41 | AZ19: 42 | BA19: 43 | BB19: 44 | BC19: 45 | BD19: 46 | BE19: 47 | BF19: 48 | BG19: 49 | BH19: 50 | BI19: 51 | BJ19: 52 | BK19: 53 | BL19: 54 | BM19: 55 | BN19: 56 | BO19: 57 | BP19: 58 | BQ19: 59 | BR19: 60 | BS19: 61
E28: MW | F28: 254
E30: Production | F30: 284
E32: PPA Revenue | F32: 356
E33: Merchant Revenue | F33: 357
E34: GoOs Revenue | F34: 358
E35: Total BESS Revenue | F35: 429
E36: Other Revenue Cost/Income | F36: 430
E38: EBITDA | F38: 24
E40: Production | F40: 284
E42: OPEX | F42: 662
C46: o | E46: MW
B50: GR_W1 | E50: GR_W1 | I50: 293 | K50: 293 | L50: 0 | M50: 0 | N50: 0 | O50: 0 | P50: 0 | Q50: 0 | R50: 0 | S50: 0 | T50: 0 | U50: 0 | V50: 0 | W50: 0 | X50: 0 | Y50: 0 | Z50: 0 | AA50: 0 | AB50: 0 | AC50: 0 | AD50: 0 | AE50: 0 | AF50: 0 | AG50: 0 | AH50: 0 | AI50: 0 | AJ50: 0 | AK50: 0 | AL50: 0 | AM50: 0 | AN50: 0 | AO50: 0 | AP50: 0 | AQ50: 0 | AR50: 0 | AS50: 0 | AT50: 0 | AU50: 0 | AV50: 0 | AW50: 0 | AX50: 0 | AY50: 0 | AZ50: 0 | BA50: 0 | BB50: 0 | BC50: 0 | BD50: 0 | BE50: 0 | BF50: 0 | BG50: 0 | BH50: 0 | BI50: 0 | BJ50: 0 | BK50: 0 | BL50: 0 | BM50: 0 | BN50: 0 | BO50: 0 | BP50: 0 | BQ50: 0 | BR50: 0 | BS50: 0
E51: GR_W2 | I51: 0 | K51: 0 | L51: 0 | M51: 0 | N51: 0 | O51: 0 | P51: 0 | Q51: 0 | R51: 0 | S51: 0 | T51: 0 | U51: 0 | V51: 0 | W51: 0 | X51: 0 | Y51: 0 | Z51: 0 | AA51: 0 | AB51: 0 | AC51: 0 | AD51: 0 | AE51: 0 | AF51: 0 | AG51: 0 | AH51: 0 | AI51: 0 | AJ51: 0 | AK51: 0 | AL51: 0 | AM51: 0 | AN51: 0 | AO51: 0 | AP51: 0 | AQ51: 0 | AR51: 0 | AS51: 0 | AT51: 0 | AU51: 0 | AV51: 0 | AW51: 0 | AX51: 0 | AY51: 0 | AZ51: 0 | BA51: 0 | BB51: 0 | BC51: 0 | BD51: 0 | BE51: 0 | BF51: 0 | BG51: 0 | BH51: 0 | BI51: 0 | BJ51: 0 | BK51: 0 | BL51: 0 | BM51: 0 | BN51: 0 | BO51: 0 | BP51: 0 | BQ51: 0 | BR51: 0 | BS51: 0
E52: GR_W3 | I52: 0 | K52: 0 | L52: 0 | M52: 0 | N52: 0 | O52: 0 | P52: 0 | Q52: 0 | R52: 0 | S52: 0 | T52: 0 | U52: 0 | V52: 0 | W52: 0 | X52: 0 | Y52: 0 | Z52: 0 | AA52: 0 | AB52: 0 | AC52: 0 | AD52: 0 | AE52: 0 | AF52: 0 | AG52: 0 | AH52: 0 | AI52: 0 | AJ52: 0 | AK52: 0 | AL52: 0 | AM52: 0 | AN52: 0 | AO52: 0 | AP52: 0 | AQ52: 0 | AR52: 0 | AS52: 0 | AT52: 0 | AU52: 0 | AV52: 0 | AW52: 0 | AX52: 0 | AY52: 0 | AZ52: 0 | BA52: 0 | BB52: 0 | BC52: 0 | BD52: 0 | BE52: 0 | BF52: 0 | BG52: 0 | BH52: 0 | BI52: 0 | BJ52: 0 | BK52: 0 | BL52: 0 | BM52: 0 | BN52: 0 | BO52: 0 | BP52: 0 | BQ52: 0 | BR52: 0 | BS52: 0
E53: GR_W4 | I53: 0 | K53: 0 | L53: 0 | M53: 0 | N53: 0 | O53: 0 | P53: 0 | Q53: 0 | R53: 0 | S53: 0 | T53: 0 | U53: 0 | V53: 0 | W53: 0 | X53: 0 | Y53: 0 | Z53: 0 | AA53: 0 | AB53: 0 | AC53: 0 | AD53: 0 | AE53: 0 | AF53: 0 | AG53: 0 | AH53: 0 | AI53: 0 | AJ53: 0 | AK53: 0 | AL53: 0 | AM53: 0 | AN53: 0 | AO53: 0 | AP53: 0 | AQ53: 0 | AR53: 0 | AS53: 0 | AT53: 0 | AU53: 0 | AV53: 0 | AW53: 0 | AX53: 0 | AY53: 0 | AZ53: 0 | BA53: 0 | BB53: 0 | BC53: 0 | BD53: 0 | BE53: 0 | BF53: 0 | BG53: 0 | BH53: 0 | BI53: 0 | BJ53: 0 | BK53: 0 | BL53: 0 | BM53: 0 | BN53: 0 | BO53: 0 | BP53: 0 | BQ53: 0 | BR53: 0 | BS53: 0
E54: GR_W5 | I54: 0 | K54: 0 | L54: 0 | M54: 0 | N54: 0 | O54: 0 | P54: 0 | Q54: 0 | R54: 0 | S54: 0 | T54: 0 | U54: 0 | V54: 0 | W54: 0 | X54: 0 | Y54: 0 | Z54: 0 | AA54: 0 | AB54: 0 | AC54: 0 | AD54: 0 | AE54: 0 | AF54: 0 | AG54: 0 | AH54: 0 | AI54: 0 | AJ54: 0 | AK54: 0 | AL54: 0 | AM54: 0 | AN54: 0 | AO54: 0 | AP54: 0 | AQ54: 0 | AR54: 0 | AS54: 0 | AT54: 0 | AU54: 0 | AV54: 0 | AW54: 0 | AX54: 0 | AY54: 0 | AZ54: 0 | BA54: 0 | BB54: 0 | BC54: 0 | BD54: 0 | BE54: 0 | BF54: 0 | BG54: 0 | BH54: 0 | BI54: 0 | BJ54: 0 | BK54: 0 | BL54: 0 | BM54: 0 | BN54: 0 | BO54: 0 | BP54: 0 | BQ54: 0 | BR54: 0 | BS54: 0
E55: IT_W1 | I55: 0 | K55: 0 | L55: 0 | M55: 0 | N55: 0 | O55: 0 | P55: 0 | Q55: 0 | R55: 0 | S55: 0 | T55: 0 | U55: 0 | V55: 0 | W55: 0 | X55: 0 | Y55: 0 | Z55: 0 | AA55: 0 | AB55: 0 | AC55: 0 | AD55: 0 | AE55: 0 | AF55: 0 | AG55: 0 | AH55: 0 | AI55: 0 | AJ55: 0 | AK55: 0 | AL55: 0 | AM55: 0 | AN55: 0 | AO55: 0 | AP55: 0 | AQ55: 0 | AR55: 0 | AS55: 0 | AT55: 0 | AU55: 0 | AV55: 0 | AW55: 0 | AX55: 0 | AY55: 0 | AZ55: 0 | BA55: 0 | BB55: 0 | BC55: 0 | BD55: 0 | BE55: 0 | BF55: 0 | BG55: 0 | BH55: 0 | BI55: 0 | BJ55: 0 | BK55: 0 | BL55: 0 | BM55: 0 | BN55: 0 | BO55: 0 | BP55: 0 | BQ55: 0 | BR55: 0 | BS55: 0
E56: IT_W2 | I56: 0 | K56: 0 | L56: 0 | M56: 0 | N56: 0 | O56: 0 | P56: 0 | Q56: 0 | R56: 0 | S56: 0 | T56: 0 | U56: 0 | V56: 0 | W56: 0 | X56: 0 | Y56: 0 | Z56: 0 | AA56: 0 | AB56: 0 | AC56: 0 | AD56: 0 | AE56: 0 | AF56: 0 | AG56: 0 | AH56: 0 | AI56: 0 | AJ56: 0 | AK56: 0 | AL56: 0 | AM56: 0 | AN56: 0 | AO56: 0 | AP56: 0 | AQ56: 0 | AR56: 0 | AS56: 0 | AT56: 0 | AU56: 0 | AV56: 0 | AW56: 0 | AX56: 0 | AY56: 0 | AZ56: 0 | BA56: 0 | BB56: 0 | BC56: 0 | BD56: 0 | BE56: 0 | BF56: 0 | BG56: 0 | BH56: 0 | BI56: 0 | BJ56: 0 | BK56: 0 | BL56: 0 | BM56: 0 | BN56: 0 | BO56: 0 | BP56: 0 | BQ56: 0 | BR56: 0 | BS56: 0
E57: IT_W3 | I57: 0 | K57: 0 | L57: 0 | M57: 0 | N57: 0 | O57: 0 | P57: 0 | Q57: 0 | R57: 0 | S57: 0 | T57: 0 | U57: 0 | V57: 0 | W57: 0 | X57: 0 | Y57: 0 | Z57: 0 | AA57: 0 | AB57: 0 | AC57: 0 | AD57: 0 | AE57: 0 | AF57: 0 | AG57: 0 | AH57: 0 | AI57: 0 | AJ57: 0 | AK57: 0 | AL57: 0 | AM57: 0 | AN57: 0 | AO57: 0 | AP57: 0 | AQ57: 0 | AR57: 0 | AS57: 0 | AT57: 0 | AU57: 0 | AV57: 0 | AW57: 0 | AX57: 0 | AY57: 0 | AZ57: 0 | BA57: 0 | BB57: 0 | BC57: 0 | BD57: 0 | BE57: 0 | BF57: 0 | BG57: 0 | BH57: 0 | BI57: 0 | BJ57: 0 | BK57: 0 | BL57: 0 | BM57: 0 | BN57: 0 | BO57: 0 | BP57: 0 | BQ57: 0 | BR57: 0 | BS57: 0
E58: IT_W4 | I58: 0 | K58: 0 | L58: 0 | M58: 0 | N58: 0 | O58: 0 | P58: 0 | Q58: 0 | R58: 0 | S58: 0 | T58: 0 | U58: 0 | V58: 0 | W58: 0 | X58: 0 | Y58: 0 | Z58: 0 | AA58: 0 | AB58: 0 | AC58: 0 | AD58: 0 | AE58: 0 | AF58: 0 | AG58: 0 | AH58: 0 | AI58: 0 | AJ58: 0 | AK58: 0 | AL58: 0 | AM58: 0 | AN58: 0 | AO58: 0 | AP58: 0 | AQ58: 0 | AR58: 0 | AS58: 0 | AT58: 0 | AU58: 0 | AV58: 0 | AW58: 0 | AX58: 0 | AY58: 0 | AZ58: 0 | BA58: 0 | BB58: 0 | BC58: 0 | BD58: 0 | BE58: 0 | BF58: 0 | BG58: 0 | BH58: 0 | BI58: 0 | BJ58: 0 | BK58: 0 | BL58: 0 | BM58: 0 | BN58: 0 | BO58: 0 | BP58: 0 | BQ58: 0 | BR58: 0 | BS58: 0
E59: IT_W5 | I59: 0 | K59: 0 | L59: 0 | M59: 0 | N59: 0 | O59: 0 | P59: 0 | Q59: 0 | R59: 0 | S59: 0 | T59: 0 | U59: 0 | V59: 0 | W59: 0 | X59: 0 | Y59: 0 | Z59: 0 | AA59: 0 | AB59: 0 | AC59: 0 | AD59: 0 | AE59: 0 | AF59: 0 | AG59: 0 | AH59: 0 | AI59: 0 | AJ59: 0 | AK59: 0 | AL59: 0 | AM59: 0 | AN59: 0 | AO59: 0 | AP59: 0 | AQ59: 0 | AR59: 0 | AS59: 0 | AT59: 0 | AU59: 0 | AV59: 0 | AW59: 0 | AX59: 0 | AY59: 0 | AZ59: 0 | BA59: 0 | BB59: 0 | BC59: 0 | BD59: 0 | BE59: 0 | BF59: 0 | BG59: 0 | BH59: 0 | BI59: 0 | BJ59: 0 | BK59: 0 | BL59: 0 | BM59: 0 | BN59: 0 | BO59: 0 | BP59: 0 | BQ59: 0 | BR59: 0 | BS59: 0
E60: IT_W6 | I60: 0 | K60: 0 | L60: 0 | M60: 0 | N60: 0 | O60: 0 | P60: 0 | Q60: 0 | R60: 0 | S60: 0 | T60: 0 | U60: 0 | V60: 0 | W60: 0 | X60: 0 | Y60: 0 | Z60: 0 | AA60: 0 | AB60: 0 | AC60: 0 | AD60: 0 | AE60: 0 | AF60: 0 | AG60: 0 | AH60: 0 | AI60: 0 | AJ60: 0 | AK60: 0 | AL60: 0 | AM60: 0 | AN60: 0 | AO60: 0 | AP60: 0 | AQ60: 0 | AR60: 0 | AS60: 0 | AT60: 0 | AU60: 0 | AV60: 0 | AW60: 0 | AX60: 0 | AY60: 0 | AZ60: 0 | BA60: 0 | BB60: 0 | BC60: 0 | BD60: 0 | BE60: 0 | BF60: 0 | BG60: 0 | BH60: 0 | BI60: 0 | BJ60: 0 | BK60: 0 | BL60: 0 | BM60: 0 | BN60: 0 | BO60: 0 | BP60: 0 | BQ60: 0 | BR60: 0 | BS60: 0
E61: IT_W7 | I61: 0 | K61: 0 | L61: 0 | M61: 0 | N61: 0 | O61: 0 | P61: 0 | Q61: 0 | R61: 0 | S61: 0 | T61: 0 | U61: 0 | V61: 0 | W61: 0 | X61: 0 | Y61: 0 | Z61: 0 | AA61: 0 | AB61: 0 | AC61: 0 | AD61: 0 | AE61: 0 | AF61: 0 | AG61: 0 | AH61: 0 | AI61: 0 | AJ61: 0 | AK61: 0 | AL61: 0 | AM61: 0 | AN61: 0 | AO61: 0 | AP61: 0 | AQ61: 0 | AR61: 0 | AS61: 0 | AT61: 0 | AU61: 0 | AV61: 0 | AW61: 0 | AX61: 0 | AY61: 0 | AZ61: 0 | BA61: 0 | BB61: 0 | BC61: 0 | BD61: 0 | BE61: 0 | BF61: 0 | BG61: 0 | BH61: 0 | BI61: 0 | BJ61: 0 | BK61: 0 | BL61: 0 | BM61: 0 | BN61: 0 | BO61: 0 | BP61: 0 | BQ61: 0 | BR61: 0 | BS61: 0
E62: IT_W8 | I62: 0 | K62: 0 | L62: 0 | M62: 0 | N62: 0 | O62: 0 | P62: 0 | Q62: 0 | R62: 0 | S62: 0 | T62: 0 | U62: 0 | V62: 0 | W62: 0 | X62: 0 | Y62: 0 | Z62: 0 | AA62: 0 | AB62: 0 | AC62: 0 | AD62: 0 | AE62: 0 | AF62: 0 | AG62: 0 | AH62: 0 | AI62: 0 | AJ62: 0 | AK62: 0 | AL62: 0 | AM62: 0 | AN62: 0 | AO62: 0 | AP62: 0 | AQ62: 0 | AR62: 0 | AS62: 0 | AT62: 0 | AU62: 0 | AV62: 0 | AW62: 0 | AX62: 0 | AY62: 0 | AZ62: 0 | BA62: 0 | BB62: 0 | BC62: 0 | BD62: 0 | BE62: 0 | BF62: 0 | BG62: 0 | BH62: 0 | BI62: 0 | BJ62: 0 | BK62: 0 | BL62: 0 | BM62: 0 | BN62: 0 | BO62: 0 | BP62: 0 | BQ62: 0 | BR62: 0 | BS62: 0
... E80: PT_W2 | I80: 0 | K80: 0 | L80: 0 | M80: 0 | N80: 0 | O80: 0 | P80: 0 | Q80: 0 | R80: 0 | S80: 0 | T80: 0 | U80: 0 | V80: 0 | W80: 0 | X80: 0 | Y80: 0 | Z80: 0 | AA80: 0 | AB80: 0 | AC80: 0 | AD80: 0 | AE80: 0 | AF80: 0 | AG80: 0 | AH80: 0 | AI80: 0 | AJ80: 0 | AK80: 0 | AL80: 0 | AM80: 0 | AN80: 0 | AO80: 0 | AP80: 0 | AQ80: 0 | AR80: 0 | AS80: 0 | AT80: 0 | AU80: 0 | AV80: 0 | AW80: 0 | AX80: 0 | AY80: 0 | AZ80: 0 | BA80: 0 | BB80: 0 | BC80: 0 | BD80: 0 | BE80: 0 | BF80: 0 | BG80: 0 | BH80: 0 | BI80: 0 | BJ80: 0 | BK80: 0 | BL80: 0 | BM80: 0 | BN80: 0 | BO80: 0 | BP80: 0 | BQ80: 0 | BR80: 0 | BS80: 0
C88: o | E88: Production
B90: Gr_W1 | E90: Production | F90: MWh | I90: 18134357 | K90: 0 | L90: 0 | M90: 313957.31 | N90: 593407.4 | O90: 603469.88 | P90: 607225.88 | Q90: 610915.77 | R90: 615358.8 | S90: 614461.26 | T90: 613510.87 | U90: 613510.87 | V90: 612615.14 | W90: 611666.66 | X90: 610772.71 | Y90: 609826.13 | Z90: 609826.13 | AA90: 608933.99 | AB90: 607989.31 | AC90: 607098.95 | AD90: 606156.18 | AE90: 606156.18 | AF90: 605267.61 | AG90: 601570.4 | AH90: 598283.47 | AI90: 597405.56 | AJ90: 596475.97 | AK90: 595599.83 | AL90: 586453.02 | AM90: 576651.74 | AN90: 575803.86 | AO90: 574906.08 | AP90: 574059.91 | AQ90: 375019.78 | AR90: 0 | AS90: 0 | AT90: 0 | AU90: 0 | AV90: 0 | AW90: 0 | AX90: 0 | AY90: 0 | AZ90: 0 | BA90: 0 | BB90: 0 | BC90: 0 | BD90: 0 | BE90: 0 | BF90: 0 | BG90: 0 | BH90: 0 | BI90: 0 | BJ90: 0 | BK90: 0 | BL90: 0 | BM90: 0 | BN90: 0 | BO90: 0 | BP90: 0 | BQ90: 0 | BR90: 0 | BS90: 0 | BU90: 0
B92: Gr_W2 | E92: Production | F92: MWh | I92: 2309060.9 | K92: 0 | L92: 0 | M92: 48551.014 | N92: 75540.14 | O92: 76819.752 | P92: 77297.964 | Q92: 77767.59 | R92: 78333.173 | S92: 78219.005 | T92: 78097.938 | U92: 78097.938 | V92: 77983.999 | W92: 77863.175 | X92: 77749.465 | Y92: 77628.883 | Z92: 77628.883 | AA92: 77515.401 | AB92: 77395.061 | AC92: 77281.807 | AD92: 77161.709 | AE92: 77161.709 | AF92: 77048.683 | AG92: 76406.4 | AH92: 75780.635 | AI92: 75669.52 | AJ92: 75551.691 | AK92: 75440.8 | AL92: 74284.661 | AM92: 73040.687 | AN92: 72933.373 | AO92: 72819.575 | AP92: 72712.478 | AQ92: 43277.838 | AR92: 0 | AS92: 0 | AT92: 0 | AU92: 0 | AV92: 0 | AW92: 0 | AX92: 0 | AY92: 0 | AZ92: 0 | BA92: 0 | BB92: 0 | BC92: 0 | BD92: 0 | BE92: 0 | BF92: 0 | BG92: 0 | BH92: 0 | BI92: 0 | BJ92: 0 | BK92: 0 | BL92: 0 | BM92: 0 | BN92: 0 | BO92: 0 | BP92: 0 | BQ92: 0 | BR92: 0 | BS92: 0 | BU92: 0
B94: Gr_W3 | E94: Production | F94: MWh | I94: 2124541.6 | K94: 0 | L94: 0 | M94: 44310.003 | N94: 69490.303 | O94: 70673.387 | P94: 71114.002 | Q94: 71545.388 | R94: 72065.718 | S94: 71961.36 | T94: 71849.304 | U94: 71849.304 | V94: 71745.156 | W94: 71633.325 | X94: 71529.385 | Y94: 71417.778 | Z94: 71417.778 | AA94: 71314.047 | AB94: 71202.665 | AC94: 71099.142 | AD94: 70987.983 | AE94: 70987.983 | AF94: 70884.669 | AG94: 70302.989 | AH94: 69717.41 | AI94: 69615.842 | AJ94: 69506.783 | AK94: 69405.42 | AL94: 68360.774 | AM94: 67196.685 | AN94: 67098.592 | AO94: 66993.264 | AP94: 66895.369 | AQ94: 40369.814 | AR94: 0 | AS94: 0 | AT94: 0 | AU94: 0 | AV94: 0 | AW94: 0 | AX94: 0 | AY94: 0 | AZ94: 0 | BA94: 0 | BB94: 0 | BC94: 0 | BD94: 0 | BE94: 0 | BF94: 0 | BG94: 0 | BH94: 0 | BI94: 0 | BJ94: 0 | BK94: 0 | BL94: 0 | BM94: 0 | BN94: 0 | BO94: 0 | BP94: 0 | BQ94: 0 | BR94: 0 | BS94: 0 | BU94: 0
B96: Gr_W4 | E96: Production | F96: MWh | I96: 3043300.5 | K96: 0 | L96: 0 | M96: 0 | N96: 0 | O96: 48613.544 | P96: 102175.48 | Q96: 103330.12 | R96: 104081.61 | S96: 103926.9 | T96: 103769.05 | U96: 103769.05 | V96: 103614.66 | W96: 103457.12 | X96: 103303.04 | Y96: 103145.82 | Z96: 103145.82 | AA96: 102992.04 | AB96: 102835.14 | AC96: 102681.67 | AD96: 102525.08 | AE96: 102525.08 | AF96: 102371.92 | AG96: 102215.65 | AH96: 102215.65 | AI96: 101326.05 | AJ96: 100385.84 | AK96: 100235.58 | AL96: 100082.26 | AM96: 100082.26 | AN96: 98467.689 | AO96: 96755.67 | AP96: 96610.546 | AQ96: 96462.471 | AR96: 96462.471 | AS96: 49735.254 | AT96: 0 | AU96: 0 | AV96: 0 | AW96: 0 | AX96: 0 | AY96: 0 | AZ96: 0 | BA96: 0 | BB96: 0 | BC96: 0 | BD96: 0 | BE96: 0 | BF96: 0 | BG96: 0 | BH96: 0 | BI96: 0 | BJ96: 0 | BK96: 0 | BL96: 0 | BM96: 0 | BN96: 0 | BO96: 0 | BP96: 0 | BQ96: 0 | BR96: 0 | BS96: 0 | BU96: 0
B98: Gr_W5 | E98: Production | F98: MWh | I98: 1374836.6 | K98: 0 | L98: 0 | M98: 0 | N98: 0 | O98: 18922.014 | P98: 39739.233 | Q98: 39844.129 | R98: 39884.173 | S98: 39944.881 | T98: 39844.249 | U98: 39924.098 | V98: 39864.731 | W98: 39804.085 | X98: 39744.838 | Y98: 39684.314 | Z98: 39684.314 | AA98: 39625.186 | AB98: 39564.783 | AC98: 39505.773 | AD98: 39445.492 | AE98: 39445.492 | AF98: 39386.601 | AG98: 39326.441 | AH98: 39326.441 | AI98: 38984.738 | AJ98: 38622.442 | AK98: 38564.664 | AL98: 38505.64 | AM98: 38505.64 | AN98: 38260.497 | AO98: 38001.306 | AP98: 37944.342 | AQ98: 37886.151 | AR98: 37886.151 | AS98: 37642.955 | AT98: 37385.807 | AU98: 37385.807 | AV98: 37385.807 | AW98: 37385.807 | AX98: 31977.564 | AY98: 0 | AZ98: 0 | BA98: 0 | BB98: 0 | BC98: 0 | BD98: 0 | BE98: 0 | BF98: 0 | BG98: 0 | BH98: 0 | BI98: 0 | BJ98: 0 | BK98: 0 | BL98: 0 | BM98: 0 | BN98: 0 | BO98: 0 | BP98: 0 | BQ98: 0 | BR98: 0 | BS98: 0 | BU98: 0
C100: 0 | E100: Greece | I100: 26986096 | K100: 0 | L100: 0 | M100: 406818.33 | N100: 738437.85 | O100: 818498.58 | P100: 897552.56 | Q100: 903403 | R100: 909723.47 | S100: 908513.41 | T100: 907071.42 | U100: 907151.27 | V100: 905823.68 | W100: 904424.36 | X100: 903099.44 | Y100: 901702.93 | Z100: 901702.93 | AA100: 900380.66 | AB100: 898986.96 | AC100: 897667.35 | AD100: 896276.44 | AE100: 896276.44 | AF100: 894959.49 | AG100: 889821.88 | AH100: 885323.6 | AI100: 883001.7 | AJ100: 880542.73 | AK100: 879246.29 | AL100: 867686.35 | AM100: 855477.01 | AN100: 852564.02 | AO100: 849475.89 | AP100: 848222.65 | AQ100: 593016.06 | AR100: 134348.62 | AS100: 87378.209 | AT100: 37385.807 | AU100: 37385.807 | AV100: 37385.807 | AW100: 37385.807 | AX100: 31977.564 | AY100: 0 | AZ100: 0 | BA100: 0 | BB100: 0 | BC100: 0 | BD100: 0 | BE100: 0 | BF100: 0 | BG100: 0 | BH100: 0 | BI100: 0 | BJ100: 0 | BK100: 0 | BL100: 0 | BM100: 0 | BN100: 0 | BO100: 0 | BP100: 0 | BQ100: 0 | BR100: 0 | BS100: 0 | BU100: 0
B102: IT_W1 | E102: Production | F102: MWh | I102: 7756680.9 | K102: 0 | L102: 0 | M102: 0 | N102: 0 | O102: 0 | P102: 0 | Q102: 3225.0625 | R102: 224481.32 | S102: 224481.32 | T102: 224481.32 | U102: 224481.32 | V102: 224481.32 | W102: 224481.32 | X102: 224481.32 | Y102: 224481.32 | Z102: 224481.32 | AA102: 224481.32 | AB102: 224481.32 | AC102: 224481.32 | AD102: 224481.32 | AE102: 224481.32 | AF102: 224481.32 | AG102: 224481.32 | AH102: 224481.32 | AI102: 224481.32 | AJ102: 224481.32 | AK102: 223415.04 | AL102: 222236.51 | AM102: 222236.51 | AN102: 222236.51 | AO102: 222236.51 | AP102: 221170.22 | AQ102: 219991.7 | AR102: 219991.7 | AS102: 219991.7 | AT102: 219991.7 | AU102: 218925.41 | AV102: 217746.88 | AW102: 217746.88 | AX102: 217746.88 | AY102: 217746.88 | AZ102: 184899.62 | BA102: 0 | BB102: 0 | BC102: 0 | BD102: 0 | BE102: 0 | BF102: 0 | BG102: 0 | BH102: 0 | BI102: 0 | BJ102: 0 | BK102: 0 | BL102: 0 | BM102: 0 | BN102: 0 | BO102: 0 | BP102: 0 | BQ102: 0 | BR102: 0 | BS102: 0 | BU102: 0
B104: IT_W2 | E104: Production | F104: MWh | I104: 1291761.5 | K104: 0 | L104: 0 | M104: 0 | N104: 0 | O104: 0 | P104: 0 | Q104: 12433.19 | R104: 37366.565 | S104: 37366.565 | T104: 37366.565 | U104: 37366.565 | V104: 37366.565 | W104: 37366.565 | X104: 37366.565 | Y104: 37366.565 | Z104: 37366.565 | AA104: 37366.565 | AB104: 37366.565 | AC104: 37366.565 | AD104: 37366.565 | AE104: 37366.565 | AF104: 37366.565 | AG104: 37366.565 | AH104: 37366.565 | AI104: 37366.565 | AJ104: 37366.565 | AK104: 37189.074 | AL104: 36992.899 | AM104: 36992.899 | AN104: 36992.899 | AO104: 36992.899 | AP104: 36815.408 | AQ104: 36619.234 | AR104: 36619.234 | AS104: 36619.234 | AT104: 36619.234 | AU104: 36441.742 | AV104: 36245.568 | AW104: 36245.568 | AX104: 36245.568 | AY104: 36245.568 | AZ104: 19486.596 | BA104: 0 | BB104: 0 | BC104: 0 | BD104: 0 | BE104: 0 | BF104: 0 | BG104: 0 | BH104: 0 | BI104: 0 | BJ104: 0 | BK104: 0 | BL104: 0 | BM104: 0 | BN104: 0 | BO104: 0 | BP104: 0 | BQ104: 0 | BR104: 0 | BS104: 0 | BU104: 0
B106: IT_W3 | E106: Production | F106: MWh | I106: 5842898 | K106: 0 | L106: 0 | M106: 0 | N106: 0 | O106: 0 | P106: 0 | Q106: 0 | R106: 103616 | S106: 169685.14 | T106: 169685.14 | U106: 169685.14 | V106: 169685.14 | W106: 169685.14 | X106: 169685.14 | Y106: 169685.14 | Z106: 169685.14 | AA106: 169685.14 | AB106: 169685.14 | AC106: 169685.14 | AD106: 169685.14 | AE106: 169685.14 | AF106: 169685.14 | AG106: 169685.14 | AH106: 169685.14 | AI106: 169685.14 | AJ106: 169685.14 | AK106: 169685.14 | AL106: 167988.29 | AM106: 167988.29 | AN106: 167988.29 | AO106: 167988.29 | AP106: 167988.29 | AQ106: 166291.44 | AR106: 166291.44 | AS106: 166291.44 | AT106: 166291.44 | AU106: 166291.44 | AV106: 164594.58 | AW106: 164594.58 | AX106: 164594.58 | AY106: 164594.58 | AZ106: 164594.58 | BA106: 20892.851 | BB106: 0 | BC106: 0 | BD106: 0 | BE106: 0 | BF106: 0 | BG106: 0 | BH106: 0 | BI106: 0 | BJ106: 0 | BK106: 0 | BL106: 0 | BM106: 0 | BN106: 0 | BO106: 0 | BP106: 0 | BQ106: 0 | BR106: 0 | BS106: 0 | BU106: 0
B108: IT_W4 | E108: Production | F108: MWh | I108: 4294840.2 | K108: 0 | L108: 0 | M108: 0 | N108: 0 | O108: 0 | P108: 0 | Q108: 0 | R108: 26433.121 | S108: 124531.8 | T108: 124531.8 | U108: 124531.8 | V108: 124531.8 | W108: 124531.8 | X108: 124531.8 | Y108: 124531.8 | Z108: 124531.8 | AA108: 124531.8 | AB108: 124531.8 | AC108: 124531.8 | AD108: 124531.8 | AE108: 124531.8 | AF108: 124531.8 | AG108: 124531.8 | AH108: 124531.8 | AI108: 124531.8 | AJ108: 124531.8 | AK108: 124531.8 | AL108: 123940.27 | AM108: 123286.48 | AN108: 123286.48 | AO108: 123286.48 | AP108: 123286.48 | AQ108: 122694.95 | AR108: 122041.16 | AS108: 122041.16 | AT108: 122041.16 | AU108: 122041.16 | AV108: 121449.64 | AW108: 120795.85 | AX108: 120795.85 | AY108: 120795.85 | AZ108: 120795.85 | BA108: 69724.046 | BB108: 0 | BC108: 0 | BD108: 0 | BE108: 0 | BF108: 0 | BG108: 0 | BH108: 0 | BI108: 0 | BJ108: 0 | BK108: 0 | BL108: 0 | BM108: 0 | BN108: 0 | BO108: 0 | BP108: 0 | BQ108: 0 | BR108: 0 | BS108: 0 | BU108: 0
B110: IT_W5 | E110: Production | F110: MWh | I110: 3650416.3 | K110: 0 | L110: 0 | M110: 0 | N110: 0 | O110: 0 | P110: 0 | Q110: 0 | R110: 75978.859 | S110: 105902.07 | T110: 105902.07 | U110: 105902.07 | V110: 105902.07 | W110: 105902.07 | X110: 105902.07 | Y110: 105902.07 | Z110: 105902.07 | AA110: 105902.07 | AB110: 105902.07 | AC110: 105902.07 | AD110: 105902.07 | AE110: 105902.07 | AF110: 105902.07 | AG110: 105902.07 | AH110: 105902.07 | AI110: 105902.07 | AJ110: 105902.07 | AK110: 105902.07 | AL110: 104843.05 | AM110: 104843.05 | AN110: 104843.05 | AO110: 104843.05 | AP110: 104843.05 | AQ110: 103784.03 | AR110: 103784.03 | AS110: 103784.03 | AT110: 103784.03 | AU110: 103784.03 | AV110: 102725.01 | AW110: 102725.01 | AX110: 102725.01 | AY110: 102725.01 | AZ110: 102725.01 | BA110: 5537.7624 | BB110: 0 | BC110: 0 | BD110: 0 | BE110: 0 | BF110: 0 | BG110: 0 | BH110: 0 | BI110: 0 | BJ110: 0 | BK110: 0 | BL110: 0 | BM110: 0 | BN110: 0 | BO110: 0 | BP110: 0 | BQ110: 0 | BR110: 0 | BS110: 0 | BU110: 0
B112: IT_W6 | E112: Production | F112: MWh | I112: 1348713.6 | K112: 0 | L112: 0 | M112: 0 | N112: 0 | O112: 0 | P112: 0 | Q112: 12981.353 | R112: 39014.007 | S112: 39014.007 | T112: 39014.007 | U112: 39014.007 | V112: 39014.007 | W112: 39014.007 | X112: 39014.007 | Y112: 39014.007 | Z112: 39014.007 | AA112: 39014.007 | AB112: 39014.007 | AC112: 39014.007 | AD112: 39014.007 | AE112: 39014.007 | AF112: 39014.007 | AG112: 39014.007 | AH112: 39014.007 | AI112: 39014.007 | AJ112: 39014.007 | AK112: 38828.69 | AL112: 38623.867 | AM112: 38623.867 | AN112: 38623.867 | AO112: 38623.867 | AP112: 38438.55 | AQ112: 38233.727 | AR112: 38233.727 | AS112: 38233.727 | AT112: 38233.727 | AU112: 38048.41 | AV112: 37843.586 | AW112: 37843.586 | AX112: 37843.586 | AY112: 37843.586 | AZ112: 20345.734 | BA112: 0 | BB112: 0 | BC112: 0 | BD112: 0 | BE112: 0 | BF112: 0 | BG112: 0 | BH112: 0 | BI112: 0 | BJ112: 0 | BK112: 0 | BL112: 0 | BM112: 0 | BN112: 0 | BO112: 0 | BP112: 0 | BQ112: 0 | BR112: 0 | BS112: 0 | BU112: 0
B114: IT_W7 | E114: Production | F114: MWh | I114: 993843.67 | K114: 0 | L114: 0 | M114: 0 | N114: 0 | O114: 0 | P114: 0 | Q114: 14110.567 | R114: 28773.578 | S114: 28773.578 | T114: 28773.578 | U114: 28773.578 | V114: 28773.578 | W114: 28773.578 | X114: 28773.578 | Y114: 28773.578 | Z114: 28773.578 | AA114: 28773.578 | AB114: 28773.578 | AC114: 28773.578 | AD114: 28773.578 | AE114: 28773.578 | AF114: 28773.578 | AG114: 28773.578 | AH114: 28773.578 | AI114: 28773.578 | AJ114: 28773.578 | AK114: 28485.842 | AL114: 28485.842 | AM114: 28485.842 | AN114: 28485.842 | AO114: 28485.842 | AP114: 28198.106 | AQ114: 28198.106 | AR114: 28198.106 | AS114: 28198.106 | AT114: 28198.106 | AU114: 27910.37 | AV114: 27910.37 | AW114: 27910.37 | AX114: 27910.37 | AY114: 27910.37 | AZ114: 10063.528 | BA114: 0 | BB114: 0 | BC114: 0 | BD114: 0 | BE114: 0 | BF114: 0 | BG114: 0 | BH114: 0 | BI114: 0 | BJ114: 0 | BK114: 0 | BL114: 0 | BM114: 0 | BN114: 0 | BO114: 0 | BP114: 0 | BQ114: 0 | BR114: 0 | BS114: 0 | BU114: 0
B116: IT_W8 | E116: Production | F116: MWh | I116: 1998121.2 | K116: 0 | L116: 0 | M116: 0 | N116: 0 | O116: 0 | P116: 0 | Q116: 0 | R116: 0 | S116: 0 | T116: 41589.089 | U116: 57968.369 | V116: 57968.369 | W116: 57968.369 | X116: 57968.369 | Y116: 57968.369 | Z116: 57968.369 | AA116: 57968.369 | AB116: 57968.369 | AC116: 57968.369 | AD116: 57968.369 | AE116: 57968.369 | AF116: 57968.369 | AG116: 57968.369 | AH116: 57968.369 | AI116: 57968.369 | AJ116: 57968.369 | AK116: 57968.369 | AL116: 57968.369 | AM116: 57968.369 | AN116: 57388.686 | AO116: 57388.686 | AP116: 57388.686 | AQ116: 57388.686 | AR116: 57388.686 | AS116: 56809.002 | AT116: 56809.002 | AU116: 56809.002 | AV116: 56809.002 | AW116: 56809.002 | AX116: 56229.318 | AY116: 56229.318 | AZ116: 56229.318 | BA116: 56229.318 | BB116: 56229.318 | BC116: 2998.0256 | BD116: 0 | BE116: 0 | BF116: 0 | BG116: 0 | BH116: 0 | BI116: 0 | BJ116: 0 | BK116: 0 | BL116: 0 | BM116: 0 | BN116: 0 | BO116: 0 | BP116: 0 | BQ116: 0 | BR116: 0 | BS116: 0 | BU116: 0
B118: IT_S1 | E118: Production | F118: MWh | I118: 2850238.2 | K118: 0 | L118: 0 | M118: 0 | N118: 0 | O118: 0 | P118: 1137.7305 | Q118: 77692.328 | R118: 77016.237 | S118: 76746.723 | T118: 76478.537 | U118: 76211.096 | V118: 75944.591 | W118: 75678.827 | X118: 75414.372 | Y118: 75150.653 | Z118: 74887.856 | AA118: 74625.79 | AB118: 74365.015 | AC118: 74104.966 | AD118: 73845.825 | AE118: 73587.406 | AF118: 73330.26 | AG118: 73073.828 | AH118: 72818.294 | AI118: 72563.47 | AJ118: 72309.902 | AK118: 72057.039 | AL118: 71805.06 | AM118: 71553.782 | AN118: 71303.742 | AO118: 71054.398 | AP118: 70805.925 | AQ118: 70558.144 | AR118: 70311.583 | AS118: 70125.171 | AT118: 69600.531 | AU118: 68506.249 | AV118: 67790.104 | AW118: 67077.53 | AX118: 66374.337 | AY118: 65674.652 | AZ118: 64984.856 | BA118: 64298.491 | BB118: 63621.203 | BC118: 62947.285 | BD118: 52804.435 | BE118: 0 | BF118: 0 | BG118: 0 | BH118: 0 | BI118: 0 | BJ118: 0 | BK118: 0 | BL118: 0 | BM118: 0 | BN118: 0 | BO118: 0 | BP118: 0 | BQ118: 0 | BR118: 0 | BS118: 0 | BU118: 0
B120: IT_S2 | E120: Production | F120: MWh | I120: 1254641 | K120: 0 | L120: 0 | M120: 0 | N120: 0 | O120: 0 | P120: 0.48761254 | Q120: 34096.796 | R120: 33800.08 | S120: 33681.799 | T120: 33564.1 | U120: 33446.728 | V120: 33329.767 | W120: 33213.132 | X120: 33097.071 | Y120: 32981.332 | Z120: 32865.999 | AA120: 32750.986 | AB120: 32636.54 | AC120: 32522.412 | AD120: 32408.683 | AE120: 32295.271 | AF120: 32182.417 | AG120: 32069.877 | AH120: 31957.731 | AI120: 31845.897 | AJ120: 31734.613 | AK120: 31623.639 | AL120: 31513.053 | AM120: 31402.775 | AN120: 31293.04 | AO120: 31183.61 | AP120: 31074.563 | AQ120: 30965.82 | AR120: 30857.612 | AS120: 30775.801 | AT120: 30574.733 | AU120: 30079.794 | AV120: 29779.785 | AW120: 29452.57 | AX120: 29158.047 | AY120: 28836.691 | AZ120: 28547.851 | BA120: 28232.54 | BB120: 27948.996 | BC120: 27639.343 | BD120: 27219.001 | BE120: 0 | BF120: 0 | BG120: 0 | BH120: 0 | BI120: 0 | BJ120: 0 | BK120: 0 | BL120: 0 | BM120: 0 | BN120: 0 | BO120: 0 | BP120: 0 | BQ120: 0 | BR120: 0 | BS120: 0 | BU120: 0
B122: IT_S3 | E122: Production | F122: MWh | I122: 1293207.5 | K122: 0 | L122: 0 | M122: 0 | N122: 0 | O122: 0 | P122: 0.50260131 | Q122: 35144.901 | R122: 34839.064 | S122: 34717.147 | T122: 34595.83 | U122: 34474.851 | V122: 34354.294 | W122: 34234.073 | X122: 34114.445 | Y122: 33995.148 | Z122: 33876.27 | AA122: 33757.722 | AB122: 33639.757 | AC122: 33522.121 | AD122: 33404.897 | AE122: 33287.998 | AF122: 33171.675 | AG122: 33055.676 | AH122: 32940.082 | AI122: 32824.811 | AJ122: 32710.106 | AK122: 32595.721 | AL122: 32481.736 | AM122: 32368.068 | AN122: 32254.96 | AO122: 32142.166 | AP122: 32029.767 | AQ122: 31917.681 | AR122: 31806.147 | AS122: 31721.822 | AT122: 31514.572 | AU122: 31004.419 | AV122: 30695.188 | AW122: 30357.916 | AX122: 30054.339 | AY122: 29723.105 | AZ122: 29425.386 | BA122: 29100.383 | BB122: 28808.122 | BC122: 28488.951 | BD122: 28055.688 | BE122: 0 | BF122: 0 | BG122: 0 | BH122: 0 | BI122: 0 | BJ122: 0 | BK122: 0 | BL122: 0 | BM122: 0 | BN122: 0 | BO122: 0 | BP122: 0 | BQ122: 0 | BR122: 0 | BS122: 0 | BU122: 0
B124: IT_B1 | E124: Production | F124: MWh | I124: 0 | K124: 0 | L124: 0 | M124: 0 | N124: 0 | O124: 0 | P124: 0 | Q124: 0 | R124: 0 | S124: 0 | T124: 0 | U124: 0 | V124: 0 | W124: 0 | X124: 0 | Y124: 0 | Z124: 0 | AA124: 0 | AB124: 0 | AC124: 0 | AD124: 0 | AE124: 0 | AF124: 0 | AG124: 0 | AH124: 0 | AI124: 0 | AJ124: 0 | AK124: 0 | AL124: 0 | AM124: 0 | AN124: 0 | AO124: 0 | AP124: 0 | AQ124: 0 | AR124: 0 | AS124: 0 | AT124: 0 | AU124: 0 | AV124: 0 | AW124: 0 | AX124: 0 | AY124: 0 | AZ124: 0 | BA124: 0 | BB124: 0 | BC124: 0 | BD124: 0 | BE124: 0 | BF124: 0 | BG124: 0 | BH124: 0 | BI124: 0 | BJ124: 0 | BK124: 0 | BL124: 0 | BM124: 0 | BN124: 0 | BO124: 0 | BP124: 0 | BQ124: 0 | BR124: 0 | BS124: 0 | BU124: 0
... B128: IT_B3 | E128: Production | F128: MWh | I128: 0 | K128: 0 | L128: 0 | M128: 0 | N128: 0 | O128: 0 | P128: 0 | Q128: 0 | R128: 0 | S128: 0 | T128: 0 | U128: 0 | V128: 0 | W128: 0 | X128: 0 | Y128: 0 | Z128: 0 | AA128: 0 | AB128: 0 | AC128: 0 | AD128: 0 | AE128: 0 | AF128: 0 | AG128: 0 | AH128: 0 | AI128: 0 | AJ128: 0 | AK128: 0 | AL128: 0 | AM128: 0 | AN128: 0 | AO128: 0 | AP128: 0 | AQ128: 0 | AR128: 0 | AS128: 0 | AT128: 0 | AU128: 0 | AV128: 0 | AW128: 0 | AX128: 0 | AY128: 0 | AZ128: 0 | BA128: 0 | BB128: 0 | BC128: 0 | BD128: 0 | BE128: 0 | BF128: 0 | BG128: 0 | BH128: 0 | BI128: 0 | BJ128: 0 | BK128: 0 | BL128: 0 | BM128: 0 | BN128: 0 | BO128: 0 | BP128: 0 | BQ128: 0 | BR128: 0 | BS128: 0 | BU128: 0
E130: Italy | I130: 32575362 | K130: 0 | L130: 0 | M130: 0 | N130: 0 | O130: 0 | P130: 1138.7207 | Q130: 189684.2 | R130: 681318.84 | S130: 874900.15 | T130: 915982.03 | U130: 931855.52 | V130: 931351.5 | W130: 930848.88 | X130: 930348.74 | Y130: 929849.98 | Z130: 929352.97 | AA130: 928857.35 | AB130: 928364.16 | AC130: 927872.35 | AD130: 927382.25 | AE130: 926893.52 | AF130: 926407.2 | AG130: 925922.23 | AH130: 925438.95 | AI130: 924957.03 | AJ130: 924477.47 | AK130: 922282.42 | AL130: 916878.94 | AM130: 915749.93 | AN130: 914697.36 | AO130: 914225.79 | AP130: 912039.04 | AQ130: 906643.51 | AR130: 905523.42 | AS130: 904591.18 | AT130: 903658.23 | AU130: 899842.02 | AV130: 893589.72 | AW130: 891558.86 | AX130: 889677.89 | AY130: 888325.61 | AZ130: 802098.33 | BA130: 274015.39 | BB130: 176607.64 | BC130: 122073.6 | BD130: 108079.12 | BE130: 0 | BF130: 0 | BG130: 0 | BH130: 0 | BI130: 0 | BJ130: 0 | BK130: 0 | BL130: 0 | BM130: 0 | BN130: 0 | BO130: 0 | BP130: 0 | BQ130: 0 | BR130: 0 | BS130: 0 | BU130: 0
B132: IE_S1 | E132: Production | F132: MWh | I132: 3172233.8 | K132: 0 | L132: 0 | M132: 0 | N132: 0 | O132: 1366.2704 | P132: 92351.634 | Q132: 91230.76 | R132: 90589.506 | S132: 89954.344 | T132: 89320.027 | U132: 88691.751 | V132: 88063.859 | W132: 87441.963 | X132: 86820.877 | Y132: 86205.736 | Z132: 85590.959 | AA132: 84982.082 | AB132: 84373.983 | AC132: 83771.733 | AD132: 83169.827 | AE132: 82573.728 | AF132: 81978.373 | AG132: 81388.776 | AH132: 80799.502 | AI132: 80215.942 | AJ132: 79633.096 | AK132: 79055.914 | AL132: 78479.038 | AM132: 77907.783 | AN132: 77337.213 | AO132: 76772.216 | AP132: 76207.506 | AQ132: 75648.328 | AR132: 75153.986 | AS132: 74369.928 | AT132: 73173.634 | AU132: 72338.276 | AV132: 71467.196 | AW132: 70565.504 | AX132: 69634.301 | AY132: 68671.337 | AZ132: 67719.114 | BA132: 66738.686 | BB132: 65728.523 | BC132: 54750.591 | BD132: 0 | BE132: 0 | BF132: 0 | BG132: 0 | BH132: 0 | BI132: 0 | BJ132: 0 | BK132: 0 | BL132: 0 | BM132: 0 | BN132: 0 | BO132: 0 | BP132: 0 | BQ132: 0 | BR132: 0 | BS132: 0 | BU132: 0
B134: IE_S2 | E134: Production | F134: MWh | I134: 2122056.3 | K134: 0 | L134: 0 | M134: 0 | N134: 0 | O134: 21791.198 | P134: 61589.206 | Q134: 60850.081 | R134: 60423.138 | S134: 59998.284 | T134: 59575.959 | U134: 59155.703 | V134: 58737.665 | W134: 58321.679 | X134: 57908.172 | Y134: 57496.697 | Z134: 57087.398 | AA134: 56680.115 | AB134: 56275.263 | AC134: 55872.405 | AD134: 55471.684 | AE134: 55072.943 | AF134: 54676.584 | AG134: 54282.184 | AH134: 53889.882 | AI134: 53499.522 | AJ134: 53111.499 | AK134: 52725.4 | AL134: 52341.359 | AM134: 51959.226 | AN134: 51579.383 | AO134: 51201.43 | AP134: 50825.496 | AQ134: 50451.436 | AR134: 50123.81 | AS134: 49589.151 | AT134: 48799.886 | AU134: 48240.777 | AV134: 47633.425 | AW134: 47031.975 | AX134: 46409.952 | AY134: 45767.597 | AZ134: 45132.395 | BA134: 44477.519 | BB134: 43777.723 | BC134: 22221.1 | BD134: 0 | BE134: 0 | BF134: 0 | BG134: 0 | BH134: 0 | BI134: 0 | BJ134: 0 | BK134: 0 | BL134: 0 | BM134: 0 | BN134: 0 | BO134: 0 | BP134: 0 | BQ134: 0 | BR134: 0 | BS134: 0 | BU134: 0
B136: IE_B1 | E136: Production | F136: MWh | I136: 0 | K136: 0 | L136: 0 | M136: 0 | N136: 0 | O136: 0 | P136: 0 | Q136: 0 | R136: 0 | S136: 0 | T136: 0 | U136: 0 | V136: 0 | W136: 0 | X136: 0 | Y136: 0 | Z136: 0 | AA136: 0 | AB136: 0 | AC136: 0 | AD136: 0 | AE136: 0 | AF136: 0 | AG136: 0 | AH136: 0 | AI136: 0 | AJ136: 0 | AK136: 0 | AL136: 0 | AM136: 0 | AN136: 0 | AO136: 0 | AP136: 0 | AQ136: 0 | AR136: 0 | AS136: 0 | AT136: 0 | AU136: 0 | AV136: 0 | AW136: 0 | AX136: 0 | AY136: 0 | AZ136: 0 | BA136: 0 | BB136: 0 | BC136: 0 | BD136: 0 | BE136: 0 | BF136: 0 | BG136: 0 | BH136: 0 | BI136: 0 | BJ136: 0 | BK136: 0 | BL136: 0 | BM136: 0 | BN136: 0 | BO136: 0 | BP136: 0 | BQ136: 0 | BR136: 0 | BS136: 0 | BU136: 0
B138: IE_B2 | E138: Production | F138: MWh | I138: 0 | K138: 0 | L138: 0 | M138: 0 | N138: 0 | O138: 0 | P138: 0 | Q138: 0 | R138: 0 | S138: 0 | T138: 0 | U138: 0 | V138: 0 | W138: 0 | X138: 0 | Y138: 0 | Z138: 0 | AA138: 0 | AB138: 0 | AC138: 0 | AD138: 0 | AE138: 0 | AF138: 0 | AG138: 0 | AH138: 0 | AI138: 0 | AJ138: 0 | AK138: 0 | AL138: 0 | AM138: 0 | AN138: 0 | AO138: 0 | AP138: 0 | AQ138: 0 | AR138: 0 | AS138: 0 | AT138: 0 | AU138: 0 | AV138: 0 | AW138: 0 | AX138: 0 | AY138: 0 | AZ138: 0 | BA138: 0 | BB138: 0 | BC138: 0 | BD138: 0 | BE138: 0 | BF138: 0 | BG138: 0 | BH138: 0 | BI138: 0 | BJ138: 0 | BK138: 0 | BL138: 0 | BM138: 0 | BN138: 0 | BO138: 0 | BP138: 0 | BQ138: 0 | BR138: 0 | BS138: 0 | BU138: 0
A140: c | E140: Ireland | I140: 5294290.1 | K140: 0 | L140: 0 | M140: 0 | N140: 0 | O140: 23157.468 | P140: 153940.84 | Q140: 152080.84 | R140: 151012.64 | S140: 149952.63 | T140: 148895.99 | U140: 147847.45 | V140: 146801.52 | W140: 145763.64 | X140: 144729.05 | Y140: 143702.43 | Z140: 142678.36 | AA140: 141662.2 | AB140: 140649.25 | AC140: 139644.14 | AD140: 138641.51 | AE140: 137646.67 | AF140: 136654.96 | AG140: 135670.96 | AH140: 134689.38 | AI140: 133715.46 | AJ140: 132744.59 | AK140: 131781.31 | AL140: 130820.4 | AM140: 129867.01 | AN140: 128916.6 | AO140: 127973.65 | AP140: 127033 | AQ140: 126099.76 | AR140: 125277.8 | AS140: 123959.08 | AT140: 121973.52 | AU140: 120579.05 | AV140: 119100.62 | AW140: 117597.48 | AX140: 116044.25 | AY140: 114438.93 | AZ140: 112851.51 | BA140: 111216.21 | BB140: 109506.25 | BC140: 76971.691 | BD140: 0 | BE140: 0 | BF140: 0 | BG140: 0 | BH140: 0 | BI140: 0 | BJ140: 0 | BK140: 0 | BL140: 0 | BM140: 0 | BN140: 0 | BO140: 0 | BP140: 0 | BQ140: 0 | BR140: 0 | BS140: 0 | BU140: 0
B142: ES_W1 | E142: Production | F142: MWh | I142: 1888200.2 | K142: 0 | L142: 0 | M142: 0 | N142: 0 | O142: 0 | P142: 0 | Q142: 0 | R142: 785.07337 | S142: 54645.238 | T142: 54645.238 | U142: 54645.238 | V142: 54645.238 | W142: 54645.238 | X142: 54645.238 | Y142: 54645.238 | Z142: 54645.238 | AA142: 54645.238 | AB142: 54645.238 | AC142: 54645.238 | AD142: 54645.238 | AE142: 54645.238 | AF142: 54645.238 | AG142: 54645.238 | AH142: 54645.238 | AI142: 54645.238 | AJ142: 54645.238 | AK142: 54645.238 | AL142: 54385.673 | AM142: 54098.786 | AN142: 54098.786 | AO142: 54098.786 | AP142: 54098.786 | AQ142: 53839.221 | AR142: 53552.333 | AS142: 53552.333 | AT142: 53552.333 | AU142: 53552.333 | AV142: 53292.769 | AW142: 53005.881 | AX142: 53005.881 | AY142: 53005.881 | AZ142: 53005.881 | BA142: 45009.909 | BB142: 0 | BC142: 0 | BD142: 0 | BE142: 0 | BF142: 0 | BG142: 0 | BH142: 0 | BI142: 0 | BJ142: 0 | BK142: 0 | BL142: 0 | BM142: 0 | BN142: 0 | BO142: 0 | BP142: 0 | BQ142: 0 | BR142: 0 | BS142: 0 | BU142: 0
B144: ES_W2 | E144: Production | F144: MWh | I144: 1409983.8 | K144: 0 | L144: 0 | M144: 0 | N144: 0 | O144: 0 | P144: 0 | Q144: 0 | R144: 20018.914 | S144: 40821.588 | T144: 40821.588 | U144: 40821.588 | V144: 40821.588 | W144: 40821.588 | X144: 40821.588 | Y144: 40821.588 | Z144: 40821.588 | AA144: 40821.588 | AB144: 40821.588 | AC144: 40821.588 | AD144: 40821.588 | AE144: 40821.588 | AF144: 40821.588 | AG144: 40821.588 | AH144: 40821.588 | AI144: 40821.588 | AJ144: 40821.588 | AK144: 40821.588 | AL144: 40413.373 | AM144: 40413.373 | AN144: 40413.373 | AO144: 40413.373 | AP144: 40413.373 | AQ144: 40005.157 | AR144: 40005.157 | AS144: 40005.157 | AT144: 40005.157 | AU144: 40005.157 | AV144: 39596.941 | AW144: 39596.941 | AX144: 39596.941 | AY144: 39596.941 | AZ144: 39596.941 | BA144: 14277.307 | BB144: 0 | BC144: 0 | BD144: 0 | BE144: 0 | BF144: 0 | BG144: 0 | BH144: 0 | BI144: 0 | BJ144: 0 | BK144: 0 | BL144: 0 | BM144: 0 | BN144: 0 | BO144: 0 | BP144: 0 | BQ144: 0 | BR144: 0 | BS144: 0 | BU144: 0
B146: ES_S1 | E146: Production | F146: MWh | I146: 647481.02 | K146: 0 | L146: 0 | M146: 0 | N146: 0 | O146: 0 | P146: 0 | Q146: 0 | R146: 259.28728 | S146: 17580.849 | T146: 17428.496 | U146: 17367.55 | V146: 17306.817 | W146: 17246.253 | X146: 17185.987 | Y146: 17125.888 | Z146: 17066 | AA146: 17006.279 | AB146: 16946.851 | AC146: 16887.589 | AD146: 16828.535 | AE146: 16769.644 | AF146: 16711.044 | AG146: 16652.606 | AH146: 16594.373 | AI146: 16536.302 | AJ146: 16478.517 | AK146: 16420.893 | AL146: 16363.47 | AM146: 16306.207 | AN146: 16249.226 | AO146: 16192.403 | AP146: 16135.779 | AQ146: 16079.314 | AR146: 16023.125 | AS146: 15967.093 | AT146: 15911.257 | AU146: 15853.223 | AV146: 15748.915 | AW146: 15556.814 | AX146: 15432.644 | AY146: 15324.728 | AZ146: 15217.718 | BA146: 15096.239 | BB146: 14990.75 | BC146: 14878.711 | BD146: 14767.153 | BE146: 14663.963 | BF146: 12322.526 | BG146: 0 | BH146: 0 | BI146: 0 | BJ146: 0 | BK146: 0 | BL146: 0 | BM146: 0 | BN146: 0 | BO146: 0 | BP146: 0 | BQ146: 0 | BR146: 0 | BS146: 0 | BU146: 0
B148: ES_S2 | E148: Production | F148: MWh | I148: 4446793 | K148: 0 | L148: 0 | M148: 0 | N148: 0 | O148: 0 | P148: 0 | Q148: 0 | R148: 60625.648 | S148: 119928.59 | T148: 119509.51 | U148: 119091.59 | V148: 118675.13 | W148: 118259.84 | X148: 117846.59 | Y148: 117434.48 | Z148: 117023.82 | AA148: 116614.31 | AB148: 116206.8 | AC148: 115800.44 | AD148: 115395.49 | AE148: 114991.67 | AF148: 114589.84 | AG148: 114189.12 | AH148: 113789.81 | AI148: 113391.61 | AJ148: 112995.37 | AK148: 112600.23 | AL148: 112206.48 | AM148: 111813.82 | AN148: 111423.09 | AO148: 111033.45 | AP148: 110645.18 | AQ148: 110257.98 | AR148: 109872.69 | AS148: 109488.47 | AT148: 109105.6 | AU148: 108897.17 | AV148: 107239.54 | AW148: 106490.18 | AX148: 105640.2 | AY148: 104901.49 | AZ148: 104168.99 | BA148: 103337.43 | BB148: 102615.33 | BC148: 101848.4 | BD148: 101084.75 | BE148: 100378.4 | BF148: 35384.439 | BG148: 0 | BH148: 0 | BI148: 0 | BJ148: 0 | BK148: 0 | BL148: 0 | BM148: 0 | BN148: 0 | BO148: 0 | BP148: 0 | BQ148: 0 | BR148: 0 | BS148: 0 | BU148: 0
E150: Spain | I150: 8392457.9 | K150: 0 | L150: 0 | M150: 0 | N150: 0 | O150: 0 | P150: 0 | Q150: 0 | R150: 81688.922 | S150: 232976.27 | T150: 232404.83 | U150: 231925.97 | V150: 231448.78 | W150: 230972.92 | X150: 230499.4 | Y150: 230027.2 | Z150: 229556.65 | AA150: 229087.41 | AB150: 228620.48 | AC150: 228154.85 | AD150: 227690.85 | AE150: 227228.14 | AF150: 226767.71 | AG150: 226308.56 | AH150: 225851.01 | AI150: 225394.74 | AJ150: 224940.72 | AK150: 224487.95 | AL150: 223368.99 | AM150: 222632.19 | AN150: 222184.48 | AO150: 221738.01 | AP150: 221293.11 | AQ150: 220181.67 | AR150: 219453.31 | AS150: 219013.06 | AT150: 218574.35 | AU150: 218307.89 | AV150: 215878.17 | AW150: 214649.82 | AX150: 213675.67 | AY150: 212829.04 | AZ150: 211989.53 | BA150: 177720.89 | BB150: 117606.08 | BC150: 116727.11 | BD150: 115851.91 | BE150: 115042.36 | BF150: 47706.965 | BG150: 0 | BH150: 0 | BI150: 0 | BJ150: 0 | BK150: 0 | BL150: 0 | BM150: 0 | BN150: 0 | BO150: 0 | BP150: 0 | BQ150: 0 | BR150: 0 | BS150: 0 | BU150: 0
B152: PT_W1 | E152: Production | F152: MWh | I152: 1979129.1 | K152: 0 | L152: 0 | M152: 0 | N152: 0 | O152: 0 | P152: 0 | Q152: 0 | R152: 0 | S152: 0 | T152: 34689.223 | U152: 57104.386 | V152: 57277.172 | W152: 57422.6 | X152: 57480.196 | Y152: 57452.838 | Z152: 57395.243 | AA152: 57392.363 | AB152: 57480.196 | AC152: 57507.554 | AD152: 57568.029 | AE152: 57507.554 | AF152: 57595.387 | AG152: 57595.387 | AH152: 57568.029 | AI152: 57480.196 | AJ152: 57507.554 | AK152: 57595.387 | AL152: 57568.029 | AM152: 57537.791 | AN152: 57019.433 | AO152: 56992.349 | AP152: 56935.329 | AQ152: 56848.374 | AR152: 56932.478 | AS152: 56416.668 | AT152: 56330.592 | AU152: 56330.592 | AV152: 56330.592 | AW152: 56330.592 | AX152: 55755.79 | AY152: 55755.79 | AZ152: 55755.79 | BA152: 55755.79 | BB152: 55755.79 | BC152: 7157.9971 | BD152: 0 | BE152: 0 | BF152: 0 | BG152: 0 | BH152: 0 | BI152: 0 | BJ152: 0 | BK152: 0 | BL152: 0 | BM152: 0 | BN152: 0 | BO152: 0 | BP152: 0 | BQ152: 0 | BR152: 0 | BS152: 0 | BU152: 0
B154: PT_W2 | E154: Production | F154: MWh | I154: 2051084 | K154: 0 | L154: 0 | M154: 0 | N154: 0 | O154: 0 | P154: 0 | Q154: 0 | R154: 0 | S154: 0 | T154: 49195.6 | U154: 58955.484 | V154: 59133.957 | W154: 59312.43 | X154: 59371.92 | Y154: 59371.92 | Z154: 59312.43 | AA154: 59252.939 | AB154: 59371.92 | AC154: 59371.92 | AD154: 59490.902 | AE154: 59371.92 | AF154: 59490.902 | AG154: 59490.902 | AH154: 59490.902 | AI154: 59371.92 | AJ154: 59371.92 | AK154: 59490.902 | AL154: 59490.902 | AM154: 59431.411 | AN154: 58895.993 | AO154: 58895.993 | AP154: 58837.097 | AQ154: 58719.305 | AR154: 58778.201 | AS154: 58301.084 | AT154: 58184.482 | AU154: 58184.482 | AV154: 58184.482 | AW154: 58184.482 | AX154: 57590.763 | AY154: 57590.763 | AZ154: 57590.763 | BA154: 57590.763 | BB154: 57590.763 | BC154: 821.50813 | BD154: 0 | BE154: 0 | BF154: 0 | BG154: 0 | BH154: 0 | BI154: 0 | BJ154: 0 | BK154: 0 | BL154: 0 | BM154: 0 | BN154: 0 | BO154: 0 | BP154: 0 | BQ154: 0 | BR154: 0 | BS154: 0 | BU154: 0
E156: Portugal | I156: 4030213.1 | K156: 0 | L156: 0 | M156: 0 | N156: 0 | O156: 0 | P156: 0 | Q156: 0 | R156: 0 | S156: 0 | T156: 83884.823 | U156: 116059.87 | V156: 116411.13 | W156: 116735.03 | X156: 116852.12 | Y156: 116824.76 | Z156: 116707.67 | AA156: 116645.3 | AB156: 116852.12 | AC156: 116879.47 | AD156: 117058.93 | AE156: 116879.47 | AF156: 117086.29 | AG156: 117086.29 | AH156: 117058.93 | AI156: 116852.12 | AJ156: 116879.47 | AK156: 117086.29 | AL156: 117058.93 | AM156: 116969.2 | AN156: 115915.43 | AO156: 115888.34 | AP156: 115772.43 | AQ156: 115567.68 | AR156: 115710.68 | AS156: 114717.75 | AT156: 114515.07 | AU156: 114515.07 | AV156: 114515.07 | AW156: 114515.07 | AX156: 113346.55 | AY156: 113346.55 | AZ156: 113346.55 | BA156: 113346.55 | BB156: 113346.55 | BC156: 7979.5053 | BD156: 0 | BE156: 0 | BF156: 0 | BG156: 0 | BH156: 0 | BI156: 0 | BJ156: 0 | BK156: 0 | BL156: 0 | BM156: 0 | BN156: 0 | BO156: 0 | BP156: 0 | BQ156: 0 | BR156: 0 | BS156: 0 | BU156: 0
C159: o | E159: Revenue
B161: GR_W1 | E161: PPA Revenue | I161: 670579.86 | K161: 0 | L161: 0 | M161: 14482.031 | N161: 43912.148 | O161: 44656.771 | P161: 44934.715 | Q161: 45207.767 | R161: 45536.551 | S161: 45470.133 | T161: 45399.805 | U161: 45399.805 | V161: 45333.52 | W161: 45263.332 | X161: 45197.181 | Y161: 45127.134 | Z161: 45127.134 | AA161: 45061.115 | AB161: 24470.719 | AC161: 0 | AD161: 0 | AE161: 0 | AF161: 0 | AG161: 0 | AH161: 0 | AI161: 0 | AJ161: 0 | AK161: 0 | AL161: 0 | AM161: 0 | AN161: 0 | AO161: 0 | AP161: 0 | AQ161: 0 | AR161: 0 | AS161: 0 | AT161: 0 | AU161: 0 | AV161: 0 | AW161: 0 | AX161: 0 | AY161: 0 | AZ161: 0 | BA161: 0 | BB161: 0 | BC161: 0 | BD161: 0 | BE161: 0 | BF161: 0 | BG161: 0 | BH161: 0 | BI161: 0 | BJ161: 0 | BK161: 0 | BL161: 0 | BM161: 0 | BN161: 0 | BO161: 0 | BP161: 0 | BQ161: 0 | BR161: 0 | BS161: 0 | BU161: 0
B162: GR_W1 | E162: Merchant Revenue | F162: €'000 | I162: 870358.41 | K162: 0 | L162: 0 | M162: 13544.243 | N162: 0 | O162: 0 | P162: 0 | Q162: 0 | R162: 0 | S162: 0 | T162: 0 | U162: 0 | V162: 0 | W162: 0 | X162: 0 | Y162: 0 | Z162: 0 | AA162: 0 | AB162: 25471.918 | AC162: 55941.077 | AD162: 56027.01 | AE162: 56197.258 | AF162: 56282.33 | AG162: 56073.712 | AH162: 55898.918 | AI162: 55945.442 | AJ162: 55983.895 | AK162: 56024.148 | AL162: 56211.879 | AM162: 56322.597 | AN162: 57308.339 | AO162: 58306.145 | AP162: 59326.515 | AQ162: 39492.986 | AR162: 0 | AS162: 0 | AT162: 0 | AU162: 0 | AV162: 0 | AW162: 0 | AX162: 0 | AY162: 0 | AZ162: 0 | BA162: 0 | BB162: 0 | BC162: 0 | BD162: 0 | BE162: 0 | BF162: 0 | BG162: 0 | BH162: 0 | BI162: 0 | BJ162: 0 | BK162: 0 | BL162: 0 | BM162: 0 | BN162: 0 | BO162: 0 | BP162: 0 | BQ162: 0 | BR162: 0 | BS162: 0 | BU162: 0
B163: GR_W1 | E163: GoOs Revenue | F163: €'000 | I163: 7328.2704 | K163: 0 | L163: 0 | M163: 68.188622 | N163: 0 | O163: 0 | P163: 0 | Q163: 0 | R163: 0 | S163: 0 | T163: 0 | U163: 0 | V163: 0 | W163: 0 | X163: 0 | Y163: 0 | Z163: 0 | AA163: 0 | AB163: 194.55035 | AC163: 434.01993 | AD163: 441.57951 | AE163: 449.96952 | AF163: 457.84679 | AG163: 463.69604 | AH163: 469.92452 | AI163: 478.15043 | AJ163: 486.47713 | AK163: 494.99205 | AL163: 496.65072 | AM163: 497.62895 | AN163: 506.33831 | AO163: 515.15426 | AP163: 524.16957 | AQ163: 348.93372 | AR163: 0 | AS163: 0 | AT163: 0 | AU163: 0 | AV163: 0 | AW163: 0 | AX163: 0 | AY163: 0 | AZ163: 0 | BA163: 0 | BB163: 0 | BC163: 0 | BD163: 0 | BE163: 0 | BF163: 0 | BG163: 0 | BH163: 0 | BI163: 0 | BJ163: 0 | BK163: 0 | BL163: 0 | BM163: 0 | BN163: 0 | BO163: 0 | BP163: 0 | BQ163: 0 | BR163: 0 | BS163: 0 | BU163: 0
B164: GR_W1 | E164: Total Wind / Solar Revenue | F164: €'000 | I164: 1548266.5 | K164: 0 | L164: 0 | M164: 28094.463 | N164: 43912.148 | O164: 44656.771 | P164: 44934.715 | Q164: 45207.767 | R164: 45536.551 | S164: 45470.133 | T164: 45399.805 | U164: 45399.805 | V164: 45333.52 | W164: 45263.332 | X164: 45197.181 | Y164: 45127.134 | Z164: 45127.134 | AA164: 45061.115 | AB164: 50137.187 | AC164: 56375.097 | AD164: 56468.589 | AE164: 56647.228 | AF164: 56740.176 | AG164: 56537.408 | AH164: 56368.842 | AI164: 56423.592 | AJ164: 56470.372 | AK164: 56519.14 | AL164: 56708.53 | AM164: 56820.226 | AN164: 57814.678 | AO164: 58821.3 | AP164: 59850.684 | AQ164: 39841.92 | AR164: 0 | AS164: 0 | AT164: 0 | AU164: 0 | AV164: 0 | AW164: 0 | AX164: 0 | AY164: 0 | AZ164: 0 | BA164: 0 | BB164: 0 | BC164: 0 | BD164: 0 | BE164: 0 | BF164: 0 | BG164: 0 | BH164: 0 | BI164: 0 | BJ164: 0 | BK164: 0 | BL164: 0 | BM164: 0 | BN164: 0 | BO164: 0 | BP164: 0 | BQ164: 0 | BR164: 0 | BS164: 0 | BU164: 0
B165: GR_W1 | E165: Total BESS Revenue | F165: €'000 | I165: 0 | K165: 0 | L165: 0 | M165: 0 | N165: 0 | O165: 0 | P165: 0 | Q165: 0 | R165: 0 | S165: 0 | T165: 0 | U165: 0 | V165: 0 | W165: 0 | X165: 0 | Y165: 0 | Z165: 0 | AA165: 0 | AB165: 0 | AC165: 0 | AD165: 0 | AE165: 0 | AF165: 0 | AG165: 0 | AH165: 0 | AI165: 0 | AJ165: 0 | AK165: 0 | AL165: 0 | AM165: 0 | AN165: 0 | AO165: 0 | AP165: 0 | AQ165: 0 | AR165: 0 | AS165: 0 | AT165: 0 | AU165: 0 | AV165: 0 | AW165: 0 | AX165: 0 | AY165: 0 | AZ165: 0 | BA165: 0 | BB165: 0 | BC165: 0 | BD165: 0 | BE165: 0 | BF165: 0 | BG165: 0 | BH165: 0 | BI165: 0 | BJ165: 0 | BK165: 0 | BL165: 0 | BM165: 0 | BN165: 0 | BO165: 0 | BP165: 0 | BQ165: 0 | BR165: 0 | BS165: 0 | BU165: 0
B166: GR_W1 | E166: Other Revenue Cost/Income | F166: €'000 | I166: -28467.031 | K166: 0 | L166: 0 | M166: -521.38076 | N166: -1186.8148 | O166: -1206.9398 | P166: 6477.0422 | Q166: -1221.8315 | R166: -1230.7176 | S166: -1228.9225 | T166: -1227.0217 | U166: -1227.0217 | V166: -1225.2303 | W166: -1223.3333 | X166: -1221.5454 | Y166: -1219.6523 | Z166: -1219.6523 | AA166: -1217.868 | AB166: -1212.3246 | AC166: -1214.1979 | AD166: -1212.3124 | AE166: -1212.3124 | AF166: -1210.5352 | AG166: -1203.1408 | AH166: -1196.5669 | AI166: -1194.8111 | AJ166: -1192.9519 | AK166: -1191.1997 | AL166: -1172.906 | AM166: -1153.3035 | AN166: -1151.6077 | AO166: -1149.8122 | AP166: -1148.1198 | AQ166: -750.03956 | AR166: 0 | AS166: 0 | AT166: 0 | AU166: 0 | AV166: 0 | AW166: 0 | AX166: 0 | AY166: 0 | AZ166: 0 | BA166: 0 | BB166: 0 | BC166: 0 | BD166: 0 | BE166: 0 | BF166: 0 | BG166: 0 | BH166: 0 | BI166: 0 | BJ166: 0 | BK166: 0 | BL166: 0 | BM166: 0 | BN166: 0 | BO166: 0 | BP166: 0 | BQ166: 0 | BR166: 0 | BS166: 0 | BU166: 0
E167: GR_W1 | F167: €'000 | I167: 1519799.5 | K167: 0 | L167: 0 | M167: 27573.082 | N167: 42725.333 | O167: 43449.832 | P167: 51411.757 | Q167: 43985.936 | R167: 44305.833 | S167: 44241.211 | T167: 44172.783 | U167: 44172.783 | V167: 44108.29 | W167: 44039.999 | X167: 43975.635 | Y167: 43907.482 | Z167: 43907.482 | AA167: 43843.247 | AB167: 48924.863 | AC167: 55160.899 | AD167: 55256.277 | AE167: 55434.916 | AF167: 55529.641 | AG167: 55334.267 | AH167: 55172.275 | AI167: 55228.781 | AJ167: 55277.42 | AK167: 55327.94 | AL167: 55535.624 | AM167: 55666.922 | AN167: 56663.07 | AO167: 57671.487 | AP167: 58702.565 | AQ167: 39091.881 | AR167: 0 | AS167: 0 | AT167: 0 | AU167: 0 | AV167: 0 | AW167: 0 | AX167: 0 | AY167: 0 | AZ167: 0 | BA167: 0 | BB167: 0 | BC167: 0 | BD167: 0 | BE167: 0 | BF167: 0 | BG167: 0 | BH167: 0 | BI167: 0 | BJ167: 0 | BK167: 0 | BL167: 0 | BM167: 0 | BN167: 0 | BO167: 0 | BP167: 0 | BQ167: 0 | BR167: 0 | BS167: 0 | BU167: 0
B169: GR_W2 | E169: PPA Revenue | I169: 85361.061 | K169: 0 | L169: 0 | M169: 1557.4992 | N169: 5438.8901 | O169: 5531.0222 | P169: 5565.4534 | Q169: 5599.2665 | R169: 5639.9884 | S169: 5631.7684 | T169: 5623.0515 | U169: 5623.0515 | V169: 5614.848 | W169: 5606.1486 | X169: 5597.9615 | Y169: 5589.2795 | Z169: 5589.2795 | AA169: 5581.1088 | AB169: 5572.4444 | AC169: 0 | AD169: 0 | AE169: 0 | AF169: 0 | AG169: 0 | AH169: 0 | AI169: 0 | AJ169: 0 | AK169: 0 | AL169: 0 | AM169: 0 | AN169: 0 | AO169: 0 | AP169: 0 | AQ169: 0 | AR169: 0 | AS169: 0 | AT169: 0 | AU169: 0 | AV169: 0 | AW169: 0 | AX169: 0 | AY169: 0 | AZ169: 0 | BA169: 0 | BB169: 0 | BC169: 0 | BD169: 0 | BE169: 0 | BF169: 0 | BG169: 0 | BH169: 0 | BI169: 0 | BJ169: 0 | BK169: 0 | BL169: 0 | BM169: 0 | BN169: 0 | BO169: 0 | BP169: 0 | BQ169: 0 | BR169: 0 | BS169: 0 | BU169: 0
B170: GR_W2 | E170: Merchant Revenue | F170: €'000 | I170: 108101.03 | K170: 0 | L170: 0 | M170: 3083.177 | N170: 0 | O170: 0 | P170: 0 | Q170: 0 | R170: 0 | S170: 0 | T170: 0 | U170: 0 | V170: 0 | W170: 0 | X170: 0 | Y170: 0 | Z170: 0 | AA170: 0 | AB170: 0 | AC170: 7121.125 | AD170: 7132.056 | AE170: 7153.7281 | AF170: 7164.5654 | AG170: 7122.0101 | AH170: 7080.3486 | AI170: 7086.2493 | AJ170: 7091.1121 | AK170: 7096.2185 | AL170: 7120.23 | AM170: 7134.0133 | AN170: 7258.8788 | AO170: 7385.2563 | AP170: 7514.5082 | AQ170: 4557.5492 | AR170: 0 | AS170: 0 | AT170: 0 | AU170: 0 | AV170: 0 | AW170: 0 | AX170: 0 | AY170: 0 | AZ170: 0 | BA170: 0 | BB170: 0 | BC170: 0 | BD170: 0 | BE170: 0 | BF170: 0 | BG170: 0 | BH170: 0 | BI170: 0 | BJ170: 0 | BK170: 0 | BL170: 0 | BM170: 0 | BN170: 0 | BO170: 0 | BP170: 0 | BQ170: 0 | BR170: 0 | BS170: 0 | BU170: 0
B171: GR_W2 | E171: GoOs Revenue | F171: €'000 | I171: 892.3082 | K171: 0 | L171: 0 | M171: 0 | N171: 0 | O171: 0 | P171: 0 | Q171: 0 | R171: 0 | S171: 0 | T171: 0 | U171: 0 | V171: 0 | W171: 0 | X171: 0 | Y171: 0 | Z171: 0 | AA171: 0 | AB171: 0 | AC171: 55.249386 | AD171: 56.211634 | AE171: 57.279655 | AF171: 58.282472 | AG171: 58.894761 | AH171: 59.522252 | AI171: 60.56424 | AJ171: 61.618861 | AK171: 62.69746 | AL171: 62.90961 | AM171: 63.031389 | AN171: 64.134618 | AO171: 65.251205 | AP171: 66.393188 | AQ171: 40.267468 | AR171: 0 | AS171: 0 | AT171: 0 | AU171: 0 | AV171: 0 | AW171: 0 | AX171: 0 | AY171: 0 | AZ171: 0 | BA171: 0 | BB171: 0 | BC171: 0 | BD171: 0 | BE171: 0 | BF171: 0 | BG171: 0 | BH171: 0 | BI171: 0 | BJ171: 0 | BK171: 0 | BL171: 0 | BM171: 0 | BN171: 0 | BO171: 0 | BP171: 0 | BQ171: 0 | BR171: 0 | BS171: 0 | BU171: 0
B172: GR_W2 | E172: Total Wind / Solar Revenue | F172: €'000 | I172: 194354.4 | K172: 0 | L172: 0 | M172: 4640.6761 | N172: 5438.8901 | O172: 5531.0222 | P172: 5565.4534 | Q172: 5599.2665 | R172: 5639.9884 | S172: 5631.7684 | T172: 5623.0515 | U172: 5623.0515 | V172: 5614.848 | W172: 5606.1486 | X172: 5597.9615 | Y172: 5589.2795 | Z172: 5589.2795 | AA172: 5581.1088 | AB172: 5572.4444 | AC172: 7176.3743 | AD172: 7188.2677 | AE172: 7211.0078 | AF172: 7222.8478 | AG172: 7180.9048 | AH172: 7139.8708 | AI172: 7146.8136 | AJ172: 7152.7309 | AK172: 7158.916 | AL172: 7183.1397 | AM172: 7197.0446 | AN172: 7323.0134 | AO172: 7450.5075 | AP172: 7580.9013 | AQ172: 4597.8166 | AR172: 0 | AS172: 0 | AT172: 0 | AU172: 0 | AV172: 0 | AW172: 0 | AX172: 0 | AY172: 0 | AZ172: 0 | BA172: 0 | BB172: 0 | BC172: 0 | BD172: 0 | BE172: 0 | BF172: 0 | BG172: 0 | BH172: 0 | BI172: 0 | BJ172: 0 | BK172: 0 | BL172: 0 | BM172: 0 | BN172: 0 | BO172: 0 | BP172: 0 | BQ172: 0 | BR172: 0 | BS172: 0 | BU172: 0
B173: GR_W2 | E173: Total BESS Revenue | F173: €'000 | I173: 0 | K173: 0 | L173: 0 | M173: 0 | N173: 0 | O173: 0 | P173: 0 | Q173: 0 | R173: 0 | S173: 0 | T173: 0 | U173: 0 | V173: 0 | W173: 0 | X173: 0 | Y173: 0 | Z173: 0 | AA173: 0 | AB173: 0 | AC173: 0 | AD173: 0 | AE173: 0 | AF173: 0 | AG173: 0 | AH173: 0 | AI173: 0 | AJ173: 0 | AK173: 0 | AL173: 0 | AM173: 0 | AN173: 0 | AO173: 0 | AP173: 0 | AQ173: 0 | AR173: 0 | AS173: 0 | AT173: 0 | AU173: 0 | AV173: 0 | AW173: 0 | AX173: 0 | AY173: 0 | AZ173: 0 | BA173: 0 | BB173: 0 | BC173: 0 | BD173: 0 | BE173: 0 | BF173: 0 | BG173: 0 | BH173: 0 | BI173: 0 | BJ173: 0 | BK173: 0 | BL173: 0 | BM173: 0 | BN173: 0 | BO173: 0 | BP173: 0 | BQ173: 0 | BR173: 0 | BS173: 0 | BU173: 0
B174: GR_W2 | E174: Other Revenue Cost/Income | F174: €'000 | I174: -6462.5453 | K174: 0 | L174: 0 | M174: -220.77905 | N174: -151.08028 | O174: -153.6395 | P174: -154.59593 | Q174: -155.53518 | R174: -156.66635 | S174: -156.43801 | T174: -156.19588 | U174: -156.19588 | V174: -155.968 | W174: -155.72635 | X174: -155.49893 | Y174: -155.25777 | Z174: -155.25777 | AA174: -155.0308 | AB174: -107.70953 | AC174: -283.45419 | AD174: -281.20206 | AE174: -279.21467 | AF174: -277.02567 | AG174: -273.74054 | AH174: -270.51424 | AI174: -268.34289 | AJ174: -266.1836 | AK174: -264.06351 | AL174: -261.75124 | AM174: -259.26329 | AN174: -259.04866 | AO174: -258.82106 | AP174: -258.60687 | AQ174: -199.73759 | AR174: 0 | AS174: 0 | AT174: 0 | AU174: 0 | AV174: 0 | AW174: 0 | AX174: 0 | AY174: 0 | AZ174: 0 | BA174: 0 | BB174: 0 | BC174: 0 | BD174: 0 | BE174: 0 | BF174: 0 | BG174: 0 | BH174: 0 | BI174: 0 | BJ174: 0 | BK174: 0 | BL174: 0 | BM174: 0 | BN174: 0 | BO174: 0 | BP174: 0 | BQ174: 0 | BR174: 0 | BS174: 0 | BU174: 0
E175: GR_W2 | F175: €'000 | I175: 187891.85 | K175: 0 | L175: 0 | M175: 4419.8971 | N175: 5287.8098 | O175: 5377.3827 | P175: 5410.8575 | Q175: 5443.7313 | R175: 5483.3221 | S175: 5475.3304 | T175: 5466.8557 | U175: 5466.8557 | V175: 5458.88 | W175: 5450.4222 | X175: 5442.4625 | Y175: 5434.0218 | Z175: 5434.0218 | AA175: 5426.078 | AB175: 5464.7349 | AC175: 6892.9202 | AD175: 6907.0656 | AE175: 6931.7931 | AF175: 6945.8222 | AG175: 6907.1643 | AH175: 6869.3566 | AI175: 6878.4707 | AJ175: 6886.5473 | AK175: 6894.8525 | AL175: 6921.3884 | AM175: 6937.7814 | AN175: 7063.9648 | AO175: 7191.6864 | AP175: 7322.2945 | AQ175: 4398.079 | AR175: 0 | AS175: 0 | AT175: 0 | AU175: 0 | AV175: 0 | AW175: 0 | AX175: 0 | AY175: 0 | AZ175: 0 | BA175: 0 | BB175: 0 | BC175: 0 | BD175: 0 | BE175: 0 | BF175: 0 | BG175: 0 | BH175: 0 | BI175: 0 | BJ175: 0 | BK175: 0 | BL175: 0 | BM175: 0 | BN175: 0 | BO175: 0 | BP175: 0 | BQ175: 0 | BR175: 0 | BS175: 0 | BU175: 0
B177: GR_W3 | E177: PPA Revenue | I177: 78501.662 | K177: 0 | L177: 0 | M177: 1403.4212 | N177: 5003.3018 | O177: 5088.4838 | P177: 5120.2082 | Q177: 5151.2679 | R177: 5188.7317 | S177: 5181.2179 | T177: 5173.1499 | U177: 5173.1499 | V177: 5165.6512 | W177: 5157.5994 | X177: 5150.1157 | Y177: 5142.08 | Z177: 5142.08 | AA177: 5134.6114 | AB177: 5126.5919 | AC177: 0 | AD177: 0 | AE177: 0 | AF177: 0 | AG177: 0 | AH177: 0 | AI177: 0 | AJ177: 0 | AK177: 0 | AL177: 0 | AM177: 0 | AN177: 0 | AO177: 0 | AP177: 0 | AQ177: 0 | AR177: 0 | AS177: 0 | AT177: 0 | AU177: 0 | AV177: 0 | AW177: 0 | AX177: 0 | AY177: 0 | AZ177: 0 | BA177: 0 | BB177: 0 | BC177: 0 | BD177: 0 | BE177: 0 | BF177: 0 | BG177: 0 | BH177: 0 | BI177: 0 | BJ177: 0 | BK177: 0 | BL177: 0 | BM177: 0 | BN177: 0 | BO177: 0 | BP177: 0 | BQ177: 0 | BR177: 0 | BS177: 0 | BU177: 0
B178: GR_W3 | E178: Merchant Revenue | F178: €'000 | I178: 99519.47 | K178: 0 | L178: 0 | M178: 2842.5344 | N178: 0 | O178: 0 | P178: 0 | Q178: 0 | R178: 0 | S178: 0 | T178: 0 | U178: 0 | V178: 0 | W178: 0 | X178: 0 | Y178: 0 | Z178: 0 | AA178: 0 | AB178: 0 | AC178: 6551.4238 | AD178: 6561.4186 | AE178: 6581.3567 | AF178: 6591.389 | AG178: 6553.0976 | AH178: 6513.8483 | AI178: 6519.3384 | AJ178: 6523.7506 | AK178: 6528.5101 | AL178: 6552.4219 | AM178: 6563.2192 | AN178: 6678.1574 | AO178: 6794.3603 | AP178: 6913.3361 | AQ178: 4251.3078 | AR178: 0 | AS178: 0 | AT178: 0 | AU178: 0 | AV178: 0 | AW178: 0 | AX178: 0 | AY178: 0 | AZ178: 0 | BA178: 0 | BB178: 0 | BC178: 0 | BD178: 0 | BE178: 0 | BF178: 0 | BG178: 0 | BH178: 0 | BI178: 0 | BJ178: 0 | BK178: 0 | BL178: 0 | BM178: 0 | BN178: 0 | BO178: 0 | BP178: 0 | BQ178: 0 | BR178: 0 | BS178: 0 | BU178: 0
B179: GR_W3 | E179: GoOs Revenue | F179: €'000 | I179: 821.45793 | K179: 0 | L179: 0 | M179: 0 | N179: 0 | O179: 0 | P179: 0 | Q179: 0 | R179: 0 | S179: 0 | T179: 0 | U179: 0 | V179: 0 | W179: 0 | X179: 0 | Y179: 0 | Z179: 0 | AA179: 0 | AB179: 0 | AC179: 50.829349 | AD179: 51.714129 | AE179: 52.696697 | AF179: 53.619783 | AG179: 54.190195 | AH179: 54.759863 | AI179: 55.719008 | AJ179: 56.688722 | AK179: 57.681567 | AL179: 57.892835 | AM179: 57.988233 | AN179: 59.003751 | AO179: 60.030441 | AP179: 61.081633 | AQ179: 37.561724 | AR179: 0 | AS179: 0 | AT179: 0 | AU179: 0 | AV179: 0 | AW179: 0 | AX179: 0 | AY179: 0 | AZ179: 0 | BA179: 0 | BB179: 0 | BC179: 0 | BD179: 0 | BE179: 0 | BF179: 0 | BG179: 0 | BH179: 0 | BI179: 0 | BJ179: 0 | BK179: 0 | BL179: 0 | BM179: 0 | BN179: 0 | BO179: 0 | BP179: 0 | BQ179: 0 | BR179: 0 | BS179: 0 | BU179: 0
B180: GR_W3 | E180: Total Wind / Solar Revenue | F180: €'000 | I180: 178842.59 | K180: 0 | L180: 0 | M180: 4245.9556 | N180: 5003.3018 | O180: 5088.4838 | P180: 5120.2082 | Q180: 5151.2679 | R180: 5188.7317 | S180: 5181.2179 | T180: 5173.1499 | U180: 5173.1499 | V180: 5165.6512 | W180: 5157.5994 | X180: 5150.1157 | Y180: 5142.08 | Z180: 5142.08 | AA180: 5134.6114 | AB180: 5126.5919 | AC180: 6602.2532 | AD180: 6613.1328 | AE180: 6634.0534 | AF180: 6645.0088 | AG180: 6607.2878 | AH180: 6568.6082 | AI180: 6575.0574 | AJ180: 6580.4393 | AK180: 6586.1917 | AL180: 6610.3147 | AM180: 6621.2075 | AN180: 6737.1612 | AO180: 6854.3907 | AP180: 6974.4177 | AQ180: 4288.8696 | AR180: 0 | AS180: 0 | AT180: 0 | AU180: 0 | AV180: 0 | AW180: 0 | AX180: 0 | AY180: 0 | AZ180: 0 | BA180: 0 | BB180: 0 | BC180: 0 | BD180: 0 | BE180: 0 | BF180: 0 | BG180: 0 | BH180: 0 | BI180: 0 | BJ180: 0 | BK180: 0 | BL180: 0 | BM180: 0 | BN180: 0 | BO180: 0 | BP180: 0 | BQ180: 0 | BR180: 0 | BS180: 0 | BU180: 0
B181: GR_W3 | E181: Total BESS Revenue | F181: €'000 | I181: 0 | K181: 0 | L181: 0 | M181: 0 | N181: 0 | O181: 0 | P181: 0 | Q181: 0 | R181: 0 | S181: 0 | T181: 0 | U181: 0 | V181: 0 | W181: 0 | X181: 0 | Y181: 0 | Z181: 0 | AA181: 0 | AB181: 0 | AC181: 0 | AD181: 0 | AE181: 0 | AF181: 0 | AG181: 0 | AH181: 0 | AI181: 0 | AJ181: 0 | AK181: 0 | AL181: 0 | AM181: 0 | AN181: 0 | AO181: 0 | AP181: 0 | AQ181: 0 | AR181: 0 | AS181: 0 | AT181: 0 | AU181: 0 | AV181: 0 | AW181: 0 | AX181: 0 | AY181: 0 | AZ181: 0 | BA181: 0 | BB181: 0 | BC181: 0 | BD181: 0 | BE181: 0 | BF181: 0 | BG181: 0 | BH181: 0 | BI181: 0 | BJ181: 0 | BK181: 0 | BL181: 0 | BM181: 0 | BN181: 0 | BO181: 0 | BP181: 0 | BQ181: 0 | BR181: 0 | BS181: 0 | BU181: 0
B182: GR_W3 | E182: Other Revenue Cost/Income | F182: €'000 | I182: -6100.2867 | K182: 0 | L182: 0 | M182: -214.4196 | N182: -138.98061 | O182: -141.34677 | P182: -142.228 | Q182: -143.09078 | R182: -144.13144 | S182: -143.92272 | T182: -143.69861 | U182: -143.69861 | V182: -143.49031 | W182: -143.26665 | X182: -143.05877 | Y182: -142.83556 | Z182: -142.83556 | AA182: -142.62809 | AB182: -99.982254 | AC182: -271.08885 | AD182: -268.85461 | AE182: -266.86722 | AF182: -264.69764 | AG182: -261.53371 | AH182: -258.38779 | AI182: -256.23553 | AJ182: -254.09379 | AK182: -251.99275 | AL182: -249.90346 | AM182: -247.57528 | AN182: -247.3791 | AO182: -247.16844 | AP182: -246.97265 | AQ182: -193.92154 | AR182: 0 | AS182: 0 | AT182: 0 | AU182: 0 | AV182: 0 | AW182: 0 | AX182: 0 | AY182: 0 | AZ182: 0 | BA182: 0 | BB182: 0 | BC182: 0 | BD182: 0 | BE182: 0 | BF182: 0 | BG182: 0 | BH182: 0 | BI182: 0 | BJ182: 0 | BK182: 0 | BL182: 0 | BM182: 0 | BN182: 0 | BO182: 0 | BP182: 0 | BQ182: 0 | BR182: 0 | BS182: 0 | BU182: 0
E183: GR_W3 | F183: €'000 | I183: 172742.3 | K183: 0 | L183: 0 | M183: 4031.5361 | N183: 4864.3212 | O183: 4947.1371 | P183: 4977.9802 | Q183: 5008.1771 | R183: 5044.6002 | S183: 5037.2952 | T183: 5029.4513 | U183: 5029.4513 | V183: 5022.1609 | W183: 5014.3327 | X183: 5007.0569 | Y183: 4999.2445 | Z183: 4999.2445 | AA183: 4991.9833 | AB183: 5026.6096 | AC183: 6331.1643 | AD183: 6344.2781 | AE183: 6367.1862 | AF183: 6380.3111 | AG183: 6345.7541 | AH183: 6310.2204 | AI183: 6318.8219 | AJ183: 6326.3455 | AK183: 6334.199 | AL183: 6360.4112 | AM183: 6373.6322 | AN183: 6489.7821 | AO183: 6607.2223 | AP183: 6727.4451 | AQ183: 4094.948 | AR183: 0 | AS183: 0 | AT183: 0 | AU183: 0 | AV183: 0 | AW183: 0 | AX183: 0 | AY183: 0 | AZ183: 0 | BA183: 0 | BB183: 0 | BC183: 0 | BD183: 0 | BE183: 0 | BF183: 0 | BG183: 0 | BH183: 0 | BI183: 0 | BJ183: 0 | BK183: 0 | BL183: 0 | BM183: 0 | BN183: 0 | BO183: 0 | BP183: 0 | BQ183: 0 | BR183: 0 | BS183: 0 | BU183: 0
B185: GR_W4 | E185: PPA Revenue | I185: 106795.04 | K185: 0 | L185: 0 | M185: 0 | N185: 0 | O185: 3354.3345 | P185: 7050.1083 | Q185: 7129.7782 | R185: 7181.6311 | S185: 7170.9564 | T185: 7160.0647 | U185: 7160.0647 | V185: 7149.4114 | W185: 7138.5415 | X185: 7127.9095 | Y185: 7117.0614 | Z185: 7117.0614 | AA185: 7106.4508 | AB185: 7095.6245 | AC185: 7085.0352 | AD185: 3651.0104 | AE185: 0 | AF185: 0 | AG185: 0 | AH185: 0 | AI185: 0 | AJ185: 0 | AK185: 0 | AL185: 0 | AM185: 0 | AN185: 0 | AO185: 0 | AP185: 0 | AQ185: 0 | AR185: 0 | AS185: 0 | AT185: 0 | AU185: 0 | AV185: 0 | AW185: 0 | AX185: 0 | AY185: 0 | AZ185: 0 | BA185: 0 | BB185: 0 | BC185: 0 | BD185: 0 | BE185: 0 | BF185: 0 | BG185: 0 | BH185: 0 | BI185: 0 | BJ185: 0 | BK185: 0 | BL185: 0 | BM185: 0 | BN185: 0 | BO185: 0 | BP185: 0 | BQ185: 0 | BR185: 0 | BS185: 0 | BU185: 0
B186: GR_W4 | E186: Merchant Revenue | F186: €'000 | I186: 145941.24 | K186: 0 | L186: 0 | M186: 0 | N186: 0 | O186: 0 | P186: 0 | Q186: 0 | R186: 0 | S186: 0 | T186: 0 | U186: 0 | V186: 0 | W186: 0 | X186: 0 | Y186: 0 | Z186: 0 | AA186: 0 | AB186: 0 | AC186: 0 | AD186: 4585.6263 | AE186: 9505.1882 | AF186: 9519.3104 | AG186: 9527.7476 | AH186: 9550.2292 | AI186: 9488.9147 | AJ186: 9421.99 | AK186: 9428.4998 | AL186: 9592.9455 | AM186: 9775.2115 | AN186: 9800.2464 | AO186: 9812.8206 | AP186: 9984.2662 | AQ186: 10158.374 | AR186: 10351.383 | AS186: 5438.4922 | AT186: 0 | AU186: 0 | AV186: 0 | AW186: 0 | AX186: 0 | AY186: 0 | AZ186: 0 | BA186: 0 | BB186: 0 | BC186: 0 | BD186: 0 | BE186: 0 | BF186: 0 | BG186: 0 | BH186: 0 | BI186: 0 | BJ186: 0 | BK186: 0 | BL186: 0 | BM186: 0 | BN186: 0 | BO186: 0 | BP186: 0 | BQ186: 0 | BR186: 0 | BS186: 0 | BU186: 0
B187: GR_W4 | E187: GoOs Revenue | F187: €'000 | I187: 1256.9262 | K187: 0 | L187: 0 | M187: 0 | N187: 0 | O187: 0 | P187: 0 | Q187: 0 | R187: 0 | S187: 0 | T187: 0 | U187: 0 | V187: 0 | W187: 0 | X187: 0 | Y187: 0 | Z187: 0 | AA187: 0 | AB187: 0 | AC187: 0 | AD187: 36.141828 | AE187: 76.107715 | AF187: 77.437906 | AG187: 78.78877 | AH187: 80.285757 | AI187: 81.099166 | AJ187: 81.873236 | AK187: 83.303944 | AL187: 84.756876 | AM187: 86.367257 | AN187: 86.588449 | AO187: 86.699546 | AP187: 88.214325 | AQ187: 89.752623 | AR187: 91.457923 | AS187: 48.050894 | AT187: 0 | AU187: 0 | AV187: 0 | AW187: 0 | AX187: 0 | AY187: 0 | AZ187: 0 | BA187: 0 | BB187: 0 | BC187: 0 | BD187: 0 | BE187: 0 | BF187: 0 | BG187: 0 | BH187: 0 | BI187: 0 | BJ187: 0 | BK187: 0 | BL187: 0 | BM187: 0 | BN187: 0 | BO187: 0 | BP187: 0 | BQ187: 0 | BR187: 0 | BS187: 0 | BU187: 0
...

Sheet NBO Case Charts
B2: Charts - NBO Case
P6: Date | W6: =+DATE(W7,12,31) -> 46022 | X6: =+DATE(X7,12,31) -> 46387 | Y6: =+DATE(Y7,12,31) -> 46752 | Z6: =+DATE(Z7,12,31) -> 47118 | AA6: =+DATE(AA7,12,31) -> 47483 | AB6: =+DATE(AB7,12,31) -> 47848 | AC6: =+DATE(AC7,12,31) -> 48213 | AD6: =+DATE(AD7,12,31) -> 48579 | ... BQ6: =+DATE(BQ7,12,31) -> 62823
P7: Year | W7: 2025 | X7: =W7+1 -> 2026 | Y7: =X7+1 -> 2027 | Z7: =Y7+1 -> 2028 | AA7: =Z7+1 -> 2029 | AB7: =AA7+1 -> 2030 | AC7: =AB7+1 -> 2031 | AD7: =AC7+1 -> 2032 | AE7: =AD7+1 -> 2033 | ... BQ7: =BP7+1 -> 2071
B10: =+MAX($B$6:B9)+1 -> 1 | C10: Electricity prices
C12: =+MAX($B$10:C11)+0.1 -> 1.1 | D12: Greece
P14: Electricity price - Greece | R14: €/MWh | S14: =IFERROR(AVERAGE(X14:BQ14),0) -> 0 | V14: Input
C33: =+MAX($B$10:C32)+0.1 -> 1.2 | D33: Italy
P35: Electricity price - Italy | R35: €/MWh | S35: =IFERROR(AVERAGE(X35:BQ35),0) -> 0 | V35: Input
B55: =+MAX($B$6:B54)+1 -> 2 | C55: Greek portfolio
C57: =+MAX($B$10:C56)+0.1 -> 2.1 | D57: Production
P59: Vermio North | Q59: GR_W1 | R59: GWh | S59: =SUM(X59:BQ59) -> 18134.357 | X59: ='NBO Case Outputs'!M90/1000 -> 313.95731 | Y59: ='NBO Case Outputs'!N90/1000 -> 593.4074 | Z59: ='NBO Case Outputs'!O90/1000 -> 603.46988 | AA59: ='NBO Case Outputs'!P90/1000 -> 607.22588 | AB59: ='NBO Case Outputs'!Q90/1000 -> 610.91577 | AC59: ='NBO Case Outputs'!R90/1000 -> 615.3588 | AD59: ='NBO Case Outputs'!S90/1000 -> 614.46126 | AE59: ='NBO Case Outputs'!T90/1000 -> 613.51087 | ... BQ59: ='NBO Case Outputs'!BF90/1000 -> 0
P60: Vermio South | Q60: GR_W2 | R60: GWh | S60: =SUM(X60:BQ60) -> 2309.0609 | X60: ='NBO Case Outputs'!M92/1000 -> 48.551014 | Y60: ='NBO Case Outputs'!N92/1000 -> 75.54014 | Z60: ='NBO Case Outputs'!O92/1000 -> 76.819752 | AA60: ='NBO Case Outputs'!P92/1000 -> 77.297964 | AB60: ='NBO Case Outputs'!Q92/1000 -> 77.76759 | AC60: ='NBO Case Outputs'!R92/1000 -> 78.333173 | AD60: ='NBO Case Outputs'!S92/1000 -> 78.219005 | AE60: ='NBO Case Outputs'!T92/1000 -> 78.097938 | ... BQ60: ='NBO Case Outputs'!BF92/1000 -> 0
P61: Mesokorfi | Q61: GR_W3 | R61: GWh | S61: =SUM(X61:BQ61) -> 2124.5416 | X61: ='NBO Case Outputs'!M94/1000 -> 44.310003 | Y61: ='NBO Case Outputs'!N94/1000 -> 69.490303 | Z61: ='NBO Case Outputs'!O94/1000 -> 70.673387 | AA61: ='NBO Case Outputs'!P94/1000 -> 71.114002 | AB61: ='NBO Case Outputs'!Q94/1000 -> 71.545388 | AC61: ='NBO Case Outputs'!R94/1000 -> 72.065718 | AD61: ='NBO Case Outputs'!S94/1000 -> 71.96136 | AE61: ='NBO Case Outputs'!T94/1000 -> 71.849304 | ... BQ61: ='NBO Case Outputs'!BF94/1000 -> 0
P62: Koukouras | Q62: GR_W4 | R62: GWh | S62: =SUM(X62:BQ62) -> 3043.3005 | X62: ='NBO Case Outputs'!M96/1000 -> 0 | Y62: ='NBO Case Outputs'!N96/1000 -> 0 | Z62: ='NBO Case Outputs'!O96/1000 -> 48.613544 | AA62: ='NBO Case Outputs'!P96/1000 -> 102.17548 | AB62: ='NBO Case Outputs'!Q96/1000 -> 103.33012 | AC62: ='NBO Case Outputs'!R96/1000 -> 104.08161 | AD62: ='NBO Case Outputs'!S96/1000 -> 103.9269 | AE62: ='NBO Case Outputs'!T96/1000 -> 103.76905 | ... BQ62: ='NBO Case Outputs'!BF96/1000 -> 0
P63: Panachaiko III | Q63: GR_W5 | R63: GWh | S63: =SUM(X63:BQ63) -> 1374.8366 | X63: ='NBO Case Outputs'!M98/1000 -> 0 | Y63: ='NBO Case Outputs'!N98/1000 -> 0 | Z63: ='NBO Case Outputs'!O98/1000 -> 18.922014 | AA63: ='NBO Case Outputs'!P98/1000 -> 39.739233 | AB63: ='NBO Case Outputs'!Q98/1000 -> 39.844129 | AC63: ='NBO Case Outputs'!R98/1000 -> 39.884173 | AD63: ='NBO Case Outputs'!S98/1000 -> 39.944881 | AE63: ='NBO Case Outputs'!T98/1000 -> 39.844249 | ... BQ63: ='NBO Case Outputs'!BF98/1000 -> 0
P64: Total production | R64: GWh | S64: =SUM(X64:BQ64) -> 26986.096 | X64: =SUM(X59:X63) -> 406.81833 | Y64: =SUM(Y59:Y63) -> 738.43785 | Z64: =SUM(Z59:Z63) -> 818.49858 | AA64: =SUM(AA59:AA63) -> 897.55256 | AB64: =SUM(AB59:AB63) -> 903.403 | AC64: =SUM(AC59:AC63) -> 909.72347 | AD64: =SUM(AD59:AD63) -> 908.51341 | AE64: =SUM(AE59:AE63) -> 907.07142 | ... BQ64: =SUM(BQ59:BQ63) -> 0
C78: =+MAX($B$10:C77)+0.1 -> 2.2 | D78: Revenues
P80: Vermio North | Q80: GR_W1 | R80: €m | S80: =SUM(X80:BQ80) -> 670.57986 | X80: ='NBO Case Outputs'!M161/1000 -> 14.482031 | Y80: ='NBO Case Outputs'!N161/1000 -> 43.912148 | Z80: ='NBO Case Outputs'!O161/1000 -> 44.656771 | AA80: ='NBO Case Outputs'!P161/1000 -> 44.934715 | AB80: ='NBO Case Outputs'!Q161/1000 -> 45.207767 | AC80: ='NBO Case Outputs'!R161/1000 -> 45.536551 | AD80: ='NBO Case Outputs'!S161/1000 -> 45.470133 | AE80: ='NBO Case Outputs'!T161/1000 -> 45.399805 | ... BQ80: ='NBO Case Outputs'!BF161/1000 -> 0
P81: Vermio South | Q81: GR_W2 | R81: €m | S81: =SUM(X81:BQ81) -> 85.361061 | X81: ='NBO Case Outputs'!M169/1000 -> 1.5574992 | Y81: ='NBO Case Outputs'!N169/1000 -> 5.4388901 | Z81: ='NBO Case Outputs'!O169/1000 -> 5.5310222 | AA81: ='NBO Case Outputs'!P169/1000 -> 5.5654534 | AB81: ='NBO Case Outputs'!Q169/1000 -> 5.5992665 | AC81: ='NBO Case Outputs'!R169/1000 -> 5.6399884 | AD81: ='NBO Case Outputs'!S169/1000 -> 5.6317684 | AE81: ='NBO Case Outputs'!T169/1000 -> 5.6230515 | ... BQ81: ='NBO Case Outputs'!BF169/1000 -> 0
P82: Mesokorfi | Q82: GR_W3 | R82: €m | S82: =SUM(X82:BQ82) -> 78.501662 | X82: ='NBO Case Outputs'!M177/1000 -> 1.4034212 | Y82: ='NBO Case Outputs'!N177/1000 -> 5.0033018 | Z82: ='NBO Case Outputs'!O177/1000 -> 5.0884838 | AA82: ='NBO Case Outputs'!P177/1000 -> 5.1202082 | AB82: ='NBO Case Outputs'!Q177/1000 -> 5.1512679 | AC82: ='NBO Case Outputs'!R177/1000 -> 5.1887317 | AD82: ='NBO Case Outputs'!S177/1000 -> 5.1812179 | AE82: ='NBO Case Outputs'!T177/1000 -> 5.1731499 | ... BQ82: ='NBO Case Outputs'!BF177/1000 -> 0
P83: Koukouras | Q83: GR_W4 | R83: €m | S83: =SUM(X83:BQ83) -> 106.79504 | X83: ='NBO Case Outputs'!M185/1000 -> 0 | Y83: ='NBO Case Outputs'!N185/1000 -> 0 | Z83: ='NBO Case Outputs'!O185/1000 -> 3.3543345 | AA83: ='NBO Case Outputs'!P185/1000 -> 7.0501083 | AB83: ='NBO Case Outputs'!Q185/1000 -> 7.1297782 | AC83: ='NBO Case Outputs'!R185/1000 -> 7.1816311 | AD83: ='NBO Case Outputs'!S185/1000 -> 7.1709564 | AE83: ='NBO Case Outputs'!T185/1000 -> 7.1600647 | ... BQ83: ='NBO Case Outputs'!BF185/1000 -> 0
P84: Panachaiko III | Q84: GR_W5 | R84: €m | S84: =SUM(X84:BQ84) -> 0 | X84: ='NBO Case Outputs'!M193/1000 -> 0 | Y84: ='NBO Case Outputs'!N193/1000 -> 0 | Z84: ='NBO Case Outputs'!O193/1000 -> 0 | AA84: ='NBO Case Outputs'!P193/1000 -> 0 | AB84: ='NBO Case Outputs'!Q193/1000 -> 0 | AC84: ='NBO Case Outputs'!R193/1000 -> 0 | AD84: ='NBO Case Outputs'!S193/1000 -> 0 | AE84: ='NBO Case Outputs'!T193/1000 -> 0 | ... BQ84: ='NBO Case Outputs'!BF193/1000 -> 0
P85: PPA revenue | R85: €m | S85: =SUM(X85:BQ85) -> 941.23763 | X85: =SUM(X80:X84) -> 17.442952 | Y85: =SUM(Y80:Y84) -> 54.35434 | Z85: =SUM(Z80:Z84) -> 58.630612 | AA85: =SUM(AA80:AA84) -> 62.670485 | AB85: =SUM(AB80:AB84) -> 63.08808 | AC85: =SUM(AC80:AC84) -> 63.546902 | AD85: =SUM(AD80:AD84) -> 63.454076 | AE85: =SUM(AE80:AE84) -> 63.356071 | ... BQ85: =SUM(BQ80:BQ84) -> 0
P86: Vermio North | Q86: GR_W1 | R86: €m | S86: =SUM(X86:BQ86) -> 870.35841 | X86: ='NBO Case Outputs'!M162/1000 -> 13.544243 | Y86: ='NBO Case Outputs'!N162/1000 -> 0 | Z86: ='NBO Case Outputs'!O162/1000 -> 0 | AA86: ='NBO Case Outputs'!P162/1000 -> 0 | AB86: ='NBO Case Outputs'!Q162/1000 -> 0 | AC86: ='NBO Case Outputs'!R162/1000 -> 0 | AD86: ='NBO Case Outputs'!S162/1000 -> 0 | AE86: ='NBO Case Outputs'!T162/1000 -> 0 | ... BQ86: ='NBO Case Outputs'!BF162/1000 -> 0
P87: Vermio South | Q87: GR_W2 | R87: €m | S87: =SUM(X87:BQ87) -> 108.10103 | X87: ='NBO Case Outputs'!M170/1000 -> 3.083177 | Y87: ='NBO Case Outputs'!N170/1000 -> 0 | Z87: ='NBO Case Outputs'!O170/1000 -> 0 | AA87: ='NBO Case Outputs'!P170/1000 -> 0 | AB87: ='NBO Case Outputs'!Q170/1000 -> 0 | AC87: ='NBO Case Outputs'!R170/1000 -> 0 | AD87: ='NBO Case Outputs'!S170/1000 -> 0 | AE87: ='NBO Case Outputs'!T170/1000 -> 0 | ... BQ87: ='NBO Case Outputs'!BF170/1000 -> 0
P88: Mesokorfi | Q88: GR_W3 | R88: €m | S88: =SUM(X88:BQ88) -> 99.51947 | X88: ='NBO Case Outputs'!M178/1000 -> 2.8425344 | Y88: ='NBO Case Outputs'!N178/1000 -> 0 | Z88: ='NBO Case Outputs'!O178/1000 -> 0 | AA88: ='NBO Case Outputs'!P178/1000 -> 0 | AB88: ='NBO Case Outputs'!Q178/1000 -> 0 | AC88: ='NBO Case Outputs'!R178/1000 -> 0 | AD88: ='NBO Case Outputs'!S178/1000 -> 0 | AE88: ='NBO Case Outputs'!T178/1000 -> 0 | ... BQ88: ='NBO Case Outputs'!BF178/1000 -> 0
P89: Koukouras | Q89: GR_W4 | R89: €m | S89: =SUM(X89:BQ89) -> 145.94124 | X89: ='NBO Case Outputs'!M186/1000 -> 0 | Y89: ='NBO Case Outputs'!N186/1000 -> 0 | Z89: ='NBO Case Outputs'!O186/1000 -> 0 | AA89: ='NBO Case Outputs'!P186/1000 -> 0 | AB89: ='NBO Case Outputs'!Q186/1000 -> 0 | AC89: ='NBO Case Outputs'!R186/1000 -> 0 | AD89: ='NBO Case Outputs'!S186/1000 -> 0 | AE89: ='NBO Case Outputs'!T186/1000 -> 0 | ... BQ89: ='NBO Case Outputs'!BF186/1000 -> 0
P90: Panachaiko III | Q90: GR_W5 | R90: €m | S90: =SUM(X90:BQ90) -> 133.20787 | X90: ='NBO Case Outputs'!M194/1000 -> 0 | Y90: ='NBO Case Outputs'!N194/1000 -> 0 | Z90: ='NBO Case Outputs'!O194/1000 -> 1.7703361 | AA90: ='NBO Case Outputs'!P194/1000 -> 3.7338218 | AB90: ='NBO Case Outputs'!Q194/1000 -> 3.649906 | AC90: ='NBO Case Outputs'!R194/1000 -> 3.4703644 | AD90: ='NBO Case Outputs'!S194/1000 -> 3.4954569 | AE90: ='NBO Case Outputs'!T194/1000 -> 3.5063766 | ... BQ90: ='NBO Case Outputs'!BF194/1000 -> 0
P91: Merchant revenue | R91: €m | S91: =SUM(X91:BQ91) -> 1357.128 | X91: =SUM(X86:X90) -> 19.469955 | Y91: =SUM(Y86:Y90) -> 0 | Z91: =SUM(Z86:Z90) -> 1.7703361 | AA91: =SUM(AA86:AA90) -> 3.7338218 | AB91: =SUM(AB86:AB90) -> 3.649906 | AC91: =SUM(AC86:AC90) -> 3.4703644 | AD91: =SUM(AD86:AD90) -> 3.4954569 | AE91: =SUM(AE86:AE90) -> 3.5063766 | ... BQ91: =SUM(BQ86:BQ90) -> 0
P92: Vermio North | Q92: GR_W1 | R92: €m | S92: =SUM(X92:BQ92) -> 7.3282704 | X92: ='NBO Case Outputs'!M163/1000 -> 0.068188622 | Y92: ='NBO Case Outputs'!N163/1000 -> 0 | Z92: ='NBO Case Outputs'!O163/1000 -> 0 | AA92: ='NBO Case Outputs'!P163/1000 -> 0 | AB92: ='NBO Case Outputs'!Q163/1000 -> 0 | AC92: ='NBO Case Outputs'!R163/1000 -> 0 | AD92: ='NBO Case Outputs'!S163/1000 -> 0 | AE92: ='NBO Case Outputs'!T163/1000 -> 0 | ... BQ92: ='NBO Case Outputs'!BF163/1000 -> 0
P93: Vermio South | Q93: GR_W2 | R93: €m | S93: =SUM(X93:BQ93) -> 0.8923082 | X93: ='NBO Case Outputs'!M171/1000 -> 0 | Y93: ='NBO Case Outputs'!N171/1000 -> 0 | Z93: ='NBO Case Outputs'!O171/1000 -> 0 | AA93: ='NBO Case Outputs'!P171/1000 -> 0 | AB93: ='NBO Case Outputs'!Q171/1000 -> 0 | AC93: ='NBO Case Outputs'!R171/1000 -> 0 | AD93: ='NBO Case Outputs'!S171/1000 -> 0 | AE93: ='NBO Case Outputs'!T171/1000 -> 0 | ... BQ93: ='NBO Case Outputs'!BF171/1000 -> 0
P94: Mesokorfi | Q94: GR_W3 | R94: €m | S94: =SUM(X94:BQ94) -> 0.82145793 | X94: ='NBO Case Outputs'!M179/1000 -> 0 | Y94: ='NBO Case Outputs'!N179/1000 -> 0 | Z94: ='NBO Case Outputs'!O179/1000 -> 0 | AA94: ='NBO Case Outputs'!P179/1000 -> 0 | AB94: ='NBO Case Outputs'!Q179/1000 -> 0 | AC94: ='NBO Case Outputs'!R179/1000 -> 0 | AD94: ='NBO Case Outputs'!S179/1000 -> 0 | AE94: ='NBO Case Outputs'!T179/1000 -> 0 | ... BQ94: ='NBO Case Outputs'!BF179/1000 -> 0
P95: Koukouras | Q95: GR_W4 | R95: €m | S95: =SUM(X95:BQ95) -> 1.2569262 | X95: ='NBO Case Outputs'!M187/1000 -> 0 | Y95: ='NBO Case Outputs'!N187/1000 -> 0 | Z95: ='NBO Case Outputs'!O187/1000 -> 0 | AA95: ='NBO Case Outputs'!P187/1000 -> 0 | AB95: ='NBO Case Outputs'!Q187/1000 -> 0 | AC95: ='NBO Case Outputs'!R187/1000 -> 0 | AD95: ='NBO Case Outputs'!S187/1000 -> 0 | AE95: ='NBO Case Outputs'!T187/1000 -> 0 | ... BQ95: ='NBO Case Outputs'!BF187/1000 -> 0
P96: Panachaiko III | Q96: GR_W5 | R96: €m | S96: =SUM(X96:BQ96) -> 0.78169186 | X96: ='NBO Case Outputs'!M195/1000 -> 0 | Y96: ='NBO Case Outputs'!N195/1000 -> 0 | Z96: ='NBO Case Outputs'!O195/1000 -> 0.020787821 | AA96: ='NBO Case Outputs'!P195/1000 -> 0 | AB96: ='NBO Case Outputs'!Q195/1000 -> 0 | AC96: ='NBO Case Outputs'!R195/1000 -> 0 | AD96: ='NBO Case Outputs'!S195/1000 -> 0 | AE96: ='NBO Case Outputs'!T195/1000 -> 0 | ... BQ96: ='NBO Case Outputs'!BF195/1000 -> 0
P97: GoOs revenue | R97: €m | S97: =SUM(X97:BQ97) -> 11.080655 | X97: =SUM(X92:X96) -> 0.068188622 | Y97: =SUM(Y92:Y96) -> 0 | Z97: =SUM(Z92:Z96) -> 0.020787821 | AA97: =SUM(AA92:AA96) -> 0 | AB97: =SUM(AB92:AB96) -> 0 | AC97: =SUM(AC92:AC96) -> 0 | AD97: =SUM(AD92:AD96) -> 0 | AE97: =SUM(AE92:AE96) -> 0 | ... BQ97: =SUM(BQ92:BQ96) -> 0
P98: Vermio North | Q98: GR_W1 | R98: €m | S98: =SUM(X98:BQ98) -> -28.467031 | X98: ='NBO Case Outputs'!M166/1000 -> -0.52138076 | Y98: ='NBO Case Outputs'!N166/1000 -> -1.1868148 | Z98: ='NBO Case Outputs'!O166/1000 -> -1.2069398 | AA98: ='NBO Case Outputs'!P166/1000 -> 6.4770422 | AB98: ='NBO Case Outputs'!Q166/1000 -> -1.2218315 | AC98: ='NBO Case Outputs'!R166/1000 -> -1.2307176 | AD98: ='NBO Case Outputs'!S166/1000 -> -1.2289225 | AE98: ='NBO Case Outputs'!T166/1000 -> -1.2270217 | ... BQ98: ='NBO Case Outputs'!BF166/1000 -> 0
P99: Vermio South | Q99: GR_W2 | R99: €m | S99: =SUM(X99:BQ99) -> -6.4625453 | X99: ='NBO Case Outputs'!M174/1000 -> -0.22077905 | Y99: ='NBO Case Outputs'!N174/1000 -> -0.15108028 | Z99: ='NBO Case Outputs'!O174/1000 -> -0.1536395 | AA99: ='NBO Case Outputs'!P174/1000 -> -0.15459593 | AB99: ='NBO Case Outputs'!Q174/1000 -> -0.15553518 | AC99: ='NBO Case Outputs'!R174/1000 -> -0.15666635 | AD99: ='NBO Case Outputs'!S174/1000 -> -0.15643801 | AE99: ='NBO Case Outputs'!T174/1000 -> -0.15619588 | ... BQ99: ='NBO Case Outputs'!BF174/1000 -> 0
P100: Mesokorfi | Q100: GR_W3 | R100: €m | S100: =SUM(X100:BQ100) -> -6.1002867 | X100: ='NBO Case Outputs'!M182/1000 -> -0.2144196 | Y100: ='NBO Case Outputs'!N182/1000 -> -0.13898061 | Z100: ='NBO Case Outputs'!O182/1000 -> -0.14134677 | AA100: ='NBO Case Outputs'!P182/1000 -> -0.142228 | AB100: ='NBO Case Outputs'!Q182/1000 -> -0.14309078 | AC100: ='NBO Case Outputs'!R182/1000 -> -0.14413144 | AD100: ='NBO Case Outputs'!S182/1000 -> -0.14392272 | AE100: ='NBO Case Outputs'!T182/1000 -> -0.14369861 | ... BQ100: ='NBO Case Outputs'!BF182/1000 -> 0
P101: Koukouras | Q101: GR_W4 | R101: €m | S101: =SUM(X101:BQ101) -> 0.029668031 | X101: ='NBO Case Outputs'!M190/1000 -> 0 | Y101: ='NBO Case Outputs'!N190/1000 -> 0 | Z101: ='NBO Case Outputs'!O190/1000 -> -0.097227088 | AA101: ='NBO Case Outputs'!P190/1000 -> -0.20435096 | AB101: ='NBO Case Outputs'!Q190/1000 -> -0.20666024 | AC101: ='NBO Case Outputs'!R190/1000 -> 7.7099668 | AD101: ='NBO Case Outputs'!S190/1000 -> -0.20785381 | AE101: ='NBO Case Outputs'!T190/1000 -> -0.20753811 | ... BQ101: ='NBO Case Outputs'!BF190/1000 -> 0
P102: Panachaiko III | Q102: GR_W5 | R102: €m | S102: =SUM(X102:BQ102) -> -7.260584 | X102: ='NBO Case Outputs'!M198/1000 -> 0 | Y102: ='NBO Case Outputs'!N198/1000 -> 0 | Z102: ='NBO Case Outputs'!O198/1000 -> -0.12300621 | AA102: ='NBO Case Outputs'!P198/1000 -> -0.24733889 | AB102: ='NBO Case Outputs'!Q198/1000 -> -0.24029263 | AC102: ='NBO Case Outputs'!R198/1000 -> -0.22947473 | AD102: ='NBO Case Outputs'!S198/1000 -> -0.22764214 | AE102: ='NBO Case Outputs'!T198/1000 -> -0.22550624 | ... BQ102: ='NBO Case Outputs'!BF198/1000 -> 0
P103: Other revenue / (cost) | R103: €m | S103: =SUM(X103:BQ103) -> -48.260779 | X103: =SUM(X98:X102) -> -0.9565794 | Y103: =SUM(Y98:Y102) -> -1.4768757 | Z103: =SUM(Z98:Z102) -> -1.7221593 | AA103: =SUM(AA98:AA102) -> 5.7285285 | AB103: =SUM(AB98:AB102) -> -1.9674104 | AC103: =SUM(AC98:AC102) -> 5.9489767 | AD103: =SUM(AD98:AD102) -> -1.9647792 | AE103: =SUM(AE98:AE102) -> -1.9599606 | ... BQ103: =SUM(BQ98:BQ102) -> 0
